[
    {
        "dosya": "27.08.2025_Gelen Fatura (1)\\01.04.2023-MNT2023000000088.pdf",
        "analiz_zamani": "2025-08-28 09:44:34",
        "ocr_istatistikleri": {
            "ortalama_guven_skoru": "63.74%",
            "toplam_kelime": 309,
            "gecerli_kelime": 217,
            "ham_metin_uzunlugu": 1301,
            "ham_metin": "Beşler Market Gümbet Paket e Te eae aC =f Adnan Menderes No:29 e 23 Bodrum/ Mugla 5 ii Vergi Dairesi: Bodrum Bes pr VKN: 9000068418 NENALL ei MERSISNO: 12345669-111 ate ten TICARETSICILNO: 12345669-111 — SAYIN Akkaya Yazilim Özelleştirme No: vide Kapı No:45 senaryo: Kapı Fatura Tipi ‘(SATIS EEE E-Posta: bodurum88@hotmail.com MNT2023000000088 Vergi Dairesi: Bodrum Fatura Tarihi: VKN: 9000068418 Düzenleme Tarihi: (o (01-04-2023 am am m 18:27:00 ETTN: cd6a6a13-83f1-45fd-8f58-1ac0eb358826 . ee İskonto | İskonto | KDV wy . . a [dam | ovr > (es Regal 12 Years 100 875,00000000 TL) 960,00) 0,00 TL|%18,00) 315,00 4.750,00 TL e ps Regal 12 Years 35 360,00000000 TL) (| 960,00) 0,00 TL] %18,00] 324,00 1.800,00 TL 0 © |Chivas Regal 12 Years 3L_| 10Adet 3.200,00000000 TL %0,00| 0,00 TL] %18,00| _5.760,00 mT sid 32.000,00 TL 110 © |Chivas Regal 12 Years 50¢ 475,00000000 TL) | 960,00) Oo 0,00 TL| %18,00 | Regal 13 Years 699,00000000 TL) (| 960,00) 0,00 TL|%18,00) 12582 ff 699,00 TL 112 _ |Chivas Regal 18 Years 1.650,00000000 TL %0,00| 0,00 TL] %18,00 1.650,00 TL Mal Hizmet Toplam Tutarı 38.374,00 TL Toplam İskonto 000TL Hesaplanan KDV(%18) 13.814,64 TL Vergiler Dahil Toplam Tutar | 45.281,32 TL Ödenecek Tutar | 45.28132TL Not 2 . oe 2 Yalnız # KIRK BEŞ BİN İKİ YÜZ SEKSEN BİR Lira OTUZ İKİ Kuruş #"
        },
        "regex": {
            "tarih": [
                "01-04-2023"
            ],
            "para": [
                "960,00",
                "0,00 TL",
                "18,00",
                "315,00",
                "4.750,00 TL",
                "324,00",
                "1.800,00 TL",
                "0,00",
                "760,00",
                "32.000,00 TL"
            ],
            "iban": [],
            "fatura_no": [],
            "vergi_no": [
                "9000068418"
            ],
            "tc_no": [],
            "telefon": [],
            "email": [
                "bodurum88@hotmail.com"
            ],
            "fatura_tipi": [],
            "kdv_orani": [],
            "ettn": [
                "cd6a6a13-83f1-45fd-8f58-1ac0eb358826"
            ],
            "mersis_no": [],
            "ticaret_sicil": [
                "12345669"
            ],
            "musteri_no": [],
            "mal_hizmet_kodu": [],
            "alici_ad_soyad": [
                "Akkaya Yazilim"
            ],
            "alici_adres": [],
            "urun_aciklama": [],
            "urun_miktar": [
                "10"
            ],
            "birim_fiyat": [
                "875,00000000 TL",
                "360,00000000 TL",
                "475,00000000 TL",
                "699,00000000 TL"
            ],
            "odeme_sekli": [],
            "kargo_bilgisi": [],
            "siparis_no": [],
            "fatura_tarihi": [],
            "duzenleme_saati": [],
            "satici_vkn": [],
            "alici_vkn": [],
            "odenecek_tutar": [],
            "doviz_kuru": [],
            "para_birimi": [
                "TL"
            ]
        },
        "structured": {
            "alici_firma_unvani": "Akkaya Yazilim Özelleştirme No",
            "alici_email": "bodurum88@hotmail.com",
            "fatura_numarasi": "MNT2023000000088",
            "ettn": "cd6a6a13-83f1-45fd-8f58-1ac0eb358826",
            "genel_toplam": "38.374,00",
            "tarih": "01-04-2023",
            "para": "960,00",
            "vergi_no": "9000068418",
            "email": "bodurum88@hotmail.com",
            "ticaret_sicil": "12345669",
            "alici_ad_soyad": "Akkaya Yazilim",
            "urun_miktar": "10",
            "kalemler": [
                {
                    "tutar": "13.814,64 KDV(%18)",
                    "aciklama": "Hesaplanan",
                    "tutar_num": 13814.6418
                },
                {
                    "tutar": "Tutar Toplam",
                    "aciklama": "Dahil Vergiler"
                }
            ],
            "fatura_tarihi": "01-04-2023"
        }
    },
    {
        "dosya": "27.08.2025_Gelen Fatura (1)\\01.04.2023-MNT2023000000089.pdf",
        "analiz_zamani": "2025-08-28 09:44:34",
        "ocr_istatistikleri": {
            "ortalama_guven_skoru": "62.98%",
            "toplam_kelime": 196,
            "gecerli_kelime": 136,
            "ham_metin_uzunlugu": 816,
            "ham_metin": "Beşler Market Gümbet Paket Be Soa N pis : tat Adnan Menderes No:29 EEL PrN, es Vergi Dairesi: Bodrum | e ah = x VKN: 9000068418 NALI MERSISNO: 12345669-111 ei A TICARETSICILNO: 12345669-111 a ri en SAYIN Akkaya Yazılım Özelleştirme No: TR1.2 yz Kapı Nos Senaryo: apı No: — aya Fatura Tip: — —|sarış E-Posta: bodurum88@hotmail.com Fatura No: “| MINT2023000000089 Vergi Dairesi: Bodrum 01-04-2023 | VKN: 9000068418 Düzenleme Tarihi: (01-04-2023 18:27:00 88267d12-82bc-429d-a2fe-739c697b0e58 WO Te fa [chives Regal 12 Years 35 360,00000000 TL} %0,001 | o,00 TL %18,00 | orf 1.800,00 TL Mal Hizmet Toplam Tutarı 38.374,00 TL Hesaplanan KDV(%18) 14.453,64 TL Vergiler Dahil Toplam Tutar | 45.2813271) Ödenecek Tutar | 45.281,32 TL havale Not 2 : . 2 oe 2 : . Yalniz # KIRK BEŞ BIN İKİ YÜZ SEKSEN BİR Lira OTUZ İKİ Kuruş #"
        },
        "regex": {
            "tarih": [
                "01-04-2023"
            ],
            "para": [
                "18,00",
                "1.800,00 TL",
                "38.374,00 TL",
                "14.453,64 TL",
                "45.281,32 TL"
            ],
            "iban": [],
            "fatura_no": [],
            "vergi_no": [
                "9000068418"
            ],
            "tc_no": [],
            "telefon": [],
            "email": [
                "bodurum88@hotmail.com"
            ],
            "fatura_tipi": [],
            "kdv_orani": [],
            "ettn": [],
            "mersis_no": [],
            "ticaret_sicil": [
                "12345669"
            ],
            "musteri_no": [],
            "mal_hizmet_kodu": [],
            "alici_ad_soyad": [
                "Akkaya Yazılım"
            ],
            "alici_adres": [],
            "urun_aciklama": [],
            "urun_miktar": [],
            "birim_fiyat": [],
            "odeme_sekli": [],
            "kargo_bilgisi": [],
            "siparis_no": [],
            "fatura_tarihi": [],
            "duzenleme_saati": [],
            "satici_vkn": [],
            "alici_vkn": [],
            "odenecek_tutar": [],
            "doviz_kuru": [],
            "para_birimi": [
                "TL"
            ]
        },
        "structured": {
            "satici_firma_unvani": "x TICARET",
            "satici_vergi_dairesi": "es Bodrum VKN",
            "satici_ticaret_sicil": "12345669",
            "alici_firma_unvani": "Akkaya Yazılım Özelleştirme No",
            "alici_email": "bodurum88@hotmail.com",
            "fatura_numarasi": "MINT2023000000089",
            "genel_toplam": "38.374,00",
            "tarih": "01-04-2023",
            "para": "18,00",
            "vergi_no": "9000068418",
            "email": "bodurum88@hotmail.com",
            "ticaret_sicil": "12345669",
            "alici_ad_soyad": "Akkaya Yazılım",
            "para_birimi": "TL",
            "kalemler": [],
            "fatura_tarihi": "Fatura Tarihi:\n\n01-04-2023"
        }
    },
    {
        "dosya": "27.08.2025_Gelen Fatura (1)\\13.08.2025-SEM2025000000068.pdf",
        "analiz_zamani": "2025-08-28 09:44:34",
        "ocr_istatistikleri": {
            "ortalama_guven_skoru": "57.58%",
            "toplam_kelime": 189,
            "gecerli_kelime": 117,
            "ham_metin_uzunlugu": 726,
            "ham_metin": ". Gerçek Oto Lastik Sanayi Tic, Ltd. Sti. ) oe LES: ae J İçerenköy Mah. Oto Sanayi Sitesi No:28 Pee ‘5 faa ad yi, Ataşehir/ İstanbul SE: Vergi Dairesi: Kozyatağı Ve, sgh a VKN: 9000068418 Ne, LY fe ye Py oy ke ve Ari e-FATURA Özelleştirme No: TR1.2 SAYI SSS Senaryo: SAYIN Fatura park (Tatko) Fatura kadıköy istanbu Fatura Tarihi; )12.08.2025 Tel: (234) 234 24-24 12-08-2025 Vergi Dairesi: BÜYÜK MÜKELLEF 14:22:48 VKN: 9000068418 Sipariş No: o | ETIN: e [RP eas GT festa TT 0,00 71} %20,00 24.624,60 LE Mal Hizmet Toplam Tutari |_123.123,00 TL Toplam İskonto | 000TH Hesaplanan KDV(%20) 24.624,60 TL Vergiler Dahil Toplam Tutar 147.747,60 TL Ödenecek Tutar 147.747,60 TL #yüzkırkyedibinyediyüzkırkyedir LaltmışKR# Fatura Notu:"
        },
        "regex": {
            "tarih": [
                "12.08.2025",
                "12-08-2025"
            ],
            "para": [
                "0,00",
                "20,00",
                "24.624,60",
                "123,00 TL",
                "24.624,60 TL",
                "147.747,60 TL"
            ],
            "iban": [],
            "fatura_no": [],
            "vergi_no": [
                "9000068418"
            ],
            "tc_no": [],
            "telefon": [],
            "email": [],
            "fatura_tipi": [
                "e-FATURA"
            ],
            "kdv_orani": [],
            "ettn": [],
            "mersis_no": [],
            "ticaret_sicil": [],
            "musteri_no": [],
            "mal_hizmet_kodu": [],
            "alici_ad_soyad": [
                "Fatura park"
            ],
            "alici_adres": [],
            "urun_aciklama": [],
            "urun_miktar": [],
            "birim_fiyat": [],
            "odeme_sekli": [],
            "kargo_bilgisi": [],
            "siparis_no": [
                "o"
            ],
            "fatura_tarihi": [],
            "duzenleme_saati": [],
            "satici_vkn": [],
            "alici_vkn": [],
            "odenecek_tutar": [
                "147.747,60 TL"
            ],
            "doviz_kuru": [],
            "para_birimi": [
                "TL"
            ]
        },
        "structured": {
            "satici_vergi_dairesi": "SE",
            "satici_vergi_numarasi": "9000068418",
            "alici_firma_unvani": "Fatura park",
            "alici_telefon": "(234) 234 24",
            "siparis_no": "o",
            "genel_toplam": "147.747,60",
            "tarih": "12.08.2025",
            "para": "0,00",
            "vergi_no": "9000068418",
            "kalemler": [],
            "fatura_numarasi": "SEM2025000000065",
            "fatura_tarihi": "Fatura Tarihi:\n\n12-08-2025"
        }
    },
    {
        "dosya": "27.08.2025_Gelen Fatura (1)\\05.07.2025-NYS2025000000189.pdf",
        "analiz_zamani": "2025-08-28 09:44:35",
        "ocr_istatistikleri": {
            "ortalama_guven_skoru": "68.03%",
            "toplam_kelime": 232,
            "gecerli_kelime": 163,
            "ham_metin_uzunlugu": 978,
            "ham_metin": "GANİMET BİLİŞİM ELEKTRİK İZ EKTRONİK BİLGİSAYAR TEKNİK DESTEK VE DANIŞMANLIK HIZM.SAN.TIC.LTD STH. LES ee Ferhatpaşa Mah, Atatürk Cad. No:61 Çatalca İstanbul pe LF 9. z Vergi Dairesj: Büyükçekmece VD. İğ. | gh ry VKN: 9000068418 Re, TER i yr?! RD = di a e-FATURA Özelleştirme No: TR1.2 Senaryo: o Fatura Tipi Tear Fatura No: — SAYIN Fatura Tarihi; = 05-07-2025 Uyumsoft Test Firma Düzenleme Tarihi; 05-07-2025 Türkiye Düzenleme Saati: VKN: 9000068418 Sipariş ETME nn Sipariş Tarihi; 03-07-2025 ETIN: we İskonto İskonto KDV wy . . ‘eee | == SS ee Ymm BİLGİSAYAR KASASI ( is- 13400F, 16GB DDR4 RAM , 500GB SSD, 2GB EKRAN 4 Adet 20.000,00000000 TL %20,00 16.000,00 TL 80.000,00 TL KARTI /400W POWER KASA ÖZELLİKLERİNDE) 24 ASUS VZ24EHE IPS FHD o Mal Hizmet Toplam Tutarı 85.780,00 TL Toplam İskonto | 0.0071] Hesaplanan KDV(%20) | 17.156,00 71] Vergiler Dahil Toplam Tutar 102.936,00 TL Ödenecek Tutar 102.936,00 TL E Fatura Not Kısmı #Yüz İki Bin Dokuz Yüz Otuz Altı Türk Lirası #"
        },
        "regex": {
            "tarih": [
                "05-07-2025",
                "03-07-2025"
            ],
            "para": [
                "20,00",
                "16.000,00 TL",
                "80.000,00 TL",
                "85.780,00 TL",
                "17.156,00",
                "102.936,00 TL"
            ],
            "iban": [],
            "fatura_no": [],
            "vergi_no": [
                "9000068418"
            ],
            "tc_no": [],
            "telefon": [],
            "email": [],
            "fatura_tipi": [
                "e-FATURA"
            ],
            "kdv_orani": [],
            "ettn": [],
            "mersis_no": [],
            "ticaret_sicil": [],
            "musteri_no": [],
            "mal_hizmet_kodu": [],
            "alici_ad_soyad": [
                "Fatura Tarihi"
            ],
            "alici_adres": [],
            "urun_aciklama": [],
            "urun_miktar": [
                "4"
            ],
            "birim_fiyat": [],
            "odeme_sekli": [],
            "kargo_bilgisi": [],
            "siparis_no": [],
            "fatura_tarihi": [],
            "duzenleme_saati": [],
            "satici_vkn": [],
            "alici_vkn": [],
            "odenecek_tutar": [
                "102.936,00 TL"
            ],
            "doviz_kuru": [],
            "para_birimi": [
                "TL"
            ]
        },
        "structured": {
            "satici_vergi_numarasi": "9000068418",
            "alici_firma_unvani": "Fatura Tarihi",
            "fatura_tipi": "Tear Fatura",
            "genel_toplam": "102.936,00",
            "mal_hizmet_toplam": "85.780,00",
            "tarih": "05-07-2025",
            "para": "20,00",
            "vergi_no": "9000068418",
            "alici_ad_soyad": "Fatura Tarihi",
            "urun_miktar": "4",
            "odenecek_tutar": "102.936,00 TL",
            "para_birimi": "TL",
            "kalemler": [],
            "fatura_numarasi": "NYS2025000000189",
            "fatura_tarihi": "05-07-2025"
        }
    },
    {
        "dosya": "27.08.2025_Gelen Fatura (1)\\05.05.2025-ABK2025000000273.pdf",
        "analiz_zamani": "2025-08-28 09:44:35",
        "ocr_istatistikleri": {
            "ortalama_guven_skoru": "61.61%",
            "toplam_kelime": 192,
            "gecerli_kelime": 128,
            "ham_metin_uzunlugu": 849,
            "ham_metin": "UYUMSOFT BİLGİ SİSTEMLERİ VE TEKNOLOJİLERİ TİCARET ANONİM ŞİRKETİ ERİ deddekorklur mahallesi atakent caddesi ON Eki on on 42000 Zincirlikuyu/ İstanbul 40 ves Tel: 9995555566666644 ae bas Web Sitesi: Www.zootopiaglobal.com Nee A Vergi Dairesi: 30 ağustos 7 ye x ae: th VKN: 9000068418 a TICARETSICILNO: 12345¢ e-FATURA eae MERSISNO: 2222 Ç 2 Ozellestirme No: TR1.2 ee OP Senaryo: SAYIN <> > Fatura Tip: —İsarıs Uyumsoft Bilgi Sistemleri Ve Teknolojileri Ticaret Anonim Şirketi Fatura No: fasxo025000000073 ILCE/ İstanbul C©@ Fatura Tarihi; 05-05-2025 VKN: 9000068418 Tarihi: — İ05-05 2025 Th sa — EP. Düzenleme Sati; [rasp ETTN: ©95052c6-696b-4251-a1 PE ee are ome el i) İİ Mal Hizmet Toplam Tutarı | 833333371) Toplam İskonto |, Hesaplanan KDV(%20.00) 16.666,67 TL Vergiler Dahil Toplam Tutar 100.000,00 TL 100.000,00 TL Yalnız #Yüz Bin Türk Lirası#"
        },
        "regex": {
            "tarih": [
                "05-05-2025"
            ],
            "para": [
                "16.666,67 TL",
                "100.000,00 TL"
            ],
            "iban": [],
            "fatura_no": [
                "fasxo02500000007"
            ],
            "vergi_no": [
                "9000068418"
            ],
            "tc_no": [],
            "telefon": [
                "99955555666"
            ],
            "email": [],
            "fatura_tipi": [
                "e-FATURA"
            ],
            "kdv_orani": [],
            "ettn": [],
            "mersis_no": [],
            "ticaret_sicil": [],
            "musteri_no": [],
            "mal_hizmet_kodu": [],
            "alici_ad_soyad": [],
            "alici_adres": [],
            "urun_aciklama": [],
            "urun_miktar": [],
            "birim_fiyat": [],
            "odeme_sekli": [],
            "kargo_bilgisi": [],
            "siparis_no": [],
            "fatura_tarihi": [],
            "duzenleme_saati": [],
            "satici_vkn": [],
            "alici_vkn": [],
            "odenecek_tutar": [],
            "doviz_kuru": [],
            "para_birimi": [
                "TL"
            ]
        },
        "structured": {
            "satici_vergi_numarasi": "9000068418",
            "alici_telefon": "9995555566666644",
            "fatura_numarasi": "fasxo025000000073",
            "genel_toplam": "100.000,00",
            "tarih": "05-05-2025",
            "para": "16.666,67 TL",
            "fatura_no": "fasxo02500000007",
            "vergi_no": "9000068418",
            "telefon": "99955555666",
            "kalemler": [],
            "fatura_tarihi": "05-05-2025"
        }
    },
    {
        "dosya": "27.08.2025_Gelen Fatura (1)\\08.08.2025-SEM2025000000050.pdf",
        "analiz_zamani": "2025-08-28 09:44:35",
        "ocr_istatistikleri": {
            "ortalama_guven_skoru": "68.26%",
            "toplam_kelime": 326,
            "gecerli_kelime": 231,
            "ham_metin_uzunlugu": 1399,
            "ham_metin": "[a] Gerçek Oto Lastik Sanayi Tic. Ltd. Sti. . EE EŞ zl İçerenköy Mah. Oto Sanayi Sitesi No:28 fee o i a ad Ataşehir/ İstanbul a feat & as See Vergi Dairesi: Kozyatağı Ne me 450 VEN: 9000068418 NG ALI ees oe tat aE: e-FATURA earl? Özelleştirme No: TR1.2 SAVIN Fatura No: İSEM2025000000050 Ataşehir/ İstanbul 08-08-2025 Tel: (435) 353-5353 08-08-2025 Vergi Dairesi: Kozyatağı 17:16:04 VEN: 9000068418 SiparisNo: ETTN: 56fdd2ba-f122-477b-9096-a3de993bf74c iskonto | iskonto | KDV wy . . fie | | miktar | | Gran | | gramı | KovTütan | Vergiter [Mal Hizmet Tutar 1 (iş Emri No:367177 | Rot 3 Adet) 13.000,00000000 TL 3.900,00 TLİ | 7.800,00 TL 35,100,00 TL Ayarı (Binek) İş Emri No:367177 | LASSA 2 LASSA GREENWAYS 2 6.400,00000000 TL 2.560,00 TL| %20,00] 2.560,00 TL 10.240,00 TL 185/65R15 88H 3 [fg Emri No:367178 | Rot 1 Adet) 12.000,00000000 TL 3.600,00 TL| | 2.400,00 TL 8.400,00 TL Ayarı (Binek) İş Emri No:367178 | LASSA 4 Multiways 2 185/65R15 3 Adet) 2.300,00000000 TL 0,00 TL} 9620,00) 1.380,00 TL 6.900,00 TL 92V XL M+S 3PMSF 5 (fiş Emri No:367179 | Rot 2 Adet) 11.000,00000000 TL 0,00 TLİ 4.400,00 TL TL Ayarı (Binek) İş Emri No:367179 | LASSA Greenways 185/65R15 1 Adet| 9.000,00000000 TL 0,00 TL} %20,00] 1.800,00 TL 9.000,00 TL B8H 101.700,00 TL 10.060,00 TL Hesaplanan KDV(%20)| ( TL Vergiler Dahil Toplam Tutar) 109.968,00 TL 109.968,00 TL #yüzdokuzbindokuzyüzaltmışsekizTL# Fatura Notu:"
        },
        "regex": {
            "tarih": [
                "08-08-2025"
            ],
            "para": [
                "3.900,00",
                "7.800,00 TL",
                "100,00 TL",
                "2.560,00 TL",
                "20,00",
                "10.240,00 TL",
                "3.600,00 TL",
                "2.400,00 TL",
                "8.400,00 TL",
                "0,00 TL"
            ],
            "iban": [],
            "fatura_no": [
                "İSEM202500000005"
            ],
            "vergi_no": [],
            "tc_no": [],
            "telefon": [],
            "email": [],
            "fatura_tipi": [
                "e-FATURA"
            ],
            "kdv_orani": [],
            "ettn": [
                "56fdd2ba-f122-477b-9096-a3de993bf74c"
            ],
            "mersis_no": [],
            "ticaret_sicil": [],
            "musteri_no": [],
            "mal_hizmet_kodu": [],
            "alici_ad_soyad": [],
            "alici_adres": [],
            "urun_aciklama": [],
            "urun_miktar": [
                "3",
                "1",
                "2"
            ],
            "birim_fiyat": [],
            "odeme_sekli": [],
            "kargo_bilgisi": [],
            "siparis_no": [],
            "fatura_tarihi": [],
            "duzenleme_saati": [],
            "satici_vkn": [],
            "alici_vkn": [],
            "odenecek_tutar": [],
            "doviz_kuru": [],
            "para_birimi": [
                "TL"
            ]
        },
        "structured": {
            "satici_firma_unvani": "Tic. Sti. EE Gerçek Lastik Oto Ltd.",
            "satici_vergi_dairesi": "Ne NG VEN",
            "alici_telefon": "(435) 353",
            "fatura_numarasi": "İSEM2025000000050",
            "ettn": "56fdd2ba-f122-477b-9096-a3de993bf74c",
            "genel_toplam": "109.968,00",
            "tarih": "08-08-2025",
            "para": "3.900,00",
            "fatura_no": "İSEM202500000005",
            "kalemler": [
                {
                    "miktar": "GREENWAYS 2 6.400,00000000",
                    "iskonto": "2.560,00 TL",
                    "kdv_orani": "%20,00] 2.560,00 TL| TL",
                    "aciklama": "10.240,00",
                    "tutar": "TL"
                },
                {
                    "miktar": "185/65R15 Adet) 2 3 2.300,00000000",
                    "kdv_orani": "0,00 9620,00) 1.380,00 TL} TL",
                    "aciklama": "6.900,00",
                    "iskonto": "TL",
                    "tutar": "TL"
                },
                {
                    "miktar": "185/65R15 Adet| 9.000,00000000 1",
                    "kdv_orani": "0,00 %20,00] 1.800,00 TL} TL",
                    "aciklama": "9.000,00",
                    "iskonto": "TL",
                    "tutar": "TL"
                },
                {
                    "aciklama": "101.700,00",
                    "tutar": "TL"
                },
                {
                    "aciklama": "10.060,00",
                    "tutar": "TL"
                },
                {
                    "aciklama": "( KDV(%20)|",
                    "kdv_orani": "Hesaplanan",
                    "tutar": "TL"
                }
            ],
            "fatura_tarihi": "08-08-2025"
        }
    },
    {
        "dosya": "27.08.2025_Gelen Fatura (1)\\03.07.2024-BTY2024000000589.pdf",
        "analiz_zamani": "2025-08-28 09:44:36",
        "ocr_istatistikleri": {
            "ortalama_guven_skoru": "64.14%",
            "toplam_kelime": 234,
            "gecerli_kelime": 154,
            "ham_metin_uzunlugu": 1053,
            "ham_metin": "Uyumsoft Bilgi Sistemleri ve Teknolojileri AŞ. 7 LONG izl shy: 9 YTÜ Davutpaşa Kampüsü No:401 Pees 9 e Esenler/ İstanbul ha = Vergi Dairesi: Esenler A ie # VKN: 9000068418 NALI ete MERSISNO: 12345669-111 deni TICARETSICILNO: 12345669-111 Ak SS - e FATURA Özelleştirme No: TR1.2 aN SAYIN Fatura Tipi: Obe kli 21 Fatura Esenler Berin Fatura Tarihi: [03-07-2024 E-Posta: test@test.com Düzenleme Tarihi: 03-07-2024 Tel: 0212200022 Fax: 22111229 Düzenleme Saati: — |18:04:52 | VKN: 9000068418 Sipariş No: ORD1234567 Sipariş Tarihi: 03-07-2024 ©478dea7-146d-4d2b-a31e-b4d823501b51 wee İskonto | İskonto KDV . eee Toe [sie TES BS aes Teo aa 102.880,00000000 Lİ io 123.456,00 TL | 123.456,00 TL Mal Hizmet Toplam Tutarı 102.880,00 TL İskonto Hesaplanan KDV(%20) 20.576,00 TL Vergiler Dahil Toplam Tutar 123.456,00 TL Ödenecek Tutar 123.456,00 TL İrsaliye No ve Tarihleri : IRS000000001 (03-07-2024) | 1RS000000002 (03-07-2024) Fatura Notu Fatura Notu . . Internet Sitesi: | Ödeme Tarihi: 03.07.2024 | Ödeme Tipi: KREDIKARTI/BANKAKARTI | Kargo Tarihi: 03.07.2024"
        },
        "regex": {
            "tarih": [
                "03-07-2024",
                "03.07.2024"
            ],
            "para": [
                "123.456,00 TL",
                "102.880,00 TL",
                "20.576,00 TL"
            ],
            "iban": [],
            "fatura_no": [],
            "vergi_no": [
                "9000068418"
            ],
            "tc_no": [],
            "telefon": [],
            "email": [
                "test@test.com"
            ],
            "fatura_tipi": [],
            "kdv_orani": [],
            "ettn": [],
            "mersis_no": [],
            "ticaret_sicil": [
                "12345669"
            ],
            "musteri_no": [],
            "mal_hizmet_kodu": [],
            "alici_ad_soyad": [
                "Fatura Tipi"
            ],
            "alici_adres": [],
            "urun_aciklama": [],
            "urun_miktar": [],
            "birim_fiyat": [],
            "odeme_sekli": [],
            "kargo_bilgisi": [],
            "siparis_no": [
                "ORD1234567"
            ],
            "fatura_tarihi": [],
            "duzenleme_saati": [],
            "satici_vkn": [],
            "alici_vkn": [],
            "odenecek_tutar": [
                "123.456,00 TL"
            ],
            "doviz_kuru": [],
            "para_birimi": [
                "TL"
            ]
        },
        "structured": {
            "satici_vergi_dairesi": "Esenler",
            "alici_firma_unvani": "Fatura Tipi",
            "alici_email": "test@test.com",
            "alici_telefon": "0212200022",
            "fatura_tarihi": "03-07-2024",
            "fatura_tipi": "Obe kli",
            "siparis_no": "ORD1234567",
            "genel_toplam": "123.456,00",
            "tarih": "03-07-2024",
            "para": "123.456,00 TL",
            "vergi_no": "9000068418",
            "email": "test@test.com",
            "ticaret_sicil": "12345669",
            "alici_ad_soyad": "Fatura Tipi",
            "odenecek_tutar": "123.456,00 TL",
            "para_birimi": "TL",
            "kalemler": [],
            "fatura_numarasi": "BTY2024000000589"
        }
    },
    {
        "dosya": "27.08.2025_Gelen Fatura (1)\\05.07.2025-NYS2025000000186.pdf",
        "analiz_zamani": "2025-08-28 09:44:36",
        "ocr_istatistikleri": {
            "ortalama_guven_skoru": "63.96%",
            "toplam_kelime": 236,
            "gecerli_kelime": 156,
            "ham_metin_uzunlugu": 936,
            "ham_metin": "belin yle GANİMET BİLİŞİM ELEKTRİK ELEKTRONİK BİLGİSAYAR TEKNİK Gs DESTEK VE DANIŞMANLIK HİZM.SAN TİC.LTD.ŞTİ, si fe Ferhatpaşa Mah. Atatürk Cad. No:61 Çatalca İstanbul EAA. & Vergi Büyükçekmece Vp, he gh > 2 5 “re VKN: 9000068418 Ne ™ va” ali a A —.. 25 Özelleştirme No: TR1.2 Senaryo: o Fatura Tipi atra No: ~~ SAYIN Fatura Tarihi Uyumsoft Test Firma Düzenleme Tarihi; 05-07-2025 Türkiye Düzenleme Saati: VKN: 9000068418 Sipariş No: ETME Sipariş Tarihi: ETIN: ee İskonto İskonto KDV ay . e amma [ar] mam |e BILGISAYAR KASASI ( is- 13400F, 16GB DDR4 RAM 1 500GB SSD, 26B EKRAN 4 Adet| 20.000,0000000p TL 7620,00) 16.000,00 TL 80.000,00 TL KARTI ,400W POWER KASA ÖZELLİKLERİNDE) 24 ASUS VZ24EHF IPS FHD Mal Hizmet Toplam Tutarı 85.780,00 TL Toplam İskonto | 0.0071 Hesaplanan KDV(%20) | 17.156,00 71 Vergiler Dahil Toplam Tutar 102.936,00 TL Ödenecek Tutar 102.936,00 TL E Fatura Not Kısmı #Yüz İki Bin Dokuz Yüz Otuz Altı Türk Lirası #"
        },
        "regex": {
            "tarih": [
                "05-07-2025"
            ],
            "para": [
                "7620,00",
                "16.000,00 TL",
                "80.000,00 TL",
                "85.780,00 TL",
                "17.156,00",
                "102.936,00 TL"
            ],
            "iban": [],
            "fatura_no": [],
            "vergi_no": [
                "9000068418"
            ],
            "tc_no": [],
            "telefon": [],
            "email": [],
            "fatura_tipi": [],
            "kdv_orani": [],
            "ettn": [],
            "mersis_no": [],
            "ticaret_sicil": [],
            "musteri_no": [],
            "mal_hizmet_kodu": [],
            "alici_ad_soyad": [
                "Fatura Tarihi Uyumsoft"
            ],
            "alici_adres": [],
            "urun_aciklama": [],
            "urun_miktar": [
                "4"
            ],
            "birim_fiyat": [],
            "odeme_sekli": [],
            "kargo_bilgisi": [],
            "siparis_no": [
                "ETME"
            ],
            "fatura_tarihi": [],
            "duzenleme_saati": [],
            "satici_vkn": [],
            "alici_vkn": [],
            "odenecek_tutar": [
                "102.936,00 TL"
            ],
            "doviz_kuru": [],
            "para_birimi": [
                "TL"
            ]
        },
        "structured": {
            "satici_firma_unvani": "GANİMET BİLİŞİM ELEKTRİK ELEKTRONİK DESTEK BİLGİSAYAR VE DANIŞMANLIK HİZM.SAN TİC.LTD.",
            "alici_firma_unvani": "Fatura Tarihi Uyumsoft Test Firma Düzenleme Tarihi",
            "fatura_tipi": "atra",
            "siparis_no": "ETME",
            "genel_toplam": "102.936,00",
            "tarih": "05-07-2025",
            "para": "7620,00",
            "vergi_no": "9000068418",
            "alici_ad_soyad": "Fatura Tarihi Uyumsoft",
            "urun_miktar": "4",
            "odenecek_tutar": "102.936,00 TL",
            "para_birimi": "TL",
            "kalemler": [],
            "fatura_numarasi": "NYS2025000000186",
            "fatura_tarihi": "05-07-2025"
        }
    },
    {
        "dosya": "27.08.2025_Gelen Fatura (1)\\05.07.2025-NYS2025000000185.pdf",
        "analiz_zamani": "2025-08-28 09:44:37",
        "ocr_istatistikleri": {
            "ortalama_guven_skoru": "60.80%",
            "toplam_kelime": 275,
            "gecerli_kelime": 188,
            "ham_metin_uzunlugu": 1125,
            "ham_metin": "a sean ee iki GANİMET BİLİŞİM ELEKTRİK ELEKTRONİK BİLGİSAYAR TEKNİK ee To By BAS Shite 4 DESTEK VE DANIŞMANLIK HIZM.SAN, STI. ie ere Ferhatpaşa Mah. Atatürk Cad. No:61 Çatalca İstanbul Lime “if Vergi Dairesi: Büyükçekmece VD. Agi | : can a o an VKN: 9000068418 Nee LT icf: ELE İn Mecazi se m8 “+5 ins ————......... - — a za a: 5 e-FATURA Ee yy Özelleştirme No: TR1.2 Senaryo: oo — Fatura Tipi: İsarıs Fatura İNYS2025000000185 SAYIN Fatura Tarihi: [05-07-2025 | Uyumson Test Firma Düzenleme Tarihi: 05-07-2005 Türkiye Düzenleme Saati: [14:39:03 © VKN: 9000068418 Sipariş No: 54 o, Sipariş Tarihi: ETİN: 28b2ad6f-86c6-423c-ad57-a9169889b731 F ilm pi İskonto | İskonto KDV . . e a BİLGİSAYAR KASASI ( İ5- 13400F, 16GB DDR4 RAM 1 S00GB SSD, 2GB EKRAN 4 Adet} 20.000,00000000 TL 020,00) 16.000,00 TL 80.000,00 TL KARTI ,400W POWER KASA OZELLIKLERINDE) IPS FHD 5.780,00000000 TL İN 9620,00) | 1.156,00 TL | 5.780,00 TL Mal Hizmet Toplam Tutarı 85.780,00 TL Toplam İskonto MY Hesaplanan KDV(%20) | 17.156,00 TH Vergiler Dahil Toplam Tutar 102.936,00 TL 102.936,00 TL E Fatura Not Kısmı #Yüz İki Bin Dokuz Yüz Otuz Altı Türk Lirası #"
        },
        "regex": {
            "tarih": [
                "05-07-2025",
                "05-07-2005"
            ],
            "para": [
                "020,00",
                "16.000,00 TL",
                "80.000,00 TL",
                "9620,00",
                "1.156,00 TL",
                "5.780,00 TL",
                "85.780,00 TL",
                "17.156,00",
                "102.936,00 TL"
            ],
            "iban": [],
            "fatura_no": [],
            "vergi_no": [
                "9000068418"
            ],
            "tc_no": [],
            "telefon": [],
            "email": [],
            "fatura_tipi": [
                "e-FATURA"
            ],
            "kdv_orani": [],
            "ettn": [],
            "mersis_no": [],
            "ticaret_sicil": [],
            "musteri_no": [],
            "mal_hizmet_kodu": [],
            "alici_ad_soyad": [
                "Fatura Tarihi"
            ],
            "alici_adres": [],
            "urun_aciklama": [],
            "urun_miktar": [
                "2",
                "4"
            ],
            "birim_fiyat": [],
            "odeme_sekli": [],
            "kargo_bilgisi": [],
            "siparis_no": [
                "54"
            ],
            "fatura_tarihi": [],
            "duzenleme_saati": [],
            "satici_vkn": [],
            "alici_vkn": [],
            "odenecek_tutar": [],
            "doviz_kuru": [],
            "para_birimi": [
                "TL"
            ]
        },
        "structured": {
            "satici_vergi_dairesi": "B",
            "alici_firma_unvani": "Fatura Tarihi",
            "fatura_numarasi": "İNYS2025000000185",
            "fatura_tarihi": "05-07-2025",
            "fatura_tipi": "İsarıs Fatura İNYS",
            "siparis_no": "54",
            "genel_toplam": "102.936,00",
            "mal_hizmet_toplam": "85.780,00",
            "tarih": "05-07-2025",
            "para": "020,00",
            "vergi_no": "9000068418",
            "alici_ad_soyad": "Fatura Tarihi",
            "urun_miktar": "2",
            "para_birimi": "TL",
            "kalemler": []
        }
    },
    {
        "dosya": "27.08.2025_Gelen Fatura (1)\\05.07.2025-NYS2025000000187.pdf",
        "analiz_zamani": "2025-08-28 09:44:37",
        "ocr_istatistikleri": {
            "ortalama_guven_skoru": "58.19%",
            "toplam_kelime": 209,
            "gecerli_kelime": 131,
            "ham_metin_uzunlugu": 697,
            "ham_metin": "NİMET BİLİŞİM ELEKTRİK ELEKTRONİK BİLGİSAYAR TEKNİK DN 3: Ast ee STEK VE DANISMANLIK HİZM.SAN TİC.LTD.ŞTİ. oa #7 o hatpaşa Mah. Atatürk Cad. No:61 Çatalca İstanbul eft few > mabe gi Dairesi: Büyükçekmece VD. Se sty VE ea N: 9000068418 Ne NAL E am e-FATURA ümmi SS — © NN — yan — SAYIN a — — — Uyumsoft Test Firma EZ Düzenleme Tarihi: . | Tarihi: Türkiye ©C Düzenleme Saati: . | Saati: VEN: 9000068418 sipariş No: — No: EM Ve — o sipariş Tarihi: Tarihi: ETTN: L. 13400F, 16GB DDR4 RAM , 500GB ssp, 2GB EKRAN 4 Adet 20.000,00000000 TU 420,00 16.000,00 TL 80.000,00 TL KARTI ,400W POWER KASA ÖZELLİKLERİNDE) A eri eri Sane iskontol MZ E Fatura Not Kısmı #Yüz İki Bin Dokuz Yüz Otuz Altı Türk Lirası #"
        },
        "regex": {
            "tarih": [],
            "para": [
                "420,00",
                "16.000,00 TL",
                "80.000,00 TL"
            ],
            "iban": [],
            "fatura_no": [],
            "vergi_no": [],
            "tc_no": [],
            "telefon": [],
            "email": [],
            "fatura_tipi": [
                "e-FATURA"
            ],
            "kdv_orani": [],
            "ettn": [],
            "mersis_no": [],
            "ticaret_sicil": [],
            "musteri_no": [],
            "mal_hizmet_kodu": [],
            "alici_ad_soyad": [],
            "alici_adres": [],
            "urun_aciklama": [],
            "urun_miktar": [
                "4"
            ],
            "birim_fiyat": [],
            "odeme_sekli": [],
            "kargo_bilgisi": [],
            "siparis_no": [],
            "fatura_tarihi": [],
            "duzenleme_saati": [],
            "satici_vkn": [],
            "alici_vkn": [],
            "odenecek_tutar": [],
            "doviz_kuru": [],
            "para_birimi": [
                "TL"
            ]
        },
        "structured": {
            "satici_firma_unvani": "VE ELEKTRİK sty BİLİŞİM HİZM.SAN TİC.LTD.",
            "genel_toplam": "80.000,00",
            "para": "420,00",
            "kalemler": []
        }
    },
    {
        "dosya": "27.08.2025_Gelen Fatura (1)\\05.07.2025-NYS2025000000188.pdf",
        "analiz_zamani": "2025-08-28 09:44:38",
        "ocr_istatistikleri": {
            "ortalama_guven_skoru": "66.28%",
            "toplam_kelime": 255,
            "gecerli_kelime": 172,
            "ham_metin_uzunlugu": 1016,
            "ham_metin": "Cİ ety GANİMET İŞİM ERK —— GANİMET BİLİŞİM ELEKTRİK ELEKTRONİK BİLGİSAYAR TEKNİK Pig ae GE ff DESTEK VE DANIŞMANLIK KE: ON Ferhatpaşa Mah. Atatürk Cad, No:61 Çatalca İstanbul fe & ote Vergi Dairesi: Büyükçekmece Vp. Ve. i a VEN: 9000068418 AĞ NA ———. ii ike ee Fat e-FATURA Özelleştirme No: TR1.2 Senaryo: oo Ek Fatura Tipi: [gare Fatura — SAYIN Fatura Tarihi: 05-07-2025 Uyumsoft Test Firma a Düzenleme Tarihi: [05-07-2995 Türkiye Saati; — VKN: 9000068418 © Sipariş No: İz ETN EX. Siparis Tarihi: 03-07-2025 ETTN: > Birim Fiyat Iskonto ay KDV Diğer Vergiler | Maj Hizmet Tutarı Oranı BO: © Oranı BİLGİSAYAR KASASI (İ5- 13400F, 16GB DDR4 RAM » 500GB SSD, 2GB EKRAN 4 Adet 20.000,00000000 TL %20,00, 16.000,00 TL 80.000,00 TL KARTI ,400W POWER KASA ÖZELLİKLERİNDE) 24 ASUS VZ24EHF IPS FHD o Mal Hizmet Toplam Tutarı 85.780,00 TL Toplam İskonto | 6,00 71] Hesaplanan KDV(%20) | 71] Vergiler Dahil Toplam Tutar 102.936,00 TL Odenecek Tutar 102.936,00 TL E Fatura Not Kısmı #Yüz İki Bin Dokuz Yüz Otuz Altı Türk Lirası #"
        },
        "regex": {
            "tarih": [
                "05-07-2025",
                "05-07-2995",
                "03-07-2025"
            ],
            "para": [
                "20,00",
                "16.000,00 TL",
                "80.000,00 TL",
                "85.780,00 TL",
                "6,00",
                "102.936,00 TL"
            ],
            "iban": [],
            "fatura_no": [],
            "vergi_no": [
                "9000068418"
            ],
            "tc_no": [],
            "telefon": [],
            "email": [],
            "fatura_tipi": [
                "e-FATURA"
            ],
            "kdv_orani": [],
            "ettn": [],
            "mersis_no": [],
            "ticaret_sicil": [],
            "musteri_no": [],
            "mal_hizmet_kodu": [],
            "alici_ad_soyad": [
                "Fatura Tarihi"
            ],
            "alici_adres": [],
            "urun_aciklama": [],
            "urun_miktar": [
                "4"
            ],
            "birim_fiyat": [],
            "odeme_sekli": [],
            "kargo_bilgisi": [],
            "siparis_no": [
                "İz"
            ],
            "fatura_tarihi": [
                "05-07-2025"
            ],
            "duzenleme_saati": [],
            "satici_vkn": [],
            "alici_vkn": [],
            "odenecek_tutar": [],
            "doviz_kuru": [],
            "para_birimi": [
                "TL"
            ]
        },
        "structured": {
            "alici_firma_unvani": "Fatura Tarihi",
            "fatura_tarihi": "05-07-2025",
            "siparis_no": "İz",
            "genel_toplam": "102.936,00",
            "tarih": "05-07-2025",
            "para": "20,00",
            "vergi_no": "9000068418",
            "kalemler": [],
            "fatura_numarasi": "NYS2025000000188"
        }
    },
    {
        "dosya": "27.08.2025_Gelen Fatura (1)\\05.07.2025-NYS2025000000191.pdf",
        "analiz_zamani": "2025-08-28 09:44:38",
        "ocr_istatistikleri": {
            "ortalama_guven_skoru": "71.27%",
            "toplam_kelime": 257,
            "gecerli_kelime": 187,
            "ham_metin_uzunlugu": 1175,
            "ham_metin": "53 İZ mel 0) a GANİMET BİLİŞİM ELEKTRİK ELEKTRONİK BİLGİSAYAR TEKNİK EŞ . pe ee DESTEK VE DANIŞMANLIK HIZM.SAN.TIC.LTD.STI. AZ o ; i atts Ferhatpaşa Mah. Atatürk Cad. No:61 Çatalca İstanbul ar es sa He Vergi Dairesi: Büyükçekmece VD. Ve. 1) sh SE, VKN: 9000068418 oo: iz e-FATURA ltt Özelleştirme No: TR1.2 Senaryo: > İTICARIFATURA Fatura Tipi: SATIS Fatura No: İNYS2025000000191 SAYIN Fatura Tarihi: 05-07-2025 Uyumsoft Test Firma Düzenleme Tarihi: (o (05-07-2025 Türkiye Düzenleme Saati: | (14:57:04 VEN: 9000068418 Sipariş No: ETİN: ccacfd94-c639-4f87-8bbc-9b485684b2d4 we iskonto | iskonto | KDV ay Sa) | Miktar Birim Fiyat KDV Tutarı Diğer Vergiler | Mal Hizmet Tutarı BİLGİSAYAR KASASI ( İ5- 13400F, 16GB DDR4 RAM 1 , 500GB SSD, 2GB EKRAN 4 Adet| 20.000,00000000 TL 20,00) 16.000,00 TL 80.000,00 TL KARTI ,400W POWER KASA ÖZELLİKLERİNDE) 24 ASUS VZ24EHF IPS FHD o 100MZ 1MS HDMI 1 Adeti 5.780,00000000 TL 020,00) O 1.156,00 5.780,00 TL Mal Hizmet Toplam Tutarı 85.780,00 TL Toplam İskonto 0,00 TL Hesaplanan KDV(%20) 17.156,00 TL Vergiler Dahil Toplam Tutar) 102.936,00 TL Ödenecek Tutar) _102.936,00 TL E Fatura Not Kısmı #Yüz Iki Bin Dokuz Yüz Otuz Altı Türk Lirası #"
        },
        "regex": {
            "tarih": [
                "05-07-2025"
            ],
            "para": [
                "20,00",
                "16.000,00 TL",
                "80.000,00 TL",
                "020,00",
                "1.156,00",
                "5.780,00 TL",
                "85.780,00 TL",
                "0,00 TL",
                "17.156,00 TL",
                "102.936,00 TL"
            ],
            "iban": [],
            "fatura_no": [
                "İNYS202500000019"
            ],
            "vergi_no": [
                "9000068418"
            ],
            "tc_no": [],
            "telefon": [],
            "email": [],
            "fatura_tipi": [
                "e-FATURA"
            ],
            "kdv_orani": [],
            "ettn": [],
            "mersis_no": [],
            "ticaret_sicil": [],
            "musteri_no": [],
            "mal_hizmet_kodu": [],
            "alici_ad_soyad": [
                "Fatura Tarihi"
            ],
            "alici_adres": [],
            "urun_aciklama": [],
            "urun_miktar": [
                "4",
                "1"
            ],
            "birim_fiyat": [],
            "odeme_sekli": [],
            "kargo_bilgisi": [],
            "siparis_no": [
                "ETİN"
            ],
            "fatura_tarihi": [
                "05-07-2025"
            ],
            "duzenleme_saati": [],
            "satici_vkn": [],
            "alici_vkn": [],
            "odenecek_tutar": [],
            "doviz_kuru": [],
            "para_birimi": [
                "TL"
            ]
        },
        "structured": {
            "satici_firma_unvani": "mel GANİMET BİLİŞİM ELEKTRİK ELEKTRONİK BİLGİSAYAR TEKNİK EŞ pe . DESTEK VE DANIŞMANLIK HIZM.SAN.TIC.LTD.",
            "satici_vergi_dairesi": "B",
            "alici_firma_unvani": "Fatura Tarihi",
            "fatura_numarasi": "İNYS2025000000191",
            "fatura_tarihi": "05-07-2025",
            "fatura_tipi": "SATIS Fatura",
            "siparis_no": "ETİN",
            "genel_toplam": "85.780,00",
            "tarih": "05-07-2025",
            "para": "20,00",
            "fatura_no": "İNYS202500000019",
            "vergi_no": "9000068418",
            "alici_ad_soyad": "Fatura Tarihi",
            "urun_miktar": "4",
            "para_birimi": "TL",
            "kalemler": []
        }
    },
    {
        "dosya": "27.08.2025_Gelen Fatura (1)\\11.06.2025-OGZ2025000000653.pdf",
        "analiz_zamani": "2025-08-28 09:44:38",
        "ocr_istatistikleri": {
            "ortalama_guven_skoru": "60.16%",
            "toplam_kelime": 213,
            "gecerli_kelime": 130,
            "ham_metin_uzunlugu": 887,
            "ham_metin": "Talia ; — m YUMSOFT BİLGİ SİSTEMLERİ VE TEKNOLOJİLERİ TİCARET : ik NONİM ŞİRKETİ er: ON fa raat, leddekorklur mahallesi atakent caddesi O. Soe 12000 Zincirlikuyu/ İstanbul \\ i rel: 9995555566666644 ee gh pa =-Posta: deneme@deneme.com ry Vergi Dairesi: 30 agustos MR VKN: 9000068418 e-FATURA Özelleştirme No: SAYIN Nor may tan Fature Tar Vergi Dairesi: ataşehir Düzenleme Tarihi: VEN: 9000068418 Saati: |12:48:00 VEN mm İDöviz Kuru: ETİN: İskonto | İskonto KDV wy . . [omer] | ae [| Mal Hizmet Toplam Tutarı) 250.000,00 USD Toplam İskonto 0,00 USD Hesaplanan KDV(%10.00) 25.000,00 USD Vergiler Dahil Toplam Tutar 275.000,00 USD Ödenecek Tutar| 275.000,00 USD Mal Hizmet Toplam Tutarı(TL) 9.750.000,00 TL Toplam İskonto(TL) Hesaplanan KDV(Yo10.00XTL) 975.000,00 TL Vergiler Dahil Toplam Tutar(TL) 10.725.000,99) Ödenecek Tutar(TL) 10.725.000,09) Yalnız #İki Yüz Yetmiş Beş Bin Dolar# asdas"
        },
        "regex": {
            "tarih": [],
            "para": [
                "250.000,00 USD",
                "0,00 USD",
                "25.000,00 USD",
                "275.000,00 USD",
                "9.750.000,00 TL",
                "975.000,00 TL",
                "10.725.000,99",
                "10.725.000,09"
            ],
            "iban": [],
            "fatura_no": [],
            "vergi_no": [
                "9000068418"
            ],
            "tc_no": [],
            "telefon": [],
            "email": [
                "deneme@deneme.com"
            ],
            "fatura_tipi": [
                "e-FATURA"
            ],
            "kdv_orani": [],
            "ettn": [],
            "mersis_no": [],
            "ticaret_sicil": [],
            "musteri_no": [],
            "mal_hizmet_kodu": [],
            "alici_ad_soyad": [
                "Nor may tan Fature Tar"
            ],
            "alici_adres": [],
            "urun_aciklama": [],
            "urun_miktar": [],
            "birim_fiyat": [],
            "odeme_sekli": [],
            "kargo_bilgisi": [],
            "siparis_no": [],
            "fatura_tarihi": [],
            "duzenleme_saati": [],
            "satici_vkn": [],
            "alici_vkn": [],
            "odenecek_tutar": [],
            "doviz_kuru": [],
            "para_birimi": [
                "USD",
                "TL"
            ]
        },
        "structured": {
            "alici_firma_unvani": "Nor may tan Fature Tar Vergi Dairesi",
            "genel_toplam": "275.000,00",
            "para": "250.000,00 USD",
            "vergi_no": "9000068418",
            "email": "deneme@deneme.com",
            "kalemler": []
        }
    },
    {
        "dosya": "27.08.2025_Gelen Fatura (1)\\08.08.2025-SEM2025000000051.pdf",
        "analiz_zamani": "2025-08-28 09:44:38",
        "ocr_istatistikleri": {
            "ortalama_guven_skoru": "60.68%",
            "toplam_kelime": 294,
            "gecerli_kelime": 204,
            "ham_metin_uzunlugu": 1238,
            "ham_metin": "ER ERE bi Gerçek Oto Lastik Sanayi Tic. Ltd. Şti. . e Ma Pen a Örnek Adres No : 123/A ON Maltepe/ Istanbul i a paren Dİ Vergi Dairesi: Kozyatağı a hy fi wats VKN: 9000068418 co: rir Moe nn LL AA rege im he i] Fİ e-FATURA fa Özelleştirme No: TRIZ SAYIN — Fatura Tipi: SATIS ae Müşterisi No: O İSEM2025000000051 Ataşehir / İstanbul Fatura Tarihi: 08-08-2025 Vergi Dairesi: Kozyatağı Düzenleme Saati: 17:40:28 VKN: 9000068418 Sipariş No: 160584 ETİN: €e999d3cd-33c7-412d-b435-498f79c0814d İskonto | İskonto | KDV e . . ee feni 3 Adet) 13.000,00000000 no | 3.900,00 TL} 920,00) | 7.020,00 35.100,00 TL Aven (UHP/ 4x4 H 2 Adet) 6.400,00000000 nn | 2.560,00 TLİ %20,00| | 2.048,00 Lİ 10.240,00 TL Greenways 1 Adet| 12.000,00000000 no | 3.600,00 TLİ | 1.680,00 qo | 8.400,00 TL a (SAA HF m 3 Adet) 2.300,00000000 nn | 0,00 TLİ | 1.380,00 6.900,00 TL 5 [FALKEN Ecorun| —_2 Adet|_11.000,00000000 no | 0,00 TLİ %20,00| 4.400,00 qo | 22.000,00 TL 6 (© Hızlı Cila 500 ml 1 Adet) 9.000,00000000TL| %20,00| 1.800,00TL] 9.000,00 TL Mal Hizmet Toplam Tutarı) 101.700,00 TL Toplam İskonto 10.060,00 TL Hesaplanan KDV(%20) 18.328,00 TL Vergiler Dahil Toplam Tutar) 109.968,00 TL Ödenecek Tutar) 109.968,00 TL #yüzdokuzbindokuzyüzaltmışsekizTL# Fatura Notu:"
        },
        "regex": {
            "tarih": [
                "08-08-2025"
            ],
            "para": [
                "3.900,00 TL",
                "920,00",
                "7.020,00",
                "35.100,00 TL",
                "2.560,00",
                "20,00",
                "2.048,00",
                "10.240,00 TL",
                "3.600,00",
                "1.680,00"
            ],
            "iban": [],
            "fatura_no": [],
            "vergi_no": [
                "9000068418"
            ],
            "tc_no": [],
            "telefon": [],
            "email": [],
            "fatura_tipi": [
                "e-FATURA"
            ],
            "kdv_orani": [],
            "ettn": [],
            "mersis_no": [],
            "ticaret_sicil": [],
            "musteri_no": [],
            "mal_hizmet_kodu": [],
            "alici_ad_soyad": [],
            "alici_adres": [],
            "urun_aciklama": [],
            "urun_miktar": [
                "3",
                "2",
                "1",
                "500"
            ],
            "birim_fiyat": [],
            "odeme_sekli": [],
            "kargo_bilgisi": [],
            "siparis_no": [
                "160584"
            ],
            "fatura_tarihi": [
                "08-08-2025"
            ],
            "duzenleme_saati": [
                "17:40:28"
            ],
            "satici_vkn": [],
            "alici_vkn": [],
            "odenecek_tutar": [],
            "doviz_kuru": [],
            "para_birimi": [
                "TL"
            ]
        },
        "structured": {
            "satici_firma_unvani": "ERE ER Pen bi a e Ma Ltd.",
            "alici_firma_unvani": "SATIS",
            "fatura_numarasi": "İSEM2025000000051",
            "fatura_tarihi": "08-08-2025",
            "fatura_tipi": "SATIS ae Müşterisi",
            "siparis_no": "160584",
            "genel_toplam": "109.968,00",
            "tarih": "08-08-2025",
            "para": "3.900,00 TL",
            "vergi_no": "9000068418",
            "urun_miktar": "3",
            "duzenleme_saati": "17:40:28",
            "para_birimi": "TL",
            "kalemler": []
        }
    },
    {
        "dosya": "27.08.2025_Gelen Fatura (1)\\08.05.2025-OGZ2025000000005.pdf",
        "analiz_zamani": "2025-08-28 09:44:39",
        "ocr_istatistikleri": {
            "ortalama_guven_skoru": "63.50%",
            "toplam_kelime": 260,
            "gecerli_kelime": 166,
            "ham_metin_uzunlugu": 1133,
            "ham_metin": "UYUMSOFT BİLGİ SİSTEMLERİ VE TEKNOLOJİLERİ TİCARET el es 2) ANONIM SIRKETI EĞ e i i SIS ir deddekorklur mahallesi atakent caddesi fer: 42000 Zincirlikuyu/ istanbul Tel: 9995555566666644 \\ ‘a due ph Web Sitesi: www.zootopiaglobal.com NE. wy i Dairesi: 30 art Net rs Vergi Dairesi: 30 agustos oe: tha VKN: 9000068418 _ es TICARETSICILNO: 12345f e-FATURA favors 5 Bog MERSISNO: 2222 ° Se SAYIN UYUMSOFT BİLGİ SİSTEMLERİ VE TEKNOLOJİLERİ TİCARET ANONİM ŞİRKETİ Özelleştirme No: ESKİ LONDRA ASFALTI CAD. KULUÇKA MRK. A1 BLOK No:151 Senaryo: İTICARIFATURA /1C FaturaTipi: (SATIS. Kapı No:2 01 Fatura Tipi: ESENLER/ İSTANBUL 0Gz2025000000005 Vergi Dairesi: ESENLER VERGİ DAİRESİ MUD. Fatura Tarihi: 03-05-2025 VKN: 9000068418 Düzenleme Tarihi: {09-05-2025 RR III Düzenleme Saati: 01:08:00 ETİN: d8243407-911e-4593-8a0d-e808dd80b9cf Birim Fiyat Iskonto | İskonto KDV KDV Tutarı Diğer Vergiler | Mal Hizmet Tutarı Oranı Tutarı Oranı TL | SS 136.363,64 TL Mal Hizmet Toplam Tutarı 136.363,64 TL Toplam İskonto |, Hesaplanan KDV(%10.00) 13.636,36 TL Vergiler Dahil Toplam Tutar 150.000,00 TL Ödenecek Tutar) TL Yalnız #Yüz Elli Bin Türk Lirası#"
        },
        "regex": {
            "tarih": [
                "03-05-2025",
                "09-05-2025"
            ],
            "para": [
                "136.363,64 TL",
                "13.636,36 TL",
                "150.000,00 TL"
            ],
            "iban": [],
            "fatura_no": [],
            "vergi_no": [
                "9000068418"
            ],
            "tc_no": [],
            "telefon": [
                "99955555666"
            ],
            "email": [],
            "fatura_tipi": [
                "e-FATURA"
            ],
            "kdv_orani": [],
            "ettn": [],
            "mersis_no": [],
            "ticaret_sicil": [],
            "musteri_no": [],
            "mal_hizmet_kodu": [],
            "alici_ad_soyad": [
                "UYUMSOFT BİLGİ SİSTEMLERİ"
            ],
            "alici_adres": [],
            "urun_aciklama": [],
            "urun_miktar": [],
            "birim_fiyat": [],
            "odeme_sekli": [],
            "kargo_bilgisi": [],
            "siparis_no": [],
            "fatura_tarihi": [
                "03-05-2025"
            ],
            "duzenleme_saati": [
                "01:08:00"
            ],
            "satici_vkn": [],
            "alici_vkn": [],
            "odenecek_tutar": [],
            "doviz_kuru": [],
            "para_birimi": [
                "TL"
            ]
        },
        "structured": {
            "satici_firma_unvani": "es TICARET",
            "satici_vergi_numarasi": "9000068418",
            "satici_ticaret_sicil": "12345",
            "alici_firma_unvani": "UYUMSOFT BİLGİ SİSTEMLERİ VE TEKNOLOJİLERİ TİCARET ANONİM ŞİRKETİ Özelleştirme No",
            "alici_telefon": "9995555566666644",
            "fatura_tarihi": "03-05-2025",
            "genel_toplam": "150.000,00",
            "tarih": "03-05-2025",
            "para": "136.363,64 TL",
            "vergi_no": "9000068418",
            "telefon": "99955555666",
            "kalemler": []
        }
    },
    {
        "dosya": "27.08.2025_Gelen Fatura (1)\\08.08.2025-SEM2025000000052.pdf",
        "analiz_zamani": "2025-08-28 09:44:40",
        "ocr_istatistikleri": {
            "ortalama_guven_skoru": "53.85%",
            "toplam_kelime": 264,
            "gecerli_kelime": 162,
            "ham_metin_uzunlugu": 987,
            "ham_metin": "ercek Oto Lastik Sanayi Tic. Ltd. Sti. ee EŞ 2 rnek Adres No : 123/A LEAF tap jaltepe/ İstanbul Jergi Dairesi: Kozyatağı A ae ae JKN: 9000068418 Nez ay ee mi re e-FATURA ~ Özelleştirme No: Senaryor — SAYIN end © eN EZ İFatura No: ____|SeM2025000000052 Ataşehir/ İstanbul Fatura Tarihi: — 08-08-2025 Tel: (435) 353-5353 Düzenleme Tarihi: . Tarihi: Vergi Dairesi: Kozyatağı ©C Düzenleme Saati: Saati: VKN: 9000068418 >> No: VEN o Sipariş Tarihi: 08-08-2025 ETİN: Sa8bb20f-667e-4642-8734-19ea0e4c8539 4 . et İskonto op KDV ae . | am (| | a et Ze anl — — — et TL) | 2.560,00 TL 10.240,00 TL et 12.000,00000000 TU |3.600,00TL 420,00) _ 1.680,00 71 ee 8.400,00 TL St 2 +f 0.007 % 20,00 1380007] 6.900,00 TL | et 11,000,00000000 Til 0,00 TE %20,00 4.400,00T 22.000,00 TL 5 Tİ 9.000,00 TL Mal Hizmet Toplam Tutarı 101.700,00 TL Toplam İskonto 10.060,00 TL Hesaplanan KDV(%20)|_ 18.328,00 TL Vergiler Dahil Toplam Tutar 109.968,00 TL 109.968,00 TL #yüzdokuzbindokuzyüzaltmışsekizTLi? Fatura Notu:"
        },
        "regex": {
            "tarih": [
                "08-08-2025"
            ],
            "para": [
                "2.560,00 TL",
                "10.240,00 TL",
                "3.600,00TL",
                "420,00",
                "1.680,00",
                "8.400,00 TL",
                "20,00",
                "6.900,00 TL",
                "0,00",
                "22.000,00 TL"
            ],
            "iban": [],
            "fatura_no": [],
            "vergi_no": [
                "9000068418"
            ],
            "tc_no": [],
            "telefon": [],
            "email": [],
            "fatura_tipi": [
                "e-FATURA"
            ],
            "kdv_orani": [],
            "ettn": [],
            "mersis_no": [],
            "ticaret_sicil": [],
            "musteri_no": [],
            "mal_hizmet_kodu": [],
            "alici_ad_soyad": [
                "end"
            ],
            "alici_adres": [],
            "urun_aciklama": [],
            "urun_miktar": [],
            "birim_fiyat": [],
            "odeme_sekli": [],
            "kargo_bilgisi": [],
            "siparis_no": [],
            "fatura_tarihi": [],
            "duzenleme_saati": [],
            "satici_vkn": [],
            "alici_vkn": [],
            "odenecek_tutar": [],
            "doviz_kuru": [],
            "para_birimi": [
                "TL"
            ]
        },
        "structured": {
            "satici_firma_unvani": "tap EŞ ee Sti. Ltd.",
            "alici_firma_unvani": "end",
            "alici_telefon": "(435) 353",
            "fatura_numarasi": "SeM2025000000052",
            "genel_toplam": "109.968,00",
            "toplam_iskonto": "10.060,00",
            "mal_hizmet_toplam": "101.700,00",
            "tarih": "08-08-2025",
            "para": "2.560,00 TL",
            "vergi_no": "9000068418",
            "kalemler": [
                {
                    "tutar": "10.060,00 İskonto",
                    "aciklama": "Toplam",
                    "tutar_num": 10060.0
                },
                {
                    "tutar": "18.328,00 KDV(%20)|_",
                    "aciklama": "Hesaplanan",
                    "tutar_num": 18328.002
                },
                {
                    "tutar": "109.968,00 Tutar Toplam",
                    "aciklama": "Dahil",
                    "tutar_num": 109968.0
                },
                {
                    "aciklama": "Vergiler",
                    "tutar": "109.968,00",
                    "tutar_num": 109968.0
                }
            ],
            "fatura_tarihi": "08-08-2025"
        }
    },
    {
        "dosya": "27.08.2025_Gelen Fatura (1)\\04.05.2023-SIM2018040000011.pdf",
        "analiz_zamani": "2025-08-28 09:44:43",
        "ocr_istatistikleri": {
            "ortalama_guven_skoru": "63.92%",
            "toplam_kelime": 324,
            "gecerli_kelime": 223,
            "ham_metin_uzunlugu": 1421,
            "ham_metin": "Uyumsoft Bilgi Sistemleri ve Teknolojileri A.Ş. Hastane Cad. ; . EN 06606 MELİKGAZİ/ KAYSERİ fee: 0. > TE Tel: 03523525252 a ys aa Ne ref! ats ated di Web Sitesi: www.hh.com Ne NA E-Posta: 2zz@zz.com ae Vergi Dairesi: Gevher Nesibe 2 VKN: 9000068418 e-FATURA —————— — O İTICARIFATURA SAYIN NE adresleri4444den3ee555 7 KOCASINAN Kl Tel: 3521111111111 Düzenleme Tarihi: 11-04-2018 Vergi Dairesi: GÜRÜN Diizenleme Saati: | Saati: VKN: 9000068418 irsaliye No: GRN2018000000017 İrsaliye Tarihi: 11-04-2018 ETİN: 29845814-fdfc-4fec-9652-1b49413550a0 İskonto | İskonto | KDV e . A [Se | [Sm orm | Ponte PS | | EZE İ2 |DDR3 ANAKART - (ASUS) | 27 Adet| (o 453,26800000 Tt Ld 28,00] 220288 TH 16 GB DDR3 RAM - 9 4 |DDR3 ANAKART - (ASUS) | 36 Adet 453,26800000 TT İ 18,00 ii 88 08 T 16 GB DDR3 RAM - o (CORSAIR) 88 Adet 326,32500000 %18,00 5.168,99 28.716,60 TL 16 GB DDR3 RAM - 9 Mal Hizmet Toplam Tutarı 95.881,11 TL Toplam İskonto Hesaplanan KDV(%8) | 2.69710TLİ Hesaplanan KDV(9618) | 1119013 TL Vergiler Dahil Toplam Tutar 109.768,35 TL 109.768,35 TL #N£TOPLAM, HAM TUTAR#95881.11 #N#GENEL TOPLAMA CUR#109768.35 #N#TOPLAM, KDV. TUTARI, CUR#13887.23 #N#GENEL TOPLAM CUR#109768.35 Sicil No: 111111111 Mersis No: 4111111111111111 İşletme Merkezi: KAYSERİ YAZI ILE: YüzDokuzBinYediYüzAltmışSekiz TL OtuzBeş Kuruş Only: One Hundred Nine Thousand Seven Hundred Sixty Eight TL And Thirty Five Kuruş Ödeme Notu: VADE TARİHİ: 2018-04-11"
        },
        "regex": {
            "tarih": [
                "11-04-2018"
            ],
            "para": [
                "28,00",
                "18,00",
                "5.168,99",
                "28.716,60 TL",
                "95.881,11 TL",
                "109.768,35 TL"
            ],
            "iban": [],
            "fatura_no": [],
            "vergi_no": [
                "9000068418"
            ],
            "tc_no": [],
            "telefon": [
                "03523525252",
                "35211111111"
            ],
            "email": [
                "2zz@zz.com"
            ],
            "fatura_tipi": [
                "e-FATURA"
            ],
            "kdv_orani": [],
            "ettn": [],
            "mersis_no": [
                "411111111111111"
            ],
            "ticaret_sicil": [
                "111111111"
            ],
            "musteri_no": [],
            "mal_hizmet_kodu": [],
            "alici_ad_soyad": [
                "NE"
            ],
            "alici_adres": [],
            "urun_aciklama": [],
            "urun_miktar": [
                "27",
                "36",
                "88"
            ],
            "birim_fiyat": [],
            "odeme_sekli": [],
            "kargo_bilgisi": [],
            "siparis_no": [],
            "fatura_tarihi": [],
            "duzenleme_saati": [],
            "satici_vkn": [],
            "alici_vkn": [],
            "odenecek_tutar": [],
            "doviz_kuru": [],
            "para_birimi": [
                "TL"
            ]
        },
        "structured": {
            "alici_firma_unvani": "NE adresleri",
            "alici_email": "2zz@zz.com",
            "alici_telefon": "03523525252",
            "fatura_numarasi": "GRN2018000000017",
            "genel_toplam": "109.768,35",
            "mal_hizmet_toplam": "95.881,11",
            "tarih": "11-04-2018",
            "para": "28,00",
            "vergi_no": "9000068418",
            "telefon": "03523525252",
            "email": "2zz@zz.com",
            "kalemler": [
                {
                    "tutar": "İskonto | 2.69710TLİ",
                    "aciklama": "Toplam",
                    "tutar_num": 269710.0
                },
                {
                    "tutar": "KDV(%8) | 1119013",
                    "aciklama": "Hesaplanan",
                    "tutar_num": 81119013.0
                },
                {
                    "tutar": "KDV(9618)",
                    "aciklama": "Hesaplanan",
                    "tutar_num": 9618.0
                },
                {
                    "tutar": "109.768,35 Tutar Toplam",
                    "aciklama": "Dahil",
                    "tutar_num": 109768.35
                },
                {
                    "aciklama": "Vergiler",
                    "tutar": "109.768,35",
                    "tutar_num": 109768.35
                }
            ],
            "fatura_tarihi": "11-04-2018",
            "ettn": "29845814-fdfc-4fec-9652-1b49413550a0"
        }
    },
    {
        "dosya": "27.08.2025_Gelen Fatura (1)\\02.05.2023-YON2023341012345.pdf",
        "analiz_zamani": "2025-08-28 09:44:56",
        "ocr_istatistikleri": {
            "ortalama_guven_skoru": "62.36%",
            "toplam_kelime": 851,
            "gecerli_kelime": 392,
            "ham_metin_uzunlugu": 2307,
            "ham_metin": "Uyumsoft Bilgi Sistemleri ve Teknolojileri A.Ş. YTÜ Davutpaşa Kampüsü No:401 Esenler/ İstanbul Vergi Dairesi: Esenler VKN: 9000068418 MERSISNO: 12345669111 TICARETSICILNO: 12345669-111 —— eaten NERMİN _ Fatura Tint İ İİ NERMIN OZER atura Tipi: Fatura No: Düzenleme Tarihi: [12-04-2023 Düzenleme Saati: — (17:00:26 — | Sipariş Tarihi; — — (0205-2023 Sipariş Tarihi: Web Sitesi: Web Sitesi E-Posta: test@test.com Tel: 0212200022 Fax: 22111222 Vergi Dairesi: B.MUKELLEFLER VKN: 9000068418 ETTN: e2d0887e-1d6c-40fc-b2ca-9f1b1415db60 | Birim Fiyat tskome KDV Tutarı Diğer Vergiler Mal Hizmet Tutarı [SAG SIS FAR BRAKETİ | 552,90000000 m | 1 32 TY Adel TL) 000 TL _1.430,80 9.379,69 TL JÖN TAMPON DARBE EMİCİ| (1 Adet) 2.613,05000000 mİ 000TL 918,00 RADYATOR YEDEK SU 1 Adet) 2.029,62000000 0,00 TLİ %18,00| 182,67 | 1.197,48 TL 2.430,88 TL DEPOSU 1 enes DROS Ral Te] — | 000 İos — — eno) | Kapağı | — TH] 18,00) — 208427 TU DAVLUMBAZI | Adet 2.314,07000000 TL | TURBO RADYATÖRÜ HORTUMU MOTOR KAPUT MENTEŞESİ SAĞ 1.256,35000000 | 0,00 TL 18,00 113,07 MOTOR KAPUTU | 4 Adet|_26.200,31000000 m) | TL Bm) 235880371 15.458,18 TL 1 O |MOTOR KAPUTU EN MN un KE MEZ foe gous con İl — — 1 SiG GN m [00 4.581,41 TL ION TAMPON | Adet{ _8.679,33000000 | 120,80 TL oe [aera sana se] — — — 4 adet) 2.859,29000000 TU ZE ME TH (SAĞ SIS FAR BRAKETİ 1 Adeti (| 418,87000000 mİ 000TL %18,00| __37,70 TL| RADYATOR HAVA 1.352,41000000 nf | 0,00 TLİ %18,00] 121,72 0 2.832,00 TL 1 YÖNLENDİRİCİ SAĞ 6H SNOW Tİ 0.0074 paseo mi | ae — — — 2.488,65 TL [SAG ALT 7 | | ON TAŞIYICI | 9.035,06000000 71 TL i [ON PORYA | 1 Adet| 7.423,12000000 Tt ooonl % 18,00 668,08 4.379,64 TL 1 o İROTBAŞI | Oi 1.746,33000000 mİ TH NE EEE | __1Adet| | 969,03000000 mİ 000 TL 7 | JAMORTİSÖR ÜST TAKOZU | 1.255,53000000 mİ |. EE | 08 İl JÖN TAMPON DEMİRİ | 1 Adet) 12.160,90000000 nm) | 000TL) %18,00|__1.094,48 mİ 2174.93 TH 18.797,40 TL 1 İYÖNLENDİRİCİ 354 Adet 50,00000000 TH %18,00| 2.867,40 GENEL ONARIM İŞÇİLİĞİ MOTOR TRAVERS , JANT mae AKİS TAMİR 220 Adet 50,00000000 TL 0,00 TL| %18,00) (1.782,00 TL 11.682,00 TL Mal Hizmet Toplam Tutarı Toplam İskonto Hesaplanan KDV(%18) Vergiler Dahil Toplam Tutar Ödenecek Tutar 72.077,38 TL 17.538,73 TL 114.976,11 TL 114.976,11 TL 1RS000000001 (02-05-2023) | IRSO00000002 (02-05-2023) İrsaliye No ve Tarihleri :"
        },
        "regex": {
            "tarih": [
                "12-04-2023",
                "02-05-2023"
            ],
            "para": [
                "430,80",
                "9.379,69 TL",
                "918,00",
                "0,00",
                "18,00",
                "182,67",
                "1.197,48 TL",
                "2.430,88 TL",
                "0,00 TL",
                "113,07"
            ],
            "iban": [],
            "fatura_no": [],
            "vergi_no": [
                "9000068418"
            ],
            "tc_no": [],
            "telefon": [],
            "email": [
                "test@test.com"
            ],
            "fatura_tipi": [],
            "kdv_orani": [],
            "ettn": [
                "e2d0887e-1d6c-40fc-b2ca-9f1b1415db60"
            ],
            "mersis_no": [],
            "ticaret_sicil": [
                "12345669"
            ],
            "musteri_no": [],
            "mal_hizmet_kodu": [],
            "alici_ad_soyad": [],
            "alici_adres": [],
            "urun_aciklama": [],
            "urun_miktar": [
                "1",
                "4",
                "354",
                "220"
            ],
            "birim_fiyat": [],
            "odeme_sekli": [],
            "kargo_bilgisi": [],
            "siparis_no": [],
            "fatura_tarihi": [],
            "duzenleme_saati": [],
            "satici_vkn": [],
            "alici_vkn": [],
            "odenecek_tutar": [
                "72.077,38 TL"
            ],
            "doviz_kuru": [],
            "para_birimi": [
                "TL"
            ]
        },
        "structured": {
            "satici_vergi_numarasi": "12345669111",
            "alici_email": "test@test.com",
            "alici_telefon": "0212200022",
            "ettn": "e2d0887e-1d6c-40fc-b2ca-9f1b1415db60",
            "genel_toplam": "72.077,38",
            "tarih": "12-04-2023",
            "para": "430,80",
            "vergi_no": "9000068418",
            "email": "test@test.com",
            "ticaret_sicil": "12345669",
            "urun_miktar": "1",
            "odenecek_tutar": "72.077,38 TL",
            "para_birimi": "TL",
            "kalemler": [
                {
                    "aciklama": "32",
                    "tutar": "TY",
                    "kdv_orani": "1"
                },
                {
                    "aciklama": "— —"
                },
                {
                    "kdv_orani": "eno)",
                    "aciklama": "|"
                },
                {
                    "tutar": "TL 4.581,41 TL",
                    "aciklama": "120,80",
                    "tutar_num": 4581.41
                },
                {
                    "aciklama": "|",
                    "kdv_orani": "se]"
                },
                {
                    "aciklama": "0",
                    "tutar": "TL 2.832,00",
                    "kdv_orani": "0.0074",
                    "tutar_num": 2832.0
                },
                {
                    "tutar": "TL 2.488,65",
                    "kdv_orani": "ae",
                    "aciklama": "— — —",
                    "tutar_num": 2488.65
                },
                {
                    "aciklama": "|",
                    "kdv_orani": "7"
                },
                {
                    "tutar": "08",
                    "aciklama": "|",
                    "kdv_orani": "EE",
                    "tutar_num": 8.0
                },
                {
                    "aciklama": "2174.93",
                    "tutar": "TH"
                },
                {
                    "tutar": "TL 11.682,00",
                    "tutar_num": 11682.0
                },
                {
                    "aciklama": "Tutarı Toplam",
                    "kdv_orani": "Mal"
                },
                {
                    "tutar": "TL 72.077,38",
                    "aciklama": "İskonto Toplam",
                    "tutar_num": 72077.38
                },
                {
                    "tutar": "TL 17.538,73",
                    "aciklama": "KDV(%18)",
                    "tutar_num": 17538.73
                },
                {
                    "aciklama": "Tutar Toplam Dahil",
                    "tutar": "TL 114.976,11",
                    "tutar_num": 114976.11
                }
            ],
            "fatura_tarihi": "12-04-2023"
        }
    },
    {
        "dosya": "27.08.2025_Gelen Fatura (1)\\08.05.2023-YON2023341012340.pdf",
        "analiz_zamani": "2025-08-28 09:45:11",
        "ocr_istatistikleri": {
            "ortalama_guven_skoru": "57.72%",
            "toplam_kelime": 878,
            "gecerli_kelime": 410,
            "ham_metin_uzunlugu": 2361,
            "ham_metin": "Uyumsoft Bilgi Sistemleri ve Teknolojileri A.Ş. YTÜ Davutpaşa Kampüsü No:401 Esenler/ İstanbul Vergi Dairesi: Esenler VKN: 9000068418 MERSISNO: 12345669111 TICARETSICILNO: 12345669-111 e-FATURA SAYIN Özelleştirme No: TR1.2 NERMİN Senaryo: İTICARIFATURA ATAKENT MH ZÜBEYDE HN. CAD. NO:15/1 fratura Tipi: SA BAŞİSKELE/ KOCAELİ Fatura No: İYON2023341012340 Web Sitesi: Web Sitesi E-Posta: test@test.com Tel: 0212200022 Fax: 22111222 VKN: 9000068418 ETİN: 938f126d-4642-43d0-ad47-b45b82d01d04 Birim Fiyat | İskonto KDV KDV Tutarı Diğer Vergiler | Mal Hizmet Tutarı Oranı Tutarı Oranı | O İSAĞSİS FAR BRAKETİ 1 Adet (o 552,90000000TLİ % 18,00 (| 326,21 TL 1 O PANEL 1 Adet) 15.897,78000000 TL | Oo 09,00TL) %18,00| 14308071 (| 9.379,69 TL 1 JÖN TAMPON DARBEEMİCİ 2.613,05000000 TL| | TL| 9418,00 1.541,70 TL DEPOSU YEDEK SU 2.029,62000000 | 0,00 TLİ oo 182,67 | 1.197,48 TL i o o TL 1 DEPO OiAdetl 731,49000000TL| | TH 1 | iAdel 372,65000000TL| oO| oo Tt 33547) TL İÇAMURLUK DAVLUMBAZI | 2.314,07000000TL| o | Tu] 28277) << 0 TURBO RADYATÖRÜ BAĞLANTI SAĞ 1 Adet 959,19000000 no | 0,00 TL! %18,00 86,33 TL P| 565,92 TL YEDEK SU BIDON 9 HORTUMU 1 Adet 971,84000000 | 0,00 TL] %18,00 87,47 mo | 573,39 TL MOTOR KAPUT 9 MENTEŞESİ SAĞ 1 Adet} 1.256,35000000 | 0,00 TL] %18,00 113,07 no 741,25 TL 1 | TH oO| 18,00] 766,26 TL 1 | 3.23585000000Tİ 00 TL %18,00] O 21231) 1 at 7.765,10000000TL] 6886) | 1 | [oo Tt TH 1 | Adet 217,52000000TL| rt | 19587) 1 [ONTAMPON SAG AYAK | | | 15887 1 o İSAĞSISFARI o | Adet]_2.859,29000000T1] TL TL o İSAĞSİSFARBRAKETİ | zade | o 377010) TL RADYATÖR HAVA o YÖNLENDİRİCİ SAĞ 1 Adet| 1.352,41000000 | 0,00 TL] %18,00 121,72 mo 797,92 TL 1 | 1Adet| | o 420071 TL H İSAĞÖNAMORTİSÖR | | Tu] 33671) i | | TL o 4785571), << 1 | O 1 | iAdet 7423120000007) | o 1 (RorBaşı | O 15771) O HE (SAĞASNRoTu o o | iade) o | ooonlerso Ban 1 o o iAdet| | o TL (ÖNTAMPON DEMİRİ o | 12.160,90000000TL| 10946871 TL DEMİR ON ALT INCE 1 Adet] 4.270,47000000 no | 0,00 TLİ %18,00] 384,34 | 2.519,58 TL RADYATÖR HAVA g VONLENDIRICH 1 Adet) 1.175,34000000 | 0,00 TL| 9518,00) 105,78 U | 693,45 TL GENEL ONARIM İŞÇİLİĞİ | 354 Adet| © 50,00000000TU) %18,00| 2867407 0000 18.797,40 TL MOTOR TRAVERS , JANT AKİS TAMİR 220 Adet 50,00000000 no | 0,00 TL! %18,00] o 1.782,00 | 11.682,00 TL İrsaliye No ve Tarihleri : | 1RS000000001 (09-05-2023) | 1RS000000002 (09-05-2023)"
        },
        "regex": {
            "tarih": [
                "09-05-2023"
            ],
            "para": [
                "18,00",
                "326,21 TL",
                "09,00TL",
                "9.379,69 TL",
                "9418,00",
                "1.541,70 TL",
                "0,00",
                "182,67",
                "1.197,48 TL",
                "0,00 TL"
            ],
            "iban": [],
            "fatura_no": [
                "İYON202334101234"
            ],
            "vergi_no": [
                "9000068418"
            ],
            "tc_no": [],
            "telefon": [],
            "email": [
                "test@test.com"
            ],
            "fatura_tipi": [
                "e-FATURA"
            ],
            "kdv_orani": [],
            "ettn": [],
            "mersis_no": [],
            "ticaret_sicil": [
                "12345669"
            ],
            "musteri_no": [],
            "mal_hizmet_kodu": [],
            "alici_ad_soyad": [
                "Özelleştirme No"
            ],
            "alici_adres": [],
            "urun_aciklama": [],
            "urun_miktar": [
                "1",
                "354",
                "220"
            ],
            "birim_fiyat": [
                "09,00TL"
            ],
            "odeme_sekli": [],
            "kargo_bilgisi": [],
            "siparis_no": [],
            "fatura_tarihi": [],
            "duzenleme_saati": [],
            "satici_vkn": [],
            "alici_vkn": [],
            "odenecek_tutar": [],
            "doviz_kuru": [],
            "para_birimi": [
                "TL"
            ]
        },
        "structured": {
            "satici_firma_unvani": "Uyumsoft Bilgi Sistemleri Teknolojileri A.Ş.",
            "satici_vergi_numarasi": "9000068418",
            "satici_ticaret_sicil": "12345669",
            "alici_firma_unvani": "Özelleştirme No",
            "alici_email": "test@test.com",
            "alici_telefon": "0212200022",
            "fatura_numarasi": "İYON2023341012340",
            "genel_toplam": "18.797,40",
            "tarih": "09-05-2023",
            "para": "18,00",
            "fatura_no": "İYON202334101234",
            "vergi_no": "9000068418",
            "email": "test@test.com",
            "kalemler": [
                {
                    "birim_fiyat": "(o 1 Adet 552,90000000TLİ",
                    "tutar": "(|",
                    "kdv_orani": "% 18,00",
                    "aciklama": "326,21 TL",
                    "birim_fiyat_num": 1552.9
                },
                {
                    "kdv_orani": "Oo %18,00| 14308071",
                    "birim_fiyat": "TL 1 Adet) 15.897,78000000",
                    "aciklama": "9.379,69 TL",
                    "tutar": "(|",
                    "birim_fiyat_num": 115897.78
                },
                {
                    "birim_fiyat": "TL| 2.613,05000000",
                    "birim_fiyat_num": 2613.05
                },
                {
                    "tutar": "| 182,67",
                    "kdv_orani": "oo 0,00 TLİ",
                    "birim_fiyat": "2.029,62000000",
                    "birim_fiyat_num": 2029.62,
                    "tutar_num": 182.67
                },
                {
                    "birim_fiyat": "o",
                    "aciklama": "TL"
                },
                {
                    "birim_fiyat": "OiAdetl 731,49000000TL|",
                    "aciklama": "TH",
                    "birim_fiyat_num": 731.49
                },
                {
                    "aciklama": "TL",
                    "birim_fiyat": "| iAdel 372,65000000TL|",
                    "kdv_orani": "oo Tt",
                    "tutar": "33547)",
                    "birim_fiyat_num": 372.65,
                    "tutar_num": 33547.0
                },
                {
                    "birim_fiyat": "| 2.314,07000000TL|",
                    "kdv_orani": "Tu]",
                    "tutar": "28277) <<",
                    "aciklama": "0",
                    "birim_fiyat_num": 2314.07,
                    "tutar_num": 28277.0
                },
                {
                    "tutar": "P|",
                    "birim_fiyat": "no"
                },
                {
                    "birim_fiyat": "Adet 1 959,19000000",
                    "aciklama": "565,92 TL",
                    "kdv_orani": "0,00 TL! %18,00",
                    "tutar": "86,33 TL",
                    "birim_fiyat_num": 1959.19,
                    "tutar_num": 86.33
                },
                {
                    "aciklama": "|",
                    "tutar": "mo",
                    "birim_fiyat": "1 Adet 971,84000000",
                    "kdv_orani": "0,00 TL] 9 %18,00",
                    "birim_fiyat_num": 1971.84
                },
                {
                    "tutar": "87,47",
                    "aciklama": "573,39 TL",
                    "tutar_num": 87.47
                },
                {
                    "birim_fiyat": "1.256,35000000",
                    "kdv_orani": "0,00 TL] 9 %18,00",
                    "tutar": "113,07",
                    "aciklama": "741,25 TL",
                    "birim_fiyat_num": 1256.35,
                    "tutar_num": 113.07
                },
                {
                    "birim_fiyat": "|",
                    "aciklama": "TH"
                },
                {
                    "aciklama": "|",
                    "birim_fiyat": "7.765,10000000TL]",
                    "tutar": "6886)",
                    "birim_fiyat_num": 7765.1,
                    "tutar_num": 6886.0
                },
                {
                    "aciklama": "TH",
                    "birim_fiyat": "|",
                    "kdv_orani": "Tt"
                },
                {
                    "birim_fiyat": "|",
                    "kdv_orani": "|",
                    "tutar": "15887",
                    "tutar_num": 15887.0
                },
                {
                    "birim_fiyat": "o | Adet]_2.859,29000000T1]",
                    "kdv_orani": "TL",
                    "aciklama": "TL",
                    "birim_fiyat_num": 2859.290000001
                },
                {
                    "aciklama": "TL",
                    "birim_fiyat": "| zade",
                    "kdv_orani": "o",
                    "tutar": "377010)",
                    "tutar_num": 377010.0
                },
                {
                    "tutar": "mo"
                },
                {
                    "birim_fiyat": "1 Adet| 1.352,41000000",
                    "aciklama": "797,92 TL",
                    "kdv_orani": "0,00 TL] o %18,00",
                    "tutar": "121,72",
                    "birim_fiyat_num": 11352.41,
                    "tutar_num": 121.72
                },
                {
                    "birim_fiyat": "| 1Adet|",
                    "kdv_orani": "o",
                    "tutar": "420071",
                    "aciklama": "TL",
                    "birim_fiyat_num": 1.0,
                    "tutar_num": 420071.0
                },
                {
                    "birim_fiyat": "|",
                    "kdv_orani": "TL o",
                    "tutar": "4785571), <<",
                    "tutar_num": 4785571.0
                },
                {
                    "aciklama": "O",
                    "birim_fiyat": "|",
                    "kdv_orani": "O",
                    "tutar": "15771)",
                    "tutar_num": 15771.0
                },
                {
                    "birim_fiyat": "o | iade) o",
                    "kdv_orani": "ooonlerso",
                    "tutar": "Ban"
                },
                {
                    "birim_fiyat": "o iAdet|",
                    "kdv_orani": "o",
                    "aciklama": "TL"
                },
                {
                    "birim_fiyat": "o | 12.160,90000000TL|",
                    "kdv_orani": "10946871",
                    "aciklama": "TL",
                    "birim_fiyat_num": 12160.9
                },
                {
                    "birim_fiyat": "no",
                    "tutar": "|"
                },
                {
                    "birim_fiyat": "1 4.270,47000000",
                    "aciklama": "2.519,58 TL",
                    "kdv_orani": "0,00 TLİ %18,00]",
                    "tutar": "384,34",
                    "birim_fiyat_num": 14270.47,
                    "tutar_num": 384.34
                },
                {
                    "aciklama": "|",
                    "birim_fiyat": "1 Adet) 1.175,34000000",
                    "kdv_orani": "0,00 TL| g 9518,00)",
                    "tutar": "105,78 U",
                    "birim_fiyat_num": 11175.34,
                    "tutar_num": 105.78
                },
                {
                    "birim_fiyat": "| © 354 Adet| 50,00000000TU)",
                    "tutar": "0000",
                    "kdv_orani": "%18,00| 2867407",
                    "aciklama": "18.797,40 TL",
                    "birim_fiyat_num": 35450.0,
                    "tutar_num": 0.0
                },
                {
                    "birim_fiyat": "50,00000000",
                    "kdv_orani": "0,00 TL! %18,00] 1.782,00",
                    "aciklama": "11.682,00 TL",
                    "birim_fiyat_num": 50.0
                }
            ],
            "fatura_tarihi": "09-05-2023"
        }
    },
    {
        "dosya": "27.08.2025_Gelen Fatura (1)\\14.04.2023-BCK2023000000006.pdf",
        "analiz_zamani": "2025-08-28 09:46:02",
        "ocr_istatistikleri": {
            "ortalama_guven_skoru": "65.95%",
            "toplam_kelime": 213,
            "gecerli_kelime": 136,
            "ham_metin_uzunlugu": 891,
            "ham_metin": "II Ni Becker Coating Boya Sanayi ve Ticaret Ltd. Sti. . wees a Bess Güzeller Organize Sanayi Bölgesi, İnönü mah. Alptegin Sok. No.7 5 (G: 41400 Tel: 0262 502 00 80 a , Web Sitesi: www.beckers-group.com E-Posta: info-tr@beckers-group.com VKN: 9000068418 Senaryo: İTEMELFATURA Fatura No: > o (| a a a m m amm Saati: | (15:27:04 SAYIN Assan Aluminyum San.Tic.A.S. YAYLA MAH. D-100 KARAYOLURUYA SOK. N° 2 —— 34940 VKN: 9000068418 Döviz SSS ETİN: 7CA9B45F-818C-433A-BEED-DDBF5AAC52A2 | Teme | kent | JOY T ovma | [Mal Tatar BeckryPol 310 Monocoat 1 310 Monee! 200 450,00000000 EUR} 960,00) (0,00 EURİ %18,00]16.200,00 EUR 90.000,00 EUR MES1003 Platinum White Hesaplanan GERÇEK USULDE KATMA Hesaplanan GERÇEK USULDE KATMA BUalandaki bilgiler tüm faturalarda görülecektir. Ax Invoice No: TRCI0000020 Döviz kuru : 20.24000 TRY Mersis no: 0760046045500020 Ödeme Koşulu: Fatura vade tarihi: 2023-08-12"
        },
        "regex": {
            "tarih": [],
            "para": [
                "960,00",
                "0,00",
                "18,00",
                "16.200,00 EUR",
                "90.000,00 EUR"
            ],
            "iban": [],
            "fatura_no": [],
            "vergi_no": [
                "9000068418"
            ],
            "tc_no": [],
            "telefon": [],
            "email": [
                "info-tr@beckers-group.com"
            ],
            "fatura_tipi": [],
            "kdv_orani": [],
            "ettn": [],
            "mersis_no": [
                "076004604550002"
            ],
            "ticaret_sicil": [],
            "musteri_no": [],
            "mal_hizmet_kodu": [],
            "alici_ad_soyad": [
                "Assan Aluminyum San.Tic.A"
            ],
            "alici_adres": [],
            "urun_aciklama": [],
            "urun_miktar": [],
            "birim_fiyat": [],
            "odeme_sekli": [],
            "kargo_bilgisi": [],
            "siparis_no": [],
            "fatura_tarihi": [],
            "duzenleme_saati": [],
            "satici_vkn": [],
            "alici_vkn": [],
            "odenecek_tutar": [],
            "doviz_kuru": [
                "20.24000"
            ],
            "para_birimi": [
                "EUR",
                "TRY"
            ]
        },
        "structured": {
            "satici_firma_unvani": "II Ni Becker Coating wees Boya Bess Sanayi Ticaret Ltd.",
            "satici_vergi_numarasi": "9000068418",
            "satici_telefon": "0262 502 00 80",
            "satici_email": "info-tr@beckers-group.com",
            "alici_firma_unvani": "Assan Aluminyum San.Tic.A.S. YAYLA MAH. D",
            "alici_email": "info-tr@beckers-group.com",
            "alici_telefon": "0262 502 00 80",
            "genel_toplam": "960,00",
            "para": "960,00",
            "vergi_no": "9000068418",
            "email": "info-tr@beckers-group.com",
            "mersis_no": "076004604550002",
            "alici_ad_soyad": "Assan Aluminyum San.Tic.A",
            "doviz_kuru": "20.24000",
            "para_birimi": "EUR",
            "kalemler": [],
            "fatura_tarihi": "Fatura Tarihi:\n\n14-04-2023"
        }
    },
    {
        "dosya": "27.08.2025_Gelen Fatura (1)\\14.05.2024-HMF2024000000001.pdf",
        "analiz_zamani": "2025-08-28 09:46:03",
        "ocr_istatistikleri": {
            "ortalama_guven_skoru": "55.22%",
            "toplam_kelime": 189,
            "gecerli_kelime": 114,
            "ham_metin_uzunlugu": 654,
            "ham_metin": "ce ele rec ik Eker aa Ma VA , ot | GROUP 77 ay Ab rgi Dairesi: TOKAT VERGİ DAİRESİ LAI ON esiri 9000068418 eres a “fl “aT : on as e-FATURA Özelleştirme No: m2 ——— Nu OX AS. Fete nn. - ÖRNEK ADRES 14-05-2024 VEN: 9000068418 Düzenleme Tarihi: 14-05-2024 VEN: 9 a — Saati: (11:40:00 ETİN: set, Ei İskonto | İskonto KDV ae . . [ome] oe aS an oo _|xyz buzdolabi | Adet| 32.740,00000000 920,00) 13.096,00 1 65.480,00 TL Mal Hizmet Toplam Tutarı 65.480,00 TL Toplam İskonto 0,00 TU Hesaplanan KDV(%20.00) 13.096,00 TL Vergiler Dahil Toplam Tutar 78.576,00 TL Ödenecek Tutar 78.576,00 TL #YALNIZ YETMİŞSEKİZBİNBEŞYÜZYETMİŞALTI TRL# Sevk Adresi : A.Ş. sevk adresi"
        },
        "regex": {
            "tarih": [
                "14-05-2024"
            ],
            "para": [
                "920,00",
                "13.096,00",
                "65.480,00 TL",
                "0,00",
                "13.096,00 TL",
                "78.576,00 TL"
            ],
            "iban": [],
            "fatura_no": [],
            "vergi_no": [],
            "tc_no": [],
            "telefon": [],
            "email": [],
            "fatura_tipi": [
                "e-FATURA"
            ],
            "kdv_orani": [],
            "ettn": [],
            "mersis_no": [],
            "ticaret_sicil": [],
            "musteri_no": [],
            "mal_hizmet_kodu": [],
            "alici_ad_soyad": [],
            "alici_adres": [],
            "urun_aciklama": [],
            "urun_miktar": [],
            "birim_fiyat": [],
            "odeme_sekli": [],
            "kargo_bilgisi": [],
            "siparis_no": [],
            "fatura_tarihi": [],
            "duzenleme_saati": [],
            "satici_vkn": [],
            "alici_vkn": [],
            "odenecek_tutar": [
                "78.576,00 TL"
            ],
            "doviz_kuru": [],
            "para_birimi": [
                "TL"
            ]
        },
        "structured": {
            "satici_firma_unvani": "Sevk A.Ş.",
            "genel_toplam": "78.576,00",
            "toplam_iskonto": "0,00",
            "mal_hizmet_toplam": "65.480,00",
            "tarih": "14-05-2024",
            "para": "920,00",
            "kalemler": [],
            "fatura_tarihi": "14-05-2024"
        }
    },
    {
        "dosya": "27.08.2025_Gelen Fatura (1)\\19.06.2025-KSN2025000000002.pdf",
        "analiz_zamani": "2025-08-28 09:46:03",
        "ocr_istatistikleri": {
            "ortalama_guven_skoru": "57.47%",
            "toplam_kelime": 148,
            "gecerli_kelime": 89,
            "ham_metin_uzunlugu": 574,
            "ham_metin": "wees OZNUR KESKIN elias NİKSAR/ TOKAT EL ON Tel: (555) 5555555Fax( ) ee! E-Posta: oznur.ozden@uyumsoft.com AS G Vergi Dairesi: NIKSAR “Nek wet VKN: 9000068418 << e-FATURA m SAYIN ect Senaryo: o — | UYUMSOFT BİLGİ SİSTEMLERİ SİVAS — Fatura Tipi: ADALAR/ ISTANBUL Fatura No: _[ksn2025000000002 Vergi Dairesi: POZANTI VEN: 9000068418 ETİN: Tee | SE Tam ri Taa 2 | see sop] nm | 0,007 Hesaplanan GERÇEK USULDE KATMA 1$ bu fatura = 90.000,00 TRY, Kur:1,000000 Karşılığı 90.000,00 TL dir. KSN2025000000002 UYUMSOFT BİLGİ SİSTEMLERİ SİVASNOLU FATURA UYUMSOFT BİLGİ SİSTEMLERİ SİVAS"
        },
        "regex": {
            "tarih": [],
            "para": [
                "90.000,00 TRY",
                "90.000,00 TL"
            ],
            "iban": [],
            "fatura_no": [],
            "vergi_no": [
                "9000068418"
            ],
            "tc_no": [],
            "telefon": [],
            "email": [
                "oznur.ozden@uyumsoft.com"
            ],
            "fatura_tipi": [
                "e-FATURA"
            ],
            "kdv_orani": [],
            "ettn": [],
            "mersis_no": [],
            "ticaret_sicil": [],
            "musteri_no": [],
            "mal_hizmet_kodu": [],
            "alici_ad_soyad": [
                "ect Senaryo"
            ],
            "alici_adres": [],
            "urun_aciklama": [],
            "urun_miktar": [],
            "birim_fiyat": [],
            "odeme_sekli": [],
            "kargo_bilgisi": [],
            "siparis_no": [],
            "fatura_tarihi": [],
            "duzenleme_saati": [],
            "satici_vkn": [],
            "alici_vkn": [],
            "odenecek_tutar": [],
            "doviz_kuru": [],
            "para_birimi": [
                "TRY",
                "TL"
            ]
        },
        "structured": {
            "satici_vergi_dairesi": "NIKSAR",
            "satici_vergi_numarasi": "9000068418",
            "satici_email": "oznur.ozden@uyumsoft.com",
            "alici_firma_unvani": "ect Senaryo",
            "alici_email": "oznur.ozden@uyumsoft.com",
            "alici_telefon": "(555) 5555555",
            "fatura_numarasi": "ksn2025000000002",
            "fatura_tipi": "ADALAR",
            "genel_toplam": "90.000,00",
            "para": "90.000,00 TRY",
            "vergi_no": "9000068418",
            "email": "oznur.ozden@uyumsoft.com",
            "alici_ad_soyad": "ect Senaryo",
            "para_birimi": "TRY",
            "kalemler": [],
            "fatura_tarihi": "18-06-2025",
            "ettn": "89091ae5-38d3-420f-bfb2-635181ce19a8"
        }
    },
    {
        "dosya": "27.08.2025_Gelen Fatura (1)\\16.06.2025-SAM2025000000015.pdf",
        "analiz_zamani": "2025-08-28 09:46:04",
        "ocr_istatistikleri": {
            "ortalama_guven_skoru": "78.53%",
            "toplam_kelime": 241,
            "gecerli_kelime": 183,
            "ham_metin_uzunlugu": 1294,
            "ham_metin": "SAMM TEKNOLOJİ İLETİŞİM SAN. VE TIC.A.S. Gebze Organize Sanayi Bölgesi (GOSB) İhsandede Cd. 800. Sok > = No: 802 Gebze ON KOCAELİ Tel: İlyasbey Fax: 0 262 677 1681 Ne YA Web Sitesi: www.samm.com NG A E-Posta: muhasebe@samm.com Vergi Dairesi: İlyasbey VKN: 9000068418 70 e-FATURA SAYIN Özelleştirme No: İTR1.2 Kormas Elektrikli Motor San. ve Tic. A.Ş. Senaryo: İTICARIFATURA San. İhtisas Bölgesi, 1. Cd. No: 30, Fatura Tipi: SATIS ÇAYIROVA/ KOCAELİ 2 Fatura No: E-Posta: busrakocoglu@kormas.com Fatura Tarihi: | oo |16:06:2025 Vergi Dairesi: İLYASBEY Cx fo) Düzenleme Saati: o (00:00:00 VKN: 9000068418 L. Sipariş No: 114314 ETİN: 37B09D26-CD76-0C7A-E063-6500000AA366 CE o elm İskonto | | KDV ay . Se) | Miktar) Birim Fiyat Tutarı KDV Tutarı Diğer Vergiler | Mal Hizmet Tutarı 963205-1 FACIAL SEAL, 5.000 1 6POS, SILICONE, Ad et 15,91620000 TL 20,00) 15.916,20 TL 79.581,00 TL NATURAL Mal Hizmet Toplam Tutarı 79.581,00 TL Toplam | Hesaplanan Gerçek Usulde Katma Değer Vergisi(9/020) 15.916,20 TL Vergiler Dahil Toplam Tutar 95.497,20 TL Ödenecek Tutar) (| 95.497,20 TL Oracle Sipariş No:114314 YALNIZ: DoksanBeşBinDörtYüzDoksanYediTürklirasıYirmiKuruş Ödeme Koşulu:Peşin Geri bildirimlerinize değer veriyoruz. Değerli geri bildirimlerinizi paylaşmak için aşağıdaki bağlantıya tiklayabilirsiniz,"
        },
        "regex": {
            "tarih": [],
            "para": [
                "20,00",
                "15.916,20 TL",
                "79.581,00 TL",
                "95.497,20 TL"
            ],
            "iban": [],
            "fatura_no": [],
            "vergi_no": [
                "9000068418"
            ],
            "tc_no": [],
            "telefon": [],
            "email": [
                "muhasebe@samm.com",
                "busrakocoglu@kormas.com"
            ],
            "fatura_tipi": [
                "e-FATURA"
            ],
            "kdv_orani": [],
            "ettn": [],
            "mersis_no": [],
            "ticaret_sicil": [],
            "musteri_no": [],
            "mal_hizmet_kodu": [],
            "alici_ad_soyad": [
                "Özelleştirme No"
            ],
            "alici_adres": [],
            "urun_aciklama": [],
            "urun_miktar": [],
            "birim_fiyat": [],
            "odeme_sekli": [],
            "kargo_bilgisi": [],
            "siparis_no": [
                "114314"
            ],
            "fatura_tarihi": [],
            "duzenleme_saati": [],
            "satici_vkn": [],
            "alici_vkn": [],
            "odenecek_tutar": [],
            "doviz_kuru": [],
            "para_birimi": [
                "TL"
            ]
        },
        "structured": {
            "satici_vergi_numarasi": "9000068418",
            "alici_firma_unvani": "Özelleştirme No",
            "alici_email": "muhasebe@samm.com",
            "fatura_tipi": "SATIS ÇAYIROVA",
            "siparis_no": "114314",
            "genel_toplam": "95.497,20",
            "para": "20,00",
            "vergi_no": "9000068418",
            "email": "muhasebe@samm.com",
            "alici_ad_soyad": "Özelleştirme No",
            "para_birimi": "TL",
            "kalemler": [],
            "fatura_numarasi": "E-Posta"
        }
    },
    {
        "dosya": "27.08.2025_Gelen Fatura (1)\\23.05.2023-HRC2023000000018.pdf",
        "analiz_zamani": "2025-08-28 09:46:04",
        "ocr_istatistikleri": {
            "ortalama_guven_skoru": "58.88%",
            "toplam_kelime": 186,
            "gecerli_kelime": 114,
            "ham_metin_uzunlugu": 730,
            "ham_metin": "hicran mühendislik TOKAT MERKEZ/ TOKAT SEL a a pres (6) A Op eso Tel: (2 : Vergi Dairesi: 19 MAYIS wish CE a Sze 2 “PB EU e-FATURA (a) eee Özelleştirme No: TR1.2 SAVIN ei UYUMSOFT BİLGİ SİSTEMLERİ. — Fatura Tipi: HDHSKHFKSHF TOKAT MERKEZ/ TOKAT İFatura No: Vergi Dairesi: İSTİKLAL 23-05-2023 VEN: 9000068418 Tarihi: | [23-05-2023 ETİN: 7bf2ad45-ed3f-4f18-9450-3330a751ce00 e İskonto | İskonto | KDV ay EM a | 1 |sigorta poliçesi 17,4 Adet) 7.500,00000000 TL) = =| (O 23.490,00TL| (| 130.500,00 TL 130.500,00 TL 0,00 TL Hesaplanan TL Vergiler Dahil Toplam Tutar) 153.990,00 TL 153.990,00 TL #YALNIZ YÜZELLİÜÇBİNDOKUZYÜZDOKSAN TRY # İş bu fatura = 153.990,00 TRY, Kur:1,000000 Karşılığı 153.990,00 TL dir. UYUMSOFT BİLGİ SİSTEMLERİ."
        },
        "regex": {
            "tarih": [
                "23-05-2023"
            ],
            "para": [
                "23.490,00TL",
                "130.500,00 TL",
                "0,00 TL",
                "153.990,00 TL",
                "153.990,00 TRY"
            ],
            "iban": [],
            "fatura_no": [],
            "vergi_no": [],
            "tc_no": [],
            "telefon": [],
            "email": [],
            "fatura_tipi": [
                "e-FATURA"
            ],
            "kdv_orani": [],
            "ettn": [],
            "mersis_no": [],
            "ticaret_sicil": [],
            "musteri_no": [],
            "mal_hizmet_kodu": [],
            "alici_ad_soyad": [],
            "alici_adres": [],
            "urun_aciklama": [],
            "urun_miktar": [
                "2",
                "4"
            ],
            "birim_fiyat": [
                "500,00000000 TL"
            ],
            "odeme_sekli": [],
            "kargo_bilgisi": [],
            "siparis_no": [],
            "fatura_tarihi": [],
            "duzenleme_saati": [],
            "satici_vkn": [],
            "alici_vkn": [],
            "odenecek_tutar": [],
            "doviz_kuru": [],
            "para_birimi": [
                "TL",
                "TRY"
            ]
        },
        "structured": {
            "alici_telefon": "(2",
            "fatura_tipi": "HDHSKHFKSHF TOKAT MERKEZ",
            "genel_toplam": "153.990,00",
            "tarih": "23-05-2023",
            "para": "23.490,00TL",
            "urun_miktar": "2",
            "kalemler": [],
            "fatura_numarasi": "HRC2023000000018",
            "fatura_tarihi": "23-05-2023"
        }
    },
    {
        "dosya": "27.08.2025_Gelen Fatura (1)\\19.03.2024-SND2024000000008.pdf",
        "analiz_zamani": "2025-08-28 09:46:05",
        "ocr_istatistikleri": {
            "ortalama_guven_skoru": "58.10%",
            "toplam_kelime": 239,
            "gecerli_kelime": 149,
            "ham_metin_uzunlugu": 941,
            "ham_metin": "eres en r ot ace NETCOM Be zorunlu PEELS o 3 Flite: ah b 38700 ZORUNLU/ ZORUNLU Vergi Dairesi: MERKEZ nat VKN: 9000068418 Nee Ree ate . Sa; ki b PON na e-FATURA Eli Sel n ai yo: TICARIFATURA KOÇAK PIRLANTA Fatura Tipi: SATIS Yildinm Beyazıd mah. mevlana cad BAL AP 04000 HAMUR/ AĞRI Fatura No: Vergi Dates Ağ Fatura Tari VKN: 9000068418 18-03-2024 Saati: İ08:51:49 ETİN: 38977a42-20c4-429c-9c27-eef261d9b4fd İskonto | İskonto KDV ay . sass EEE %5,00] 1.666,67 TL 2620,00) SSS 31.666,67 TL 2 İHP BİLGİSAYAR | 1 Adet) 37.500,00000000 71 905,00) 1.875,00 TL 5.698 5 BiLGisavaR | 1 Adet) 41.666,66666700 TL Ye5,00) 2.083,33 TL| 2816671) İİ 59.583 33 Mal Hizmet Toplam Tutarı 112.500,00 TL Toplam İskonto | Hesaplanan KDV(%20) | Vergiler Dahil Toplam Tutar 128.250,00 TL Ödenecek Tutar 128.250,00 TL Sicil No: Mersis No: 1616161616161616 İşletme Merkezi; ZORUNLU YAZI ILE: YüzYirmiSekizBinİkiYüzElli TL Odeme Notu: VADE TARİHİ: 2024-03-18 (PESIN)"
        },
        "regex": {
            "tarih": [
                "18-03-2024"
            ],
            "para": [
                "5,00",
                "1.666,67 TL",
                "2620,00",
                "31.666,67 TL",
                "905,00",
                "1.875,00 TL",
                "2.083,33 TL",
                "112.500,00 TL",
                "128.250,00 TL"
            ],
            "iban": [],
            "fatura_no": [],
            "vergi_no": [
                "9000068418"
            ],
            "tc_no": [],
            "telefon": [],
            "email": [],
            "fatura_tipi": [
                "e-FATURA"
            ],
            "kdv_orani": [],
            "ettn": [],
            "mersis_no": [
                "161616161616161"
            ],
            "ticaret_sicil": [],
            "musteri_no": [],
            "mal_hizmet_kodu": [],
            "alici_ad_soyad": [],
            "alici_adres": [],
            "urun_aciklama": [],
            "urun_miktar": [
                "1"
            ],
            "birim_fiyat": [],
            "odeme_sekli": [],
            "kargo_bilgisi": [],
            "siparis_no": [],
            "fatura_tarihi": [],
            "duzenleme_saati": [],
            "satici_vkn": [],
            "alici_vkn": [],
            "odenecek_tutar": [
                "128.250,00 TL"
            ],
            "doviz_kuru": [],
            "para_birimi": [
                "TL"
            ]
        },
        "structured": {
            "satici_vergi_dairesi": "Flite",
            "satici_vergi_numarasi": "9000068418",
            "fatura_tipi": "SATIS Yildinm Beyazıd mah",
            "genel_toplam": "128.250,00",
            "mal_hizmet_toplam": "112.500,00",
            "tarih": "18-03-2024",
            "para": "5,00",
            "vergi_no": "9000068418",
            "mersis_no": "161616161616161",
            "urun_miktar": "1",
            "odenecek_tutar": "128.250,00 TL",
            "para_birimi": "TL",
            "kalemler": [],
            "fatura_numarasi": "SND2024000000008",
            "fatura_tarihi": "Fatura Tarihi:\n\n18-03-2024"
        }
    },
    {
        "dosya": "27.08.2025_Gelen Fatura (1)\\18.05.2023-CWF2023000000010.pdf",
        "analiz_zamani": "2025-08-28 09:46:05",
        "ocr_istatistikleri": {
            "ortalama_guven_skoru": "65.57%",
            "toplam_kelime": 275,
            "gecerli_kelime": 186,
            "ham_metin_uzunlugu": 1457,
            "ham_metin": "TR mm MARK'S TURKEY COMPANY RI 4 1 MAIN STREET 73 SON tot 10000 KONAKPINAR/ Balikesir ke ff z Pao Vergi Dairesi: Istanbul Ae i ary) i VKN: 9000068418 Nees. Al SUBENO: MBR set, LER TICARETSICILNO: TRN9000068418 a vi MERSISNO: MER9000068418 e-FATURA SAYIN AKB SHIPPING COMPANY ABC STREET AKBAL PLAZA KAT:3 NO:317 Özelleştirme No: 34440 KADIKOY/ Istanbul TEMELE E-Posta: akn@akborg.com EMELFATURA . Tel: +902163555555 SATIS Vergi Dairesi: KADIKOY Fatura No: VKN: 9000068418 18-05-2023 Düzenleme Tarihi: 18-05-2023 ETTİN: b71a16e5-8a5d-47f2-90ee-bb68deSb573b İskonto | İskonto KDV ay . . wine e Documentation) | |... 35.000,00000000 İ | | 6.300,00 35.000,00 TL na atan Other 1 3.000,00000000 TL İN 540,00 TL | 3.000,00 TL 3 JUluslararası Tasimaciik | 1 Adet) 2.000,00000000 TL HN 618,00 | 720,00 4.000,00 TL 8 Surcharge | 1 Adet{100.000,00000000 TL oC 18.000,00 TL 100.000,00 TL Mal Hizmet Toplam Tutarı 142.000,00 TL Toplam İskonto Hesaplanan KDV(%18) 25.560,00 TL Vergiler Dahil Toplam Tutar 167.560,00 TL 167.560,00 TL InvoiceDescription (S00004476 BranchAddress|Sube Adresi: 1 MAIN STREET OrganizationContact|ilgil: AKN CurrencyToString]Yalniz yüzaltmışyedibinbeşyüzaltmış TRY InvoiceMessage|Please contact us within 7 days should there be any discrepancies, LocalTotalTax-18/142000.00,25560.00 LocalLegalMoney-TaxExclusiveAmount|142000.00 LocalLegalMoney-TaxInclusiveAmount|167560.00 LocalLegalMoney-PayableAmount!167560.00 Hesap Aciklamasi: BANK OF TURKEY"
        },
        "regex": {
            "tarih": [
                "18-05-2023"
            ],
            "para": [
                "6.300,00",
                "35.000,00 TL",
                "540,00 TL",
                "3.000,00 TL",
                "618,00",
                "720,00",
                "4.000,00 TL",
                "18.000,00 TL",
                "100.000,00 TL",
                "142.000,00 TL"
            ],
            "iban": [],
            "fatura_no": [],
            "vergi_no": [
                "9000068418"
            ],
            "tc_no": [],
            "telefon": [
                "+902163555555"
            ],
            "email": [
                "akn@akborg.com"
            ],
            "fatura_tipi": [
                "e-FATURA"
            ],
            "kdv_orani": [],
            "ettn": [],
            "mersis_no": [],
            "ticaret_sicil": [],
            "musteri_no": [],
            "mal_hizmet_kodu": [],
            "alici_ad_soyad": [
                "AKB SHIPPING COMPANY ABC"
            ],
            "alici_adres": [],
            "urun_aciklama": [],
            "urun_miktar": [
                "1"
            ],
            "birim_fiyat": [],
            "odeme_sekli": [],
            "kargo_bilgisi": [],
            "siparis_no": [],
            "fatura_tarihi": [],
            "duzenleme_saati": [],
            "satici_vkn": [],
            "alici_vkn": [],
            "odenecek_tutar": [],
            "doviz_kuru": [],
            "para_birimi": [
                "TL",
                "TRY"
            ]
        },
        "structured": {
            "satici_firma_unvani": "Nees. MBR i TICARET",
            "satici_vergi_dairesi": "ke Istanbul z i VKN",
            "satici_vergi_numarasi": "9000068418",
            "alici_firma_unvani": "AKB SHIPPING COMPANY ABC STREET AKBAL PLAZA KAT",
            "alici_email": "akn@akborg.com",
            "alici_telefon": "+902163555555",
            "genel_toplam": "167.560,00",
            "mal_hizmet_toplam": "142.000,00",
            "tarih": "18-05-2023",
            "para": "6.300,00",
            "vergi_no": "9000068418",
            "telefon": "+902163555555",
            "email": "akn@akborg.com",
            "kalemler": [],
            "fatura_numarasi": "Icwr2023000000010",
            "fatura_tarihi": "18-05-2023"
        }
    },
    {
        "dosya": "27.08.2025_Gelen Fatura (1)\\15.03.2024-SND2024000000004.pdf",
        "analiz_zamani": "2025-08-28 09:46:05",
        "ocr_istatistikleri": {
            "ortalama_guven_skoru": "63.22%",
            "toplam_kelime": 240,
            "gecerli_kelime": 158,
            "ham_metin_uzunlugu": 1051,
            "ham_metin": "NETCOM e zorunlu EN Dea eme 38700 ZORUNLU/ ZORUNLU o: Be 2 4 ME ek Vergi Dairesi: MERKEZ Ne iş), VKN: 9000068418 aaa > . e-FATURA faye EŞİ ‘ SS ee pa SAYIN İTICARIFATURA KOÇAK PIRLANTA Fatura Tipi Beyazıd mgh, mevlana cad BAL AP Fatura No: | 04000 HAMUR/ AĞRI _ SND2024000000004 Vergi Dairesi: AĞRI Fatura Tarihi: VEN: 9000068418 Düzenleme Tarihi: (15-03-2024 Düzenleme Saati: 112928 İİ ETİN: 27d06435-9c77-4a8f-8148-828bb7b63e84 Birim Fiyat İskonto | İskonto KDV KDV Tutarı Diğer Vergiler | Mal Hizmet Tutarı Oranı Tutarı Oranı | |ALDA GENC ODASI 20.633,33333300TL| 4.166,67 | 208333371 KULA GENÇ ODASI 1 Adet) 33.333,33333300 (20,00) EE EEE MİNA GENÇ ODASI 1 Adet) 37.500,00000000 TL) 0 | (20,00) 7.500,00 37.500,00 TL Mal Hizmet Toplam Tutarı 91.666,67 TL Toplam İskonto TL Hesaplanan KDV(%20) 18.333,33 TL Vergiler Dahil Toplam Tutar 109.999,99 TL Ödenecek Tutar) (109.999,99 TL Sicil No: Mersis No: 1616161616161616 İşletme Merkezi: ZORUNLU YAZI İLE: YüzDokuzBinDokuzYüzDoksanDokuz TL DoksanDokuz Kuruş Ödeme Notu: VADE TARİHİ: 2024-03-15 (PEŞİN)"
        },
        "regex": {
            "tarih": [
                "15-03-2024"
            ],
            "para": [
                "4.166,67",
                "20,00",
                "7.500,00",
                "37.500,00 TL",
                "91.666,67 TL",
                "18.333,33 TL",
                "109.999,99 TL"
            ],
            "iban": [],
            "fatura_no": [],
            "vergi_no": [
                "9000068418"
            ],
            "tc_no": [],
            "telefon": [],
            "email": [],
            "fatura_tipi": [
                "e-FATURA"
            ],
            "kdv_orani": [],
            "ettn": [],
            "mersis_no": [
                "161616161616161"
            ],
            "ticaret_sicil": [],
            "musteri_no": [],
            "mal_hizmet_kodu": [],
            "alici_ad_soyad": [
                "İTICARIFATURA KOÇAK"
            ],
            "alici_adres": [],
            "urun_aciklama": [],
            "urun_miktar": [
                "1"
            ],
            "birim_fiyat": [
                "500,00000000 TL"
            ],
            "odeme_sekli": [],
            "kargo_bilgisi": [],
            "siparis_no": [],
            "fatura_tarihi": [],
            "duzenleme_saati": [],
            "satici_vkn": [],
            "alici_vkn": [],
            "odenecek_tutar": [],
            "doviz_kuru": [],
            "para_birimi": [
                "TL"
            ]
        },
        "structured": {
            "alici_firma_unvani": "İTICARIFATURA KOÇAK PIRLANTA Fatura Tipi Beyazıd mgh",
            "fatura_numarasi": "SND2024000000004",
            "fatura_tipi": "Beyazıd mgh",
            "genel_toplam": "109.999,99",
            "tarih": "15-03-2024",
            "para": "4.166,67",
            "vergi_no": "9000068418",
            "mersis_no": "161616161616161",
            "alici_ad_soyad": "İTICARIFATURA KOÇAK",
            "urun_miktar": "1",
            "kalemler": [
                {
                    "aciklama": "EE",
                    "tutar": "EEE"
                },
                {
                    "tutar": "TL",
                    "aciklama": "37.500,00"
                },
                {
                    "tutar": "TL",
                    "aciklama": "91.666,67 Tutarı Toplam",
                    "kdv_orani": "Mal"
                },
                {
                    "tutar": "TL",
                    "aciklama": "İskonto"
                },
                {
                    "tutar": "TL",
                    "aciklama": "18.333,33 KDV(%20)"
                }
            ],
            "fatura_tarihi": "Fatura Tarihi: 15-03-2024"
        }
    },
    {
        "dosya": "27.08.2025_Gelen Fatura (1)\\22.05.2023-ARD2023000000022.pdf",
        "analiz_zamani": "2025-08-28 09:46:05",
        "ocr_istatistikleri": {
            "ortalama_guven_skoru": "58.33%",
            "toplam_kelime": 211,
            "gecerli_kelime": 135,
            "ham_metin_uzunlugu": 879,
            "ham_metin": "Bi Pal 51 ya e TEST Uhap Kullanıcısı douche oy Cher , aa\" 5 4 ie. ° CANKAYA/ ANKARA 1 Tel: 5555555555 fe ot m ww a6 ie E-Posta: info@info.com No. 7) tre eke ae Vergi Dairesi: Çankaya Vergi Dairesi Müdürlüğü İNE ght VKN: 0730712912 7 eA TICARETSICILNO: 555555 as MERSISNO: 5555555555555555 e-FATURA aa Ozellestirme No: TR1.2 SAYIN — Fatura Tip se — Uyumsoft Bilgi Sistem.ve Tekno.Tic.A.Ş. ARD2023000000022 06500 Merkez/ ANKARA Fatura Tarihi: VKN: 9000068418 Düzenleme Tarihi: [22-05-2023 —— MM ---....., Düzenleme Saati; 00:00:00 “cae3a82-(911-449c-aac7-2a22f1746dc0 İskonto | İskonto KDV wy . . amman [itor [on [nana a KE 100,00000000 TL} TL %18,00 18.000,00 yo 100.000,00 TL Mal Hizmet Toplam Tutarı 100.000,00 TL Toplam İskonto | 0,00 Hesaplanan KDV(%18.00) 18.000,00 TL Vergiler Dahil Toplam Tutar 118.000,00 TL Ödenecek Tutar 118.000,00 TL Yalnız YüzOnSekizBin TL Sifir Kuruş"
        },
        "regex": {
            "tarih": [
                "22-05-2023"
            ],
            "para": [
                "18,00",
                "18.000,00",
                "100.000,00 TL",
                "0,00",
                "18.000,00 TL",
                "118.000,00 TL"
            ],
            "iban": [],
            "fatura_no": [],
            "vergi_no": [
                "0730712912",
                "9000068418"
            ],
            "tc_no": [],
            "telefon": [],
            "email": [
                "info@info.com"
            ],
            "fatura_tipi": [
                "e-FATURA"
            ],
            "kdv_orani": [],
            "ettn": [],
            "mersis_no": [
                "555555555555555"
            ],
            "ticaret_sicil": [
                "555555"
            ],
            "musteri_no": [],
            "mal_hizmet_kodu": [],
            "alici_ad_soyad": [],
            "alici_adres": [],
            "urun_aciklama": [],
            "urun_miktar": [],
            "birim_fiyat": [],
            "odeme_sekli": [],
            "kargo_bilgisi": [],
            "siparis_no": [],
            "fatura_tarihi": [],
            "duzenleme_saati": [],
            "satici_vkn": [],
            "alici_vkn": [],
            "odenecek_tutar": [
                "118.000,00 TL"
            ],
            "doviz_kuru": [],
            "para_birimi": [
                "TL"
            ]
        },
        "structured": {
            "satici_vergi_dairesi": "No",
            "satici_vergi_numarasi": "0730712912",
            "alici_email": "info@info.com",
            "alici_telefon": "5555555555",
            "fatura_numarasi": "ARD2023000000022",
            "genel_toplam": "118.000,00",
            "mal_hizmet_toplam": "100.000,00",
            "tarih": "22-05-2023",
            "para": "18,00",
            "vergi_no": "0730712912",
            "email": "info@info.com",
            "kalemler": [],
            "fatura_tarihi": "Fatura Tarihi: 22-05-2023"
        }
    },
    {
        "dosya": "27.08.2025_Gelen Fatura (1)\\19.06.2025-MM12025000000009.pdf",
        "analiz_zamani": "2025-08-28 09:46:07",
        "ocr_istatistikleri": {
            "ortalama_guven_skoru": "69.96%",
            "toplam_kelime": 207,
            "gecerli_kelime": 147,
            "ham_metin_uzunlugu": 914,
            "ham_metin": "MERT - OZNUR - ELİF EĞİTİM FİRMASI Joe Be AAA A AAA , a TOKAT MERKEZ/ TOKAT ae Yo Tek( ) ——Fe( ) _ Ng. j E-Posta: mert.alparsian@uyumsoft.com Ne Ay is. Vergi Dairesi: 19 MAYıs be VKN: 9000068418 No: TR1.2 Senaryo: oo — SIN SATIS SAYIN Fatura No: J a Ni MM12025000000009 UYUMSOFT Bit Gi SİSTEMLERİ Sivas 7 AAAAAA Fatura Tarihi; Vergi Dairesi: POZANTI Düzenleme Saati: VKN: 9000068418 İrsaliye No: MRT2025000000004 ETİN: İrsaliye Tarihi; 17-06-2025 ETİN; SCS sormam Tör Ta | (1 TAPPLE IPHONE 15 | 2 Adet| 34.000,00000000 TL %20,00] 13.600,00 68.000,00 TL Mal Hizmet Toplam Tutarı TL Toplam İskonto | Hesaplanan GERÇEK USULDE KATMA DEĞER VERGISI(%20,00) 13.600,00 TL Vergiler Dahil Toplam Tutar 81.600,00 TL Ödenecek O 81.600,00 TL #YALNIZ SEKSENBİRBİNALTIYÜZ TRY # İŞ bu fatura = 81.600,00 TRY, Kur:1,000000 Karşılığı 81.600,00 TL dir. MM12025000000009 Numaralı fatura Sevk Adresi : AAA AAA TOKAT ALMUS 60100 TÜRKİYE"
        },
        "regex": {
            "tarih": [
                "17-06-2025"
            ],
            "para": [
                "20,00",
                "13.600,00",
                "68.000,00 TL",
                "13.600,00 TL",
                "81.600,00 TL",
                "81.600,00 TRY"
            ],
            "iban": [],
            "fatura_no": [],
            "vergi_no": [
                "9000068418"
            ],
            "tc_no": [],
            "telefon": [],
            "email": [
                "mert.alparsian@uyumsoft.com"
            ],
            "fatura_tipi": [],
            "kdv_orani": [],
            "ettn": [],
            "mersis_no": [],
            "ticaret_sicil": [],
            "musteri_no": [],
            "mal_hizmet_kodu": [],
            "alici_ad_soyad": [
                "Fatura No"
            ],
            "alici_adres": [],
            "urun_aciklama": [],
            "urun_miktar": [
                "2"
            ],
            "birim_fiyat": [],
            "odeme_sekli": [],
            "kargo_bilgisi": [],
            "siparis_no": [],
            "fatura_tarihi": [],
            "duzenleme_saati": [],
            "satici_vkn": [],
            "alici_vkn": [],
            "odenecek_tutar": [],
            "doviz_kuru": [],
            "para_birimi": [
                "TL",
                "TRY"
            ]
        },
        "structured": {
            "satici_vergi_numarasi": "9000068418",
            "alici_firma_unvani": "Fatura No",
            "alici_email": "mert.alparsian@uyumsoft.com",
            "fatura_numarasi": "MRT2025000000004",
            "genel_toplam": "81.600,00",
            "tarih": "17-06-2025",
            "para": "20,00",
            "vergi_no": "9000068418",
            "email": "mert.alparsian@uyumsoft.com",
            "alici_ad_soyad": "Fatura No",
            "urun_miktar": "2",
            "para_birimi": "TL",
            "kalemler": [],
            "fatura_tarihi": "17-06-2025"
        }
    },
    {
        "dosya": "27.08.2025_Gelen Fatura (1)\\24.07.2025-TTT2025000000018.pdf",
        "analiz_zamani": "2025-08-28 09:46:07",
        "ocr_istatistikleri": {
            "ortalama_guven_skoru": "63.30%",
            "toplam_kelime": 208,
            "gecerli_kelime": 137,
            "ham_metin_uzunlugu": 950,
            "ham_metin": "aj UYUMSOFT BİLGİ SİSTEMLERİ VE TEKNOLOJİLERİ TİCARET ey. a ANONİM ŞİRKETİ ELTON rink: iii 42000 Zincirlikuyu/ İstanbul eft feet ed Tek: 1111111111111111111 Ne iğ Stan Web Sitesi: www.uyumsoft.com.tr NE NALD Vergi Dairesi: 30 ağustos ti VKN: 9000068418 Wes e-FATURA (ay Özelleştirme No: TR1.2 Senaryo: İTEMELFATURA m ae LL SAYIN Fatura Tipi: SATIS Uyumsoft Bilgi Sistemleri Ve Teknolojileri Ticaret Anonim Şirketi Fatura No: ILCE/ İstanbul Fatura Tarihi: 24-07-2025 VKN: 9000068418 Düzenleme Tarihi: o (24-07-2025 gg DR Düzenleme Saati: 13:36:00 ETİN: 11717a36-75f7-4df2-ab2f-247618685333 wee İskonto | İskonto | KDV . . | Tamam 1 Adet{179.683,00000000 TL) %25,00] 44-9275 26.952,45 no | 134.762,25 TL Mal Hizmet Toplam Tutarı) 179.683,00 TL Toplam İskonto) ( 44.920,75 TL Hesaplanan KDV(%20.00) 26.952,45 TL Vergiler Dahil Toplam Tutar) 161.714,70 TL Ödenecek Tutar) 161.714,70TL Yalnız #Yüz Altmış Bir Bin Yedi Yüz On Dört Türk Lirası Yetmiş Kuruş#"
        },
        "regex": {
            "tarih": [
                "24-07-2025"
            ],
            "para": [
                "25,00",
                "26.952,45",
                "134.762,25 TL",
                "179.683,00 TL",
                "44.920,75 TL",
                "26.952,45 TL",
                "161.714,70 TL",
                "161.714,70TL"
            ],
            "iban": [],
            "fatura_no": [],
            "vergi_no": [
                "9000068418"
            ],
            "tc_no": [],
            "telefon": [],
            "email": [],
            "fatura_tipi": [
                "e-FATURA"
            ],
            "kdv_orani": [],
            "ettn": [],
            "mersis_no": [],
            "ticaret_sicil": [],
            "musteri_no": [],
            "mal_hizmet_kodu": [],
            "alici_ad_soyad": [
                "Fatura Tipi"
            ],
            "alici_adres": [],
            "urun_aciklama": [],
            "urun_miktar": [
                "1"
            ],
            "birim_fiyat": [
                "683,00000000 TL"
            ],
            "odeme_sekli": [],
            "kargo_bilgisi": [],
            "siparis_no": [],
            "fatura_tarihi": [
                "24-07-2025"
            ],
            "duzenleme_saati": [
                "13:36:00"
            ],
            "satici_vkn": [],
            "alici_vkn": [],
            "odenecek_tutar": [],
            "doviz_kuru": [],
            "para_birimi": [
                "TL"
            ]
        },
        "structured": {
            "satici_firma_unvani": "BİLGİ TEKNOLOJİLERİ TİCARET",
            "alici_firma_unvani": "Fatura Tipi",
            "fatura_tarihi": "24-07-2025",
            "fatura_tipi": "SATIS Uyumsoft Bilgi Sistemleri Ve Teknolojileri Ticaret Anonim Şirketi Fatura",
            "genel_toplam": "179.683,00",
            "tarih": "24-07-2025",
            "para": "25,00",
            "vergi_no": "9000068418",
            "alici_ad_soyad": "Fatura Tipi",
            "urun_miktar": "1",
            "kalemler": []
        }
    },
    {
        "dosya": "27.08.2025_Gelen Fatura (1)\\18.09.2024-PRT2024000003518.pdf",
        "analiz_zamani": "2025-08-28 09:46:08",
        "ocr_istatistikleri": {
            "ortalama_guven_skoru": "72.47%",
            "toplam_kelime": 295,
            "gecerli_kelime": 217,
            "ham_metin_uzunlugu": 1372,
            "ham_metin": "PARILTIM END.TOPLU YEMEK HİZ.TUR.SAN.VE TİC.A.Ş. GÖZTEPE MAH. EKSEN SOK. NO:8/1 BEYKOZ/ İSTANBUL İstanbul ee aS. 34815 Beykoz/ istanbul ON Tel; 0216 465 96 66 Fax: 0216 465 97 17 ‘ os O . Web Sitesi: www. pariltim-newrest.com İğ. ji E-Posta: muhasebe@pariltim-newrest.eu A ALE. YA Vergi Dairesi: BEYKOZ me VKN: 9000068418 . TICARETSICILNO: 702892-0 e-FATURA MERSISNO: 0721038111300018 a a a SAYIN YONCA GIDA SAN. İŞL, İÇ VE DIŞ TİC. AŞ. Özelleştirme No: TR1.2 Mah 1476/1 Sokak İsmet İş Merkezi Blok No:3 Kapı:7 Senaryo: TICARTFATURA Mah 1476/1 Soak İsmet İş Merkezi Blok No:3 Kap AMME: 35220 KONAK / İZMİR ER 2520, Vergi Dairesi: HASAN TAHSİN Düzenleme Tarihi: 07-09-2024 VEN: 9000068418 Saati: | ETİN: 3c63d314-264e-44a8-ac4c-09ffc69bac16 İskonto | İskonto | KDV wy N . S| ravine [oor [i a | Tm ÖĞLE YEMEĞİ- YONCA 1.045 5 he YEMEGI-YONCA | 439 || 87,76000000TL %10,00| 3.852,66 | 38.526,64 TL KAHVALTINONCAGIDA | SisAdet| 28.857,78 TL Mal Hizmet Toplam Tutarı| TL Toplam İskonto 0,00 TL Hesaplanan GERÇEK USÜLDE KATMA DEĞER VERGİSİ(9010)) | Vergiler Dahil Toplam Tutar) TL Ödenecek Tutar) TL 1-7.09 MERKEZ +SOSYAL yüz yetmiş beş bin iki türk lirası ve doksan sekiz kuruş #SEVKADRESI: İZZET GÖKDENİZ Alsancak Mah.1476/1 Sokak İsmet İş Merkezi Blok No:3 Kapı:7 KONAK 35220 İZMİR 50.30.02 - İzmir MM Kemalpaşa Osb. 18. Sok No:132 Kemalpaşa/ İzmir İzmir İzmir 34000 EGE BÖLGE"
        },
        "regex": {
            "tarih": [
                "07-09-2024",
                "1-7.09",
                "50.30.02"
            ],
            "para": [
                "10,00",
                "3.852,66",
                "38.526,64 TL",
                "28.857,78 TL",
                "0,00 TL"
            ],
            "iban": [],
            "fatura_no": [],
            "vergi_no": [
                "9000068418"
            ],
            "tc_no": [],
            "telefon": [],
            "email": [
                "muhasebe@pariltim-newrest.eu"
            ],
            "fatura_tipi": [
                "e-FATURA"
            ],
            "kdv_orani": [],
            "ettn": [],
            "mersis_no": [
                "072103811130001"
            ],
            "ticaret_sicil": [
                "702892"
            ],
            "musteri_no": [],
            "mal_hizmet_kodu": [],
            "alici_ad_soyad": [
                "YONCA GIDA SAN. İŞL"
            ],
            "alici_adres": [],
            "urun_aciklama": [],
            "urun_miktar": [],
            "birim_fiyat": [],
            "odeme_sekli": [],
            "kargo_bilgisi": [],
            "siparis_no": [],
            "fatura_tarihi": [],
            "duzenleme_saati": [],
            "satici_vkn": [],
            "alici_vkn": [],
            "odenecek_tutar": [],
            "doviz_kuru": [],
            "para_birimi": [
                "TL"
            ]
        },
        "structured": {
            "satici_firma_unvani": "TİC.A.Ş.",
            "alici_firma_unvani": "YONCA GIDA SAN. İŞL",
            "alici_email": "muhasebe@pariltim-newrest.eu",
            "genel_toplam": "38.526,64",
            "toplam_iskonto": "0,00",
            "tarih": "07-09-2024",
            "para": "10,00",
            "vergi_no": "9000068418",
            "email": "muhasebe@pariltim-newrest.eu",
            "kalemler": [],
            "fatura_tarihi": "Fatura Tarihi:\n\n07-09-2024"
        }
    },
    {
        "dosya": "27.08.2025_Gelen Fatura (1)\\18.09.2024-APU2024000000001.pdf",
        "analiz_zamani": "2025-08-28 09:46:08",
        "ocr_istatistikleri": {
            "ortalama_guven_skoru": "78.77%",
            "toplam_kelime": 290,
            "gecerli_kelime": 230,
            "ham_metin_uzunlugu": 1518,
            "ham_metin": "PARILTIM END.TOPLU YEMEK HİZ.TUR.SAN VE TİC.A.Ş. GÖZTEPE MAH. EKSEN SOK, NO:8/1 BEYKOZ/ İSTANBUL İstanbul SL 34815 Beykoz/ istanbul ferry Tel: 0216 465 96 66 Fax: 0216 465 97 17 fe: 0: 3 Web Sitesi: www.pariltim-newrest.com Nie: i | E-Posta: muhasebe@pariltim-newrest.eu Nee eh: Vergi Dairesi: BEYKOZ 7 VKN: 9000068418 TICARETSICILNO: 702892-0 e-FATURA MERSISNO: 0721038111300018 SAYIN GENNET TATİL EVLERİ SİTE YÖNETİCİLİĞİ Özelleştirme No: Göltürkbükü Mah. 314 Sok. No:12/1 Senaryo: | — TEMELFATURA > 48483 BODRUM / MUĞLA Fatura Tipi: satis E-Posta: odik@mohg.com FaturaNo: | APU2024000000001 Tel: 0252 311 26 20 Fax: 0252 311 26 20 07-09-2024 Vergi Dairesi: BODRUM 07-09-2024 VKN: 9000068418 Düzenleme Saati: [00:00:00 İrsaliye Tarihi: 02-09-2024 ETİN: 20066b70-e7e3-40d8-badb-bb1874865121 Birim Fiyat Iskonto | İskonto KDV KDV Tutarı Diğer Vergiler | Mal Hizmet Tutarı Oranı Tutarı Oranı AŞ CENNETİ so adet 83,20000000 TL 2.912,00 TL | 29.120,00 TL EST AŞ 497 Adet) © 125,52000000 TL TL | 62.383,44 TL Kai ASTAŞ 34 Adet) (| 117,73000000TL | 400,28 TL | 4.002,82 TL Mal Hizmet Toplam Tutarı 157.764,18 TL Toplam O00T| Hesaplanan GERÇEK USÜLDE KATMA DEĞER VERGİSİ(9o10)) (| Vergiler Dahil Toplam Tutar 173.540,60 TL Ödenecek Tutar 173.540,60 TL 1-7 EYLÜL LİMON BAHÇE SAYILARI yüz yetmiş üç bin beş yüz kırk türk lirası ve altmış kuruş 7 #SEVKADRESI: BARANSEL ÖZCAN Göltürkbükü Mah. 314 Sok. No:12/1 BODRUM 48483 MUĞLA 50.20.01 - Bodrum MM . Konacik Mah. Gazderesi cad. No21-3 Bodrum/ Mugla Mugla Mugla 34000 EGE BOLGE"
        },
        "regex": {
            "tarih": [
                "07-09-2024",
                "02-09-2024",
                "50.20.01"
            ],
            "para": [
                "2.912,00 TL",
                "29.120,00 TL",
                "62.383,44 TL",
                "400,28 TL",
                "4.002,82 TL",
                "157.764,18 TL",
                "173.540,60 TL"
            ],
            "iban": [],
            "fatura_no": [],
            "vergi_no": [
                "9000068418"
            ],
            "tc_no": [],
            "telefon": [],
            "email": [
                "muhasebe@pariltim-newrest.eu",
                "odik@mohg.com"
            ],
            "fatura_tipi": [
                "e-FATURA"
            ],
            "kdv_orani": [],
            "ettn": [],
            "mersis_no": [
                "072103811130001"
            ],
            "ticaret_sicil": [
                "702892"
            ],
            "musteri_no": [],
            "mal_hizmet_kodu": [],
            "alici_ad_soyad": [
                "GENNET TATİL EVLERİ SİTE"
            ],
            "alici_adres": [],
            "urun_aciklama": [
                "Hizmet Tutarı Oranı Tutarı Oranı AŞ CENNETİ so adet"
            ],
            "urun_miktar": [
                "497",
                "34"
            ],
            "birim_fiyat": [],
            "odeme_sekli": [],
            "kargo_bilgisi": [],
            "siparis_no": [],
            "fatura_tarihi": [],
            "duzenleme_saati": [],
            "satici_vkn": [],
            "alici_vkn": [],
            "odenecek_tutar": [
                "173.540,60 TL"
            ],
            "doviz_kuru": [],
            "para_birimi": [
                "TL"
            ]
        },
        "structured": {
            "satici_firma_unvani": "VE PARILTIM END.TOPLU HİZ.TUR.SAN YEMEK TİC.A.Ş.",
            "alici_firma_unvani": "GENNET TATİL EVLERİ SİTE YÖNETİCİLİĞİ Özelleştirme No",
            "alici_email": "muhasebe@pariltim-newrest.eu",
            "alici_telefon": "0216 465 96 66",
            "fatura_numarasi": "APU2024000000001",
            "fatura_tipi": "satis E",
            "genel_toplam": "173.540,60",
            "tarih": "07-09-2024",
            "para": "2.912,00 TL",
            "vergi_no": "9000068418",
            "email": "muhasebe@pariltim-newrest.eu",
            "mersis_no": "072103811130001",
            "ticaret_sicil": "702892",
            "alici_ad_soyad": "GENNET TATİL EVLERİ SİTE",
            "urun_aciklama": "Hizmet Tutarı Oranı Tutarı Oranı AŞ CENNETİ so adet",
            "urun_miktar": "497",
            "odenecek_tutar": "173.540,60 TL",
            "para_birimi": "TL",
            "kalemler": [
                {
                    "aciklama": "Mal",
                    "birim_fiyat": "Hizmet Tutarı Oranı Tutarı Oranı AŞ CENNETİ so adet",
                    "tutar": "83,20000000 TL"
                }
            ],
            "fatura_tarihi": "07-09-2024"
        }
    },
    {
        "dosya": "27.08.2025_Gelen Fatura (1)\\18.09.2024-PRT2024000003508.pdf",
        "analiz_zamani": "2025-08-28 09:46:09",
        "ocr_istatistikleri": {
            "ortalama_guven_skoru": "68.13%",
            "toplam_kelime": 307,
            "gecerli_kelime": 226,
            "ham_metin_uzunlugu": 1433,
            "ham_metin": "PARILTIM YEMEK HİZ.TUR.SAN.VE TİC.A.Ş, GÖZTEPE MAH, EKSEN SOK. NO:8/1 BEYKOZ/ İSTANBUL İstanbul TONS 34815 Beykoz/ istanbul JE, Tel: 0216 465 96 66 Fay: 0216 465 97 17 & Web Sitesi: Www. pariltim-newrest.com Ve if nf E-Posta; muhasebe@pariltim-newrest.ey AN , iS Vergi Dairesi: BEYKOz erent aes” VKN: 9000068418 a TICARETSICILNO: 702892-9 e-FATURA MERSISNO; 0721038111300018 SAYIN BEŞER BALATACILIK SAN, VE TICA.S, Özelleştirme No; TR1.2 BEŞER BALATACILIK SAN VE TİCA,Ş, Senaryo: SULARA CAD. NO: 309 Fatura Tipi; SATIS E-Posta: mustafa.guler@beser.com.tr No; ~~ Tel: 0530 425 97 53 Fatura Tarihi: 0709205 Vergi BORNOVA Düzenleme Tarihi: 07-09-2024 VKN: 9000068418 Düzenleme Saati: ETME İrsaliye Tarihi; 01-09-2024 ETTN; we İskonto İskonto KDV oy Pane Tam MM, | 41, | %10,00/ 128 89 7, | 1.288,00 TL BALATAĞILIK EE | 1375 92,00000000 TL Pd 701000) 12.650,00 T1 | 126.500,00 TL 400 oz 71 3.680,00 71 | 36.800,00 TL MM 11,00000000 Tı. İN 701000) | 36.300,00 TL cc MM ae 11,00000000 TL | 1 | 20.900,00 TL Mal Hizmet Toplam Tutarı; 221.788,00 TL Toplam İskonto | 0.0071 Hesaplanan GERÇEK USÜLDE KATMA DEĞER | 22.178,80TL Vergiler Dahil Toplam Tutar 243.966,80 TL 243.966,80 TL 1-7.09 FATURASIDIR iki yüz kirk üç bin dokuz yüz altmış altı türk lirası ve seksen kuruş #SEVKADRESİ: BEŞER BALATACILIK SAN.VE ANKARA CAD. No: 309 BORNOVA 35080 izmir 50.30.02 - İzmir MM Kemalpasa Osb. 18, Sok No:132 Kemalpaşa/ Izmir İzmir İzmir 34000 EGE BÖLGE"
        },
        "regex": {
            "tarih": [
                "07-09-2024",
                "01-09-2024",
                "1-7.09",
                "50.30.02"
            ],
            "para": [
                "10,00",
                "1.288,00 TL",
                "12.650,00",
                "126.500,00 TL",
                "3.680,00",
                "36.800,00 TL",
                "36.300,00 TL",
                "20.900,00 TL",
                "221.788,00 TL",
                "22.178,80TL"
            ],
            "iban": [],
            "fatura_no": [],
            "vergi_no": [
                "9000068418"
            ],
            "tc_no": [],
            "telefon": [],
            "email": [
                "muhasebe@pariltim-newrest.ey",
                "mustafa.guler@beser.com.tr"
            ],
            "fatura_tipi": [
                "e-FATURA"
            ],
            "kdv_orani": [],
            "ettn": [],
            "mersis_no": [],
            "ticaret_sicil": [
                "702892"
            ],
            "musteri_no": [],
            "mal_hizmet_kodu": [],
            "alici_ad_soyad": [
                "BEŞER BALATACILIK SAN"
            ],
            "alici_adres": [],
            "urun_aciklama": [],
            "urun_miktar": [],
            "birim_fiyat": [],
            "odeme_sekli": [],
            "kargo_bilgisi": [],
            "siparis_no": [],
            "fatura_tarihi": [],
            "duzenleme_saati": [],
            "satici_vkn": [],
            "alici_vkn": [],
            "odenecek_tutar": [],
            "doviz_kuru": [],
            "para_birimi": [
                "TL"
            ]
        },
        "structured": {
            "satici_firma_unvani": "iS erent TICARET",
            "satici_vergi_numarasi": "9000068418",
            "alici_firma_unvani": "BEŞER BALATACILIK SAN",
            "alici_email": "mustafa.guler@beser.com.tr",
            "alici_telefon": "0216 465 96 66",
            "genel_toplam": "243.966,80",
            "tarih": "07-09-2024",
            "para": "10,00",
            "vergi_no": "9000068418",
            "email": "muhasebe@pariltim-newrest.ey",
            "kalemler": [],
            "fatura_numarasi": "PRT2024000003508",
            "fatura_tarihi": "07-09-2024"
        }
    },
    {
        "dosya": "27.08.2025_Gelen Fatura (1)\\26.06.2025-EF02025000000012.pdf",
        "analiz_zamani": "2025-08-28 09:46:10",
        "ocr_istatistikleri": {
            "ortalama_guven_skoru": "51.48%",
            "toplam_kelime": 214,
            "gecerli_kelime": 120,
            "ham_metin_uzunlugu": 741,
            "ham_metin": "İmam OT) a Bilgi Teknolojileri . Kee, SINS 0 Merkez/ İSTANBUL 850 221 73 54 Fax: 0 370 439 1054 5 Sitesi: www-enoca.com Ae: 4 j La osta: enoca@enoca.com miz rhe gi Dairesi: ÜSKÜDAR BE \" oF. N: 9000068418 Le e-FATURA fale pa Be. özelleştirme No: — — URA AYIN cisi YUMSOFT BiLGi SİSTEMLERİ VE TEKNOLOJİLE Fatura =F02025000000012 STANBUL kara — 2000 rok Sa hi Da EN ECM (KN? 9000068418 irsaliye No: 0080000113 9000060008 irsaliye Tarihi: ETİN; me (ee KE a em ne 14.635,00000000 %20,00|_14.635,00 — sao Mal Hizmet Toplam Tutarı 74.630,00 TL Toplam İskonto 0,00 TH ——Fesaplanan KDV(9/010.00) Hesaplanan KOV(9/020.00) 14.635,00 TL Vergiler Dahil Toplam Tutar 89.410,50 TL ödenecek Tutar 89.410,50 TL YALNIZ TRY ELLİ KR IDE:SAP Fatura No:0090000089"
        },
        "regex": {
            "tarih": [],
            "para": [
                "20,00",
                "635,00",
                "74.630,00 TL",
                "0,00",
                "14.635,00 TL",
                "89.410,50 TL"
            ],
            "iban": [],
            "fatura_no": [],
            "vergi_no": [],
            "tc_no": [],
            "telefon": [],
            "email": [
                "enoca@enoca.com"
            ],
            "fatura_tipi": [
                "e-FATURA"
            ],
            "kdv_orani": [],
            "ettn": [],
            "mersis_no": [],
            "ticaret_sicil": [],
            "musteri_no": [],
            "mal_hizmet_kodu": [],
            "alici_ad_soyad": [],
            "alici_adres": [],
            "urun_aciklama": [],
            "urun_miktar": [],
            "birim_fiyat": [],
            "odeme_sekli": [],
            "kargo_bilgisi": [],
            "siparis_no": [],
            "fatura_tarihi": [],
            "duzenleme_saati": [],
            "satici_vkn": [],
            "alici_vkn": [],
            "odenecek_tutar": [
                "89.410,50 TL"
            ],
            "doviz_kuru": [],
            "para_birimi": [
                "TL",
                "TRY"
            ]
        },
        "structured": {
            "fatura_numarasi": "0090000089",
            "genel_toplam": "89.410,50",
            "para": "20,00",
            "email": "enoca@enoca.com",
            "kalemler": [
                {
                    "tutar": "Toplam",
                    "aciklama": "Dahil Vergiler"
                }
            ]
        }
    },
    {
        "dosya": "27.08.2025_Gelen Fatura (1)\\25.08.2025-SEM2025000000201.pdf",
        "analiz_zamani": "2025-08-28 09:46:12",
        "ocr_istatistikleri": {
            "ortalama_guven_skoru": "65.58%",
            "toplam_kelime": 300,
            "gecerli_kelime": 208,
            "ham_metin_uzunlugu": 1251,
            "ham_metin": "Gerçek Oto Lastik Sanayi Tic. Ltd. Şti, oe Bes ere pee Ornek Adres No : 123/A 5 $e nf Maltepe/ İstanbul LR Vergi Dairesi: Kozyatağı 2 no VKN: 9000068418 Ng e AGEN Bez. ız ar e-FATURA mi Özelleştirme No: —— o, |TICARIFATURA SAYIN FaturaTipi: (satis i atura ae Müşterisi Fatura No: Atagehit/ İstanbul Fatura Tarihi: [25-08-2025 Tel: (435) 353-5353 Düzenleme Tarihi: [25-08-2025 Vergi Kozyatağı Düzenleme Saati: [16:32:11 VEN: 9000068418 SiparişNo: ooo — — Sipariş Tarihi: 25-08-2025 ET™N: 7d481f48-0558-420e-bd89-47a46c3f7396 İskonto | İskonto | KDV wy . . tne [i e RO LT245/75R16 120/116Q 1 DYNAPRO MT2 RTOS 4 Adet 6.458,33000000 TL 0,00 TL “620,00 5.166,68 TL XL EAG 8.750,00000000 0,00 TLİ 9620,00) | 7.000,00 TL | 35.000,00 TL be ane 818 | 4.375,00000000 | 0,00 TLİ 9620,00) | 3.500,00 TL | 17.500,00 TL a 818 5112 ET40.BD 5.416,67000000 TL 0,00 TL| 9620,00) | 4.333,32 TL 21.666,68 TL 66,45 20 INC 205/55R16 91V N BLUE Ss o SEAT / AUD 4 Adet 2.291,67000000 yo 0,00 TL %20,00 1.833,32 yo 9.166,68 TL Eagle Fi Asymmetric 6 js 92Y XL FP 4 Adet 3.958,33000000 TL 0,00 TL 020,00 3.166,68 TL Mal Hizmet Toplam Tutarı 125.000,00 TL Toplam Hesaplanan KDV(%20) 25.000,00 TL Vergiler Dahil Toplam Tutar 150.000,00 TL 150.000,00 TL #yüzellibinTL# Fatura Notu:"
        },
        "regex": {
            "tarih": [
                "25-08-2025"
            ],
            "para": [
                "0,00 TL",
                "620,00",
                "5.166,68 TL",
                "0,00",
                "9620,00",
                "7.000,00 TL",
                "35.000,00 TL",
                "3.500,00 TL",
                "17.500,00 TL",
                "4.333,32 TL"
            ],
            "iban": [],
            "fatura_no": [],
            "vergi_no": [
                "9000068418"
            ],
            "tc_no": [],
            "telefon": [],
            "email": [],
            "fatura_tipi": [
                "e-FATURA"
            ],
            "kdv_orani": [],
            "ettn": [],
            "mersis_no": [],
            "ticaret_sicil": [],
            "musteri_no": [],
            "mal_hizmet_kodu": [],
            "alici_ad_soyad": [
                "FaturaTipi"
            ],
            "alici_adres": [],
            "urun_aciklama": [],
            "urun_miktar": [
                "4"
            ],
            "birim_fiyat": [],
            "odeme_sekli": [],
            "kargo_bilgisi": [],
            "siparis_no": [
                "ooo"
            ],
            "fatura_tarihi": [],
            "duzenleme_saati": [],
            "satici_vkn": [],
            "alici_vkn": [],
            "odenecek_tutar": [],
            "doviz_kuru": [],
            "para_birimi": [
                "TL"
            ]
        },
        "structured": {
            "satici_firma_unvani": "Gerçek Oto Lastik Sanayi Tic. Ltd.",
            "satici_vergi_numarasi": "9000068418",
            "satici_telefon": "(435) 353",
            "alici_firma_unvani": "FaturaTipi",
            "alici_telefon": "(435) 353",
            "fatura_numarasi": "Atagehit/",
            "fatura_tarihi": "25-08-2025",
            "siparis_no": "ooo",
            "genel_toplam": "150.000,00",
            "mal_hizmet_toplam": "125.000,00",
            "tarih": "25-08-2025",
            "para": "0,00 TL",
            "vergi_no": "9000068418",
            "kalemler": [],
            "ettn": "7d481f48-0558-420e-bd89-47a46c3f7396"
        }
    },
    {
        "dosya": "27.08.2025_Gelen Fatura (1)\\27.06.2025-FMH2025000000006.pdf",
        "analiz_zamani": "2025-08-28 09:46:13",
        "ocr_istatistikleri": {
            "ortalama_guven_skoru": "73.17%",
            "toplam_kelime": 277,
            "gecerli_kelime": 202,
            "ham_metin_uzunlugu": 1479,
            "ham_metin": "FRESENİUS MEDİKAL HİZMETLER ANONİM ŞİRKETİ MERKEZ: Rüzgarlı Bahçe Mah, Cumhuriyet Cad. No:39 Kat:7 Kavacık BEYKOZ/ISTANBUL ANTALYA MUMESSILLIK ECZA DEPOSU 5 ve, Ata Be ŞUBESİ: AOSB 1.Kısım Mah.8.Cadde No:3 KEZ DOSEMEALTI/ ANTALYA Tel: 0242 2594092 Fax: 0242 2594094 j = Web Sitesi: www.freseniusmedicalcare.com.tr 1 On Ld os E-Posta; info.turkey@freseniusmedicalcare.com oat” Vergi Dairesi: B.MUKELLEFLER mm VKN: 9000068418 e-FATURA TICARETSICILNO: 40368 MERSISNO: 324000887200015 Ozellestirme No: T.C. IST.VAL. İL SAĞLIK MÜDÜRLÜĞÜ DR, LÜTFİ KIRDAR ŞEHİR Senaryo: 34865 CEVİZLİ MH. KARTAL/ İSTANBUL 7 E-Posta: defaultpk@muhasebat.gov.tr Fatura Tarihi: (25-06-2025 Tel: 2164413900 Düzenleme Tarihi: | Vergi Dairesi: KARTAL Düzenleme Saati: © )10:24:36 — VKN: 9000068418 1FM2025000000021 irsaliye Tarihi: 25-06-2025 ETİN: 04d0ef8a-83 1f-4d4e-87ae-7701d72c999d ae İskonto | İskonto | KDV wy . . Tots Tm a {Aqua RO MOBILE | 1 Adet|200.000,00000000 TL İİ 20.000,00 200.000,00 TL Mal Hizmet Toplam Tutarı 200.000,00 TL Toplam İskonto | Hesaplanan Satış vergisi(%10.00) 20.000,00 TL, Vergiler Dahil Toplam Tutar 220.000,00 TL Ödenecek Tutar 220.000,00 TL Yalnız İKİYÜZYİRMİBİN LİRA TCMB Efektif Satış Kuru; 33.16290 SAP fatura no: 0188147349 SAP sipariş no: 2361001844 Müş. No: 0920175949 FIRMA TANIMLAYICI NO: 2667269040084 ee , Sevk Adresi: T.C. İST.VAL, İL SAĞLIK MÜDÜRLÜĞÜ DR. LÜTFİ KIRDAR ŞEHİR HAST, .GNL.BUT ŞEMSİ DENİZER CD. CEVİZLİ MH. KARTAL ISTANBUL Vade: 90 Gün 23.09.2025 ,"
        },
        "regex": {
            "tarih": [
                "25-06-2025",
                "23.09.2025"
            ],
            "para": [
                "20.000,00",
                "200.000,00 TL",
                "20.000,00 TL",
                "220.000,00 TL"
            ],
            "iban": [],
            "fatura_no": [],
            "vergi_no": [
                "9000068418"
            ],
            "tc_no": [],
            "telefon": [],
            "email": [
                "info.turkey@freseniusmedicalcare.com",
                "defaultpk@muhasebat.gov.tr"
            ],
            "fatura_tipi": [
                "e-FATURA"
            ],
            "kdv_orani": [],
            "ettn": [],
            "mersis_no": [
                "324000887200015"
            ],
            "ticaret_sicil": [],
            "musteri_no": [],
            "mal_hizmet_kodu": [],
            "alici_ad_soyad": [],
            "alici_adres": [],
            "urun_aciklama": [],
            "urun_miktar": [
                "1"
            ],
            "birim_fiyat": [],
            "odeme_sekli": [],
            "kargo_bilgisi": [],
            "siparis_no": [
                "2361001844"
            ],
            "fatura_tarihi": [],
            "duzenleme_saati": [],
            "satici_vkn": [],
            "alici_vkn": [],
            "odenecek_tutar": [
                "220.000,00 TL"
            ],
            "doviz_kuru": [],
            "para_birimi": [
                "TL"
            ]
        },
        "structured": {
            "satici_firma_unvani": "e-FATURA TICARET",
            "satici_vergi_dairesi": "B",
            "satici_vergi_numarasi": "9000068418",
            "satici_ticaret_sicil": "40368",
            "alici_email": "defaultpk@muhasebat.gov.tr",
            "alici_telefon": "0242 2594092",
            "fatura_numarasi": "0188147349",
            "fatura_tarihi": "25-06-2025",
            "siparis_no": "2361001844",
            "genel_toplam": "220.000,00",
            "mal_hizmet_toplam": "200.000,00",
            "tarih": "25-06-2025",
            "para": "20.000,00",
            "vergi_no": "9000068418",
            "email": "info.turkey@freseniusmedicalcare.com",
            "kalemler": []
        }
    },
    {
        "dosya": "27.08.2025_Gelen Fatura (1)\\27.06.2025-FRE2025000000001.pdf",
        "analiz_zamani": "2025-08-28 09:46:25",
        "ocr_istatistikleri": {
            "ortalama_guven_skoru": "77.78%",
            "toplam_kelime": 300,
            "gecerli_kelime": 234,
            "ham_metin_uzunlugu": 1638,
            "ham_metin": "FRESENİUS MEDİKAL HİZMET LER ANONİM ŞİRKETİ MERKEZ: Rüzgarlı Bahçe Mah, Cumhuriyet Cad, No:39 Kat:7 Mı Kavacık BEYKOZ/IST, ANBUL ANT, ALYA MÜMESSİLLİK ECZA DEPOSU 5 < ve, ŞUBESİ: AOSB 1.Kısım Mah.8.Cadde No:3 Ker: ON DÖŞEMEALTI/ ANTALYA & ffars Tel: 0242 2594092 Fax: 0242 2594094 ie “8 Web Sitesi: “ww. freseniusmedicalcare.com,tr Ne. OE E-Posta; info.turkey@freseniusmedicalcare.com eet Vergi Dairesi: B.MUKELLEFLER VKN: 9000068418 e-FATURA TICARET: SICILNO: 40368 MERSISNO: 324000887200015 SAYIN 7 Özelleştirme No: TR1.2 T.C. İST.VAL, İL SAĞLIK MÜDÜRLÜĞÜ DR. LÜTFİ KIRDAR ŞEHİR Senaryo: ŞEMSİ co Fatura Tir —— 21865 CEVİZLİ MH. KARTAL İSTANBUL Nor E-Posta; defaultok@muhasebat.gov.tr 18-06-2025 Tel: 2164413909 Düzenleme Tarihi: 18-06-2025 Vergi Dairesi: KARTAL 12:39:58 VKN: 9000068418 İrsaliye No: IFM2025000000013 ETN a İrsaliye Tarihi; 18-06-2025 | ETTN; 9180 Birim Fiyat Iskonto | İskonto KDV Diğer Vergiler | Maj Hizmet Tutarı Oranı Tutarı Oranı dass 120 Adet) TL 14.400,00 TL | 144.000,00 TL Mal Hizmet Toplam Tutarı 144.000,00 TL Toplam İskonto | Hesaplanan Satis vergisi( 2010.00) 14.400,00 TL Vergiler Dahil Toplam Tutar 158.400,00 TL Ödenecek Tutar) 158.400,00 TL Yalnız YÜZ ELLİSEKİZBİNDÖRTYÜZ LİRA TCMB Efektif Satış Kuru: 33.16290 SAP fatura no: 0188147341 SAP sipariş no; 2361001642 Müş. No: 0920175949 FİRMA TANIMLAYICI No: 2667269040084 | Sevk Adresi: T.C. İST.VAL, İL SAĞLIK MÜDÜRLÜĞÜ DR. LÜTFİ KIRDAR ŞEHİR HAST.GNL.BUT ŞEMSİ DENIZER Cp, CEVİZLİ MH. KARTAL IST, ANBUL Vade: 90 Gün 16.09.2025 . Satır - Serj No.: E1X105120 UBB: 4039361068257 Kodu: F00002386 Skt: 2026-08-31 Adet: 120 SUT: NF1007 DMO Uriin No: SM10038"
        },
        "regex": {
            "tarih": [
                "18-06-2025",
                "16.09.2025"
            ],
            "para": [
                "14.400,00 TL",
                "144.000,00 TL",
                "158.400,00 TL"
            ],
            "iban": [],
            "fatura_no": [],
            "vergi_no": [
                "9000068418"
            ],
            "tc_no": [],
            "telefon": [],
            "email": [
                "info.turkey@freseniusmedicalcare.com",
                "defaultok@muhasebat.gov.tr"
            ],
            "fatura_tipi": [
                "e-FATURA"
            ],
            "kdv_orani": [],
            "ettn": [],
            "mersis_no": [
                "324000887200015"
            ],
            "ticaret_sicil": [],
            "musteri_no": [],
            "mal_hizmet_kodu": [],
            "alici_ad_soyad": [],
            "alici_adres": [],
            "urun_aciklama": [
                "Tutarı Oranı Tutarı Oranı dass 120 Adet"
            ],
            "urun_miktar": [
                "120",
                "31"
            ],
            "birim_fiyat": [],
            "odeme_sekli": [],
            "kargo_bilgisi": [],
            "siparis_no": [],
            "fatura_tarihi": [],
            "duzenleme_saati": [],
            "satici_vkn": [],
            "alici_vkn": [],
            "odenecek_tutar": [],
            "doviz_kuru": [],
            "para_birimi": [
                "TL"
            ]
        },
        "structured": {
            "satici_vergi_dairesi": "OE B",
            "alici_telefon": "0242 2594092",
            "fatura_numarasi": "0188147341",
            "genel_toplam": "158.400,00",
            "tarih": "18-06-2025",
            "para": "14.400,00 TL",
            "vergi_no": "9000068418",
            "email": "info.turkey@freseniusmedicalcare.com",
            "kalemler": [],
            "fatura_tarihi": "18-06-2025"
        }
    },
    {
        "dosya": "27.08.2025_Gelen Fatura (1)\\27.06.2025-FRE2025000000002.pdf",
        "analiz_zamani": "2025-08-28 09:46:39",
        "ocr_istatistikleri": {
            "ortalama_guven_skoru": "76.12%",
            "toplam_kelime": 296,
            "gecerli_kelime": 222,
            "ham_metin_uzunlugu": 1549,
            "ham_metin": "FRESENİUS MEDİKAL HİZMETLER ANONİM ŞİRKETİ MERKEZ: Rüzgarlı Bahçe Mah. Cumhuriyet Cad. No:39 Kat:7 Kavacık BEYKOZ/ISTANBUL ANTALYA MUMESSILLIK ECZA DEPOSU p Gi Ma : ŞUBESİ: AOSB 1.Kısım Mah.8.Cadde No:3 MEN, DÖŞEMEALTI/ ANTALYA YO Tel: 0242 2594092 Fax: 0242 2594094 i } = Web Sitesi: www.freseniusmedicalcare.com.tr İNE. E-Posta: info.turkey ©freseniusmedicalcare.com Vergi Dairesi: B.MUKELLEFLER VKN: 9000068418 e-FATURA TICARETSICILNO: 40368 MERSISNO: 324000887200015 e m — aaa aaa a a a a a SAYIN özelleştirme No: — T.C. IST.VAL. İL SAĞLIK MÜDÜRLÜĞÜ DR. LÜTFİ KIRDAR ŞEHİR 34865 CEVİZLİ MH. KARTAL/ İSTANBUL E Pasta: Tel: 2164413900 Düzenleme Tarihi: 18-06-2025 Vergi Dairesi: KARTAL Düzenleme Saati: 10:45:34 VKN: 9000068418 Irsaliye No: IFM2025000000014 em — ——— ro — — ——— ——— İrsaliye Tarihi: 18-06-2025 ETIN: f2f40d65-5a3e-4d1c-bce0-043f69a78724 Birim Fiyat İskonto | iskonto KDV | Diğer Vergiler | Mal Hizmet Tutarı Oranı Tutarı Oranı , © [40085 classix BASIC 1 Adet) 180.000,00000000 TL %10,00| 18.000,00 TL 180.000,00 TL VERSION Mal Hizmet Toplam Tutarı 180.000,00 TL Toplam İskonto Td Hesaplanan Satis vergisi(%10.00) 18.000,00 TL Vergiler Dahil Toplam Tutar 198.000,00 TL Ödenecek Tutar) (198.000,00 TL Yalnız YÜZ DOKSANSEKİZBİN LİRA TCMB Efektif Satış Kuru: 33.16290 SAP fatura no: 0188147342 SAP sipariş no: 2361001645 Müş. No: 0920175949 FİRMA TANIMLAYICI NO: 2667269040084 | ; Sevk Adresi: T.C. IST.VAL. İL SAĞLIK MÜDÜRLÜĞÜ DR. LÜTFİ KIRDAR ŞEHİR HAST.GNL.BUT ŞEMSİ DENİZER CD. CEVİZLİ MH. KARTAL İSTANBUL Vade: 90 Gün 16.09.2025 ."
        },
        "regex": {
            "tarih": [
                "18-06-2025",
                "16.09.2025"
            ],
            "para": [
                "10,00",
                "18.000,00 TL",
                "180.000,00 TL",
                "198.000,00 TL"
            ],
            "iban": [],
            "fatura_no": [],
            "vergi_no": [
                "9000068418"
            ],
            "tc_no": [],
            "telefon": [],
            "email": [],
            "fatura_tipi": [
                "e-FATURA"
            ],
            "kdv_orani": [],
            "ettn": [],
            "mersis_no": [
                "324000887200015"
            ],
            "ticaret_sicil": [],
            "musteri_no": [],
            "mal_hizmet_kodu": [],
            "alici_ad_soyad": [
                "özelleştirme No"
            ],
            "alici_adres": [],
            "urun_aciklama": [],
            "urun_miktar": [
                "1"
            ],
            "birim_fiyat": [],
            "odeme_sekli": [],
            "kargo_bilgisi": [],
            "siparis_no": [
                "2361001645"
            ],
            "fatura_tarihi": [],
            "duzenleme_saati": [
                "10:45:34"
            ],
            "satici_vkn": [],
            "alici_vkn": [],
            "odenecek_tutar": [],
            "doviz_kuru": [],
            "para_birimi": [
                "TL"
            ]
        },
        "structured": {
            "satici_ticaret_sicil": "324000887200015",
            "alici_firma_unvani": "özelleştirme No",
            "alici_telefon": "0242 2594092",
            "fatura_numarasi": "0188147342",
            "siparis_no": "2361001645",
            "genel_toplam": "198.000,00",
            "tarih": "18-06-2025",
            "para": "10,00",
            "vergi_no": "9000068418",
            "kalemler": [
                {
                    "tutar": "TL",
                    "aciklama": "180.000,00",
                    "kdv_orani": "18.000,00"
                },
                {
                    "tutar": "TL",
                    "aciklama": "180.000,00 Tutarı Toplam"
                },
                {
                    "tutar": "TL",
                    "aciklama": "18.000,00",
                    "kdv_orani": "Hesaplanan"
                },
                {
                    "tutar": "TL",
                    "aciklama": "198.000,00 Tutar Toplam",
                    "kdv_orani": "Vergiler"
                }
            ],
            "fatura_tarihi": "18-06-2025",
            "ettn": "f2f40d65-5a3e-4d1c-bce0-043f69a78724"
        }
    },
    {
        "dosya": "27.08.2025_Gelen Fatura (1)\\28.05.2025-AKA2025000000005.pdf",
        "analiz_zamani": "2025-08-28 09:47:07",
        "ocr_istatistikleri": {
            "ortalama_guven_skoru": "57.73%",
            "toplam_kelime": 218,
            "gecerli_kelime": 130,
            "ham_metin_uzunlugu": 809,
            "ham_metin": "is zeki LI Netsim Yazılım A.Ş Jb çe ye Adres 1 uyumsoft o ‘i ore ii Talas/ Kayseri oT E-Posta: dfsdf@ggh.gfgh ay : : 2. K ry me LF ie Vergi Dairesi: daire NAL VKN: 9000068418 eer? ae rik ıl e-FATURA a ——— ÖzelleştirmeNo: (Ri? << | SAYIN Senaryo: cara Fatura Tipi: saris Vergi Dairesi: daire Fatura Tarihi: 28-05-2025 VKN: 9000068418 Düzenleme Tarihi: {28-05-2025 Düzenleme Saati: 10:00:05 ETTN: c8dd4798-42d4-4fdf-b165-1b8a24236b2d we İskonto | İskonto | KDV ay . ET [er [arn | Tama 1 75.000,00000000 75.000,00 TL Mal Hizmet Toplam Tutari 75.000,00 TL, Toplam İskonto |, Hesaplanan KDV(%20) 15.000,00 TL Vergiler Dahil Toplam Tutar 90.000,00 TL Ödenecek Tutar 90.000,00 TL Sicil No: 150 Mersis No: 1111111111111111 işletme Merkezi: Kayseri YAZI İLE: DoksanBin TL Ni Ödeme Notu: VADE TARİHİ: 2025-05-28 (-- --)"
        },
        "regex": {
            "tarih": [
                "28-05-2025"
            ],
            "para": [
                "75.000,00 TL",
                "15.000,00 TL",
                "90.000,00 TL"
            ],
            "iban": [],
            "fatura_no": [],
            "vergi_no": [
                "9000068418"
            ],
            "tc_no": [],
            "telefon": [],
            "email": [
                "dfsdf@ggh.gfgh"
            ],
            "fatura_tipi": [
                "e-FATURA"
            ],
            "kdv_orani": [],
            "ettn": [
                "c8dd4798-42d4-4fdf-b165-1b8a24236b2d"
            ],
            "mersis_no": [
                "111111111111111"
            ],
            "ticaret_sicil": [],
            "musteri_no": [],
            "mal_hizmet_kodu": [],
            "alici_ad_soyad": [
                "Senaryo"
            ],
            "alici_adres": [],
            "urun_aciklama": [],
            "urun_miktar": [],
            "birim_fiyat": [],
            "odeme_sekli": [],
            "kargo_bilgisi": [],
            "siparis_no": [],
            "fatura_tarihi": [
                "28-05-2025"
            ],
            "duzenleme_saati": [
                "10:00:05"
            ],
            "satici_vkn": [],
            "alici_vkn": [],
            "odenecek_tutar": [
                "90.000,00 TL"
            ],
            "doviz_kuru": [],
            "para_birimi": [
                "TL"
            ]
        },
        "structured": {
            "satici_email": "dfsdf@ggh.gfgh",
            "alici_firma_unvani": "Senaryo",
            "alici_email": "dfsdf@ggh.gfgh",
            "fatura_tarihi": "28-05-2025",
            "ettn": "c8dd4798-42d4-4fdf-b165-1b8a24236b2d",
            "fatura_tipi": "saris",
            "genel_toplam": "90.000,00",
            "tarih": "28-05-2025",
            "para": "75.000,00 TL",
            "vergi_no": "9000068418",
            "email": "dfsdf@ggh.gfgh",
            "mersis_no": "111111111111111",
            "alici_ad_soyad": "Senaryo",
            "duzenleme_saati": "10:00:05",
            "odenecek_tutar": "90.000,00 TL",
            "para_birimi": "TL",
            "kalemler": []
        }
    },
    {
        "dosya": "27.08.2025_Gelen Fatura (1)\\29.04.2023-RSE2023000000171.pdf",
        "analiz_zamani": "2025-08-28 09:47:12",
        "ocr_istatistikleri": {
            "ortalama_guven_skoru": "59.89%",
            "toplam_kelime": 236,
            "gecerli_kelime": 147,
            "ham_metin_uzunlugu": 931,
            "ham_metin": "a? : Bip UYUMSOFT BİLGİ SİSTEMLERİ VE TEKNOLOJİLERİ TİCARET Te ANONİM ŞİRKETİ EE ae Gree . “re: Ni B, ge a Tel: test@test.com Fax: 5 AN Web Sitesi: http://www.test.com i ia E-Posta: test@test.com Ne i] oat Oa i Dairnei ie da ro Vergi Dairesi: test3 ge Hs VKN: 9000068418 e TICARETSICILNO: MERSISNO: 11111111111111 e FATURA il Özelleştirme No: TR1.2 Senaryo: oo — Fatura Tipi: SATIS Fatura No: SAYIN Fatura Tarihi: 29-04-2023 Uyumsoft Bilgi Sistem.ve Tekno.Tic.A.Ş. Düzenleme Tarihi: | |29-04-2023 YENİŞEHİR/ İstanbul Düzenleme Saati: 11:20:00 VKN: 9000068418 Sipariş No: 4, 4 o, Sipariş Tarihi: 29-04-2023 ETİN: Bi İskonto | İskonto KDV ay . . o İBİLGİSAYAR 10 Adet) 8.000,00000000 TL HN a 018,00) 14.400,00 80.000,00 TL Mal Hizmet Toplam Tutarı 80.000,00 TL Toplam İskonto |, oni Hesaplanan KDV(%18.00) 14.400,00 TL Vergiler Dahil Toplam Tutar 94.400,00 TL Ödenecek Tutar 94.400,00 TL Yalnız #Doksan Dört Bin Dört Yüz Türk Lirası#"
        },
        "regex": {
            "tarih": [
                "29-04-2023"
            ],
            "para": [
                "018,00",
                "14.400,00",
                "80.000,00 TL",
                "14.400,00 TL",
                "94.400,00 TL"
            ],
            "iban": [],
            "fatura_no": [],
            "vergi_no": [
                "9000068418"
            ],
            "tc_no": [],
            "telefon": [],
            "email": [
                "test@test.com"
            ],
            "fatura_tipi": [],
            "kdv_orani": [],
            "ettn": [],
            "mersis_no": [],
            "ticaret_sicil": [],
            "musteri_no": [],
            "mal_hizmet_kodu": [],
            "alici_ad_soyad": [
                "Fatura Tarihi"
            ],
            "alici_adres": [],
            "urun_aciklama": [],
            "urun_miktar": [
                "10"
            ],
            "birim_fiyat": [],
            "odeme_sekli": [],
            "kargo_bilgisi": [],
            "siparis_no": [
                "4"
            ],
            "fatura_tarihi": [
                "29-04-2023"
            ],
            "duzenleme_saati": [
                "11:20:00"
            ],
            "satici_vkn": [],
            "alici_vkn": [],
            "odenecek_tutar": [
                "94.400,00 TL"
            ],
            "doviz_kuru": [],
            "para_birimi": [
                "TL"
            ]
        },
        "structured": {
            "satici_firma_unvani": "da ge ro e TICARET",
            "satici_vergi_numarasi": "9000068418",
            "alici_firma_unvani": "Fatura Tarihi",
            "alici_email": "test@test.com",
            "fatura_tarihi": "29-04-2023",
            "fatura_tipi": "SATIS Fatura",
            "siparis_no": "4",
            "genel_toplam": "94.400,00",
            "tarih": "29-04-2023",
            "para": "018,00",
            "vergi_no": "9000068418",
            "email": "test@test.com",
            "alici_ad_soyad": "Fatura Tarihi",
            "urun_miktar": "10",
            "duzenleme_saati": "11:20:00",
            "odenecek_tutar": "94.400,00 TL",
            "para_birimi": "TL",
            "kalemler": [],
            "fatura_numarasi": "RSE2003000000171"
        }
    },
    {
        "dosya": "27.08.2025_Gelen Fatura (1)\\28.07.2025-GCE2025000000020.pdf",
        "analiz_zamani": "2025-08-28 09:47:12",
        "ocr_istatistikleri": {
            "ortalama_guven_skoru": "64.42%",
            "toplam_kelime": 229,
            "gecerli_kelime": 152,
            "ham_metin_uzunlugu": 980,
            "ham_metin": "ENİ Ob ÇATALTEPE Mİ GÜLTEKİN ÇATALTEPE ZEN | OSMAN YILMAZ MAH. 608/4. SK. NO: 4 IÇ KAPI NO: 15 GEBZE/ iz Kone ae Gebze/ Kocaeli A ght is Tel: 5334262729 NE ALI E-Posta: gultekin.cataltepe@pargesoft.com Di © ix a Pass Vergi Dairesi: ilyasbey a VKN: 9000068418 e-FATURA parr Fa Özelleştirme No: TR1.2 TEST ANONİM SİRKETİ ORTAKÖY M he Fatura Tipi: SATIS Silivri/ Istanbul Fatura No: Oooo |GCE2025000000020 Vergi Dairesi: YENİKAPI VERGİ DAİRESİ MÜD. Fatura Tarihi: 01-07-2025 VKN: 9000068418 Düzenleme Tarihi: (o (01-07-2025 aaa Düzenleme Saati: 21:54:00 ETİN: 9f30d2e9-2ce3-4938-ad38-f34256b1c0f3 [Sra] | Miktar Birim Fiyat Iskonto KDV Tutarı Diğer Vergiler | Mal Hizmet Tutarı MAYIS AYI HİZMET i | O| O 22.119,80TL| 110.599,00 TL Mal Hizmet Toplam Tutarı) 110.599,00 TL Toplam İskonto 0,00 TL Hesaplanan KDV GERCEK(%20) 22.119,80 TL Vergiler Dahil Toplam Tutar) 132.718,80 TL Ödenecek Tutar) 132.718,80 TL Yazı ile: # Yüz Otuz İki Bin Yedi Yüz On Sekiz TL Seksen KRŞ # PO-0003699008"
        },
        "regex": {
            "tarih": [
                "01-07-2025"
            ],
            "para": [
                "22.119,80TL",
                "110.599,00 TL",
                "0,00 TL",
                "22.119,80 TL",
                "132.718,80 TL"
            ],
            "iban": [],
            "fatura_no": [],
            "vergi_no": [
                "9000068418"
            ],
            "tc_no": [],
            "telefon": [],
            "email": [
                "gultekin.cataltepe@pargesoft.com"
            ],
            "fatura_tipi": [
                "e-FATURA"
            ],
            "kdv_orani": [],
            "ettn": [],
            "mersis_no": [],
            "ticaret_sicil": [],
            "musteri_no": [],
            "mal_hizmet_kodu": [],
            "alici_ad_soyad": [],
            "alici_adres": [],
            "urun_aciklama": [],
            "urun_miktar": [],
            "birim_fiyat": [],
            "odeme_sekli": [],
            "kargo_bilgisi": [],
            "siparis_no": [],
            "fatura_tarihi": [
                "01-07-2025"
            ],
            "duzenleme_saati": [
                "21:54:00"
            ],
            "satici_vkn": [],
            "alici_vkn": [],
            "odenecek_tutar": [],
            "doviz_kuru": [],
            "para_birimi": [
                "TL"
            ]
        },
        "structured": {
            "alici_email": "gultekin.cataltepe@pargesoft.com",
            "alici_telefon": "5334262729",
            "fatura_numarasi": "GCE2025000000020",
            "fatura_tarihi": "01-07-2025",
            "fatura_tipi": "SATIS Silivri",
            "genel_toplam": "132.718,80",
            "tarih": "01-07-2025",
            "para": "22.119,80TL",
            "vergi_no": "9000068418",
            "email": "gultekin.cataltepe@pargesoft.com",
            "duzenleme_saati": "21:54:00",
            "para_birimi": "TL",
            "kalemler": []
        }
    },
    {
        "dosya": "27.08.2025_Gelen Fatura (1)\\28.09.2024-PRT2024000003551.pdf",
        "analiz_zamani": "2025-08-28 09:47:13",
        "ocr_istatistikleri": {
            "ortalama_guven_skoru": "73.85%",
            "toplam_kelime": 291,
            "gecerli_kelime": 215,
            "ham_metin_uzunlugu": 1387,
            "ham_metin": "\\RILTIM END.TOPLU YEMEK HİZ.TUR.SAN VE TİC.A.Ş. uhasebe ÖZTEPE MAH. EKSEN SOK. NO:8/1 BEYKOZ/ İSTANBUL İstanbul EN 4815 Beykoz/ İstanbul RY 0 al: 0216 465 96 66 Fax: 0216 465 97 17 7 & Veb Sitesi: www.pariltim-newrest.com Ao Ni aft -Posta: muhasebe@pariltim-newrest.eu he Ab Jergi Dairesi: BEYKOZ ae JKN: 9000068418 TICARETSİCİLNO: 702892-0 e-FATURA MERSISNO: 0721038111300018 SAYIN SOA TOPLU YEMEK URETIM VE SERVIS A.S. özelleştirme No: SOR TOPLU YEMEK ÜRETİM 8 MM Çaybaşı Mahallesi Aydın Caddesi No:51 35880 Torbali İzmir İZMİR a Tel: 0530 763 15 49 Fax: 0530 763 15 49 Fatura Tarihi: 14-09-2024 Vergi Dairesi: KOZYATAGI Düzenleme Tarihi: 14-09-2024 VEN: 9000068418 Saati: (00:00:01 aş İrsaliye Tarihi: 08-09-2024 ETİN: Gi İskonto | İskonto KDV - . . oe YEMEGI-SOA YEMEK 1 Fen 92,00000000 Ld %10,00| 11.454,00 \"en 114.540,00 TU 3 [SOA -POGACA BEDELİ: | 555 Adet|___10,00000000 NE 7 ÇORBA BEDELİ-SOA 4 YEMEK 10,00000000 TL 10,00 Mal Hizmet Toplam Tutarı 206.140,00 TL Toplam İskonto 000TL Hesaplanan GERÇEK USÜLDE KATMA DEĞER VERGİSİ(Y010) 20.614,00 TL Vergiler Dahil Toplam Tutar 226.754,00 TL 226.754,00 TL iki yüz yirmi altı bin yedi yüz elli dört türk lirası #SEVKADRESİ: SOA TOPLU YEMEK ÜRETİM VE SERVİS A.Ş. Gaybaşi Mahallesi Aydın Caddesi No:51 35880 Torbalı İzmir Torbalı 35880 İZMİR 50.30.02 - İzmir MM Kemalpaşa Osb. 18. Sok No:132 Kemalpaşa/ İzmir izmir İzmir 34000 EGE BÖLGE"
        },
        "regex": {
            "tarih": [
                "14-09-2024",
                "08-09-2024",
                "50.30.02"
            ],
            "para": [
                "10,00",
                "11.454,00",
                "114.540,00",
                "206.140,00 TL",
                "20.614,00 TL",
                "226.754,00 TL"
            ],
            "iban": [],
            "fatura_no": [],
            "vergi_no": [],
            "tc_no": [],
            "telefon": [],
            "email": [
                "muhasebe@pariltim-newrest.eu"
            ],
            "fatura_tipi": [
                "e-FATURA"
            ],
            "kdv_orani": [],
            "ettn": [],
            "mersis_no": [
                "072103811130001"
            ],
            "ticaret_sicil": [
                "702892"
            ],
            "musteri_no": [],
            "mal_hizmet_kodu": [],
            "alici_ad_soyad": [
                "SOA TOPLU YEMEK URETIM VE"
            ],
            "alici_adres": [],
            "urun_aciklama": [],
            "urun_miktar": [
                "555"
            ],
            "birim_fiyat": [],
            "odeme_sekli": [],
            "kargo_bilgisi": [],
            "siparis_no": [],
            "fatura_tarihi": [
                "14-09-2024"
            ],
            "duzenleme_saati": [],
            "satici_vkn": [],
            "alici_vkn": [],
            "odenecek_tutar": [],
            "doviz_kuru": [],
            "para_birimi": [
                "TL"
            ]
        },
        "structured": {
            "satici_firma_unvani": "VE TİC.A.Ş.",
            "alici_firma_unvani": "SOA TOPLU YEMEK URETIM VE SERVIS A.S. özelleştirme No",
            "alici_telefon": "0530 763 15 49",
            "fatura_tarihi": "14-09-2024",
            "genel_toplam": "226.754,00",
            "mal_hizmet_toplam": "206.140,00",
            "tarih": "14-09-2024",
            "para": "10,00",
            "email": "muhasebe@pariltim-newrest.eu",
            "kalemler": [
                {
                    "tutar": "USÜLDE",
                    "aciklama": "GERÇEK"
                },
                {
                    "aciklama": "DEĞER",
                    "tutar": "VERGİSİ(Y010)",
                    "tutar_num": 10.0
                },
                {
                    "tutar": "Toplam",
                    "aciklama": "Dahil Vergiler"
                },
                {
                    "tutar": "İZMİR 35880",
                    "aciklama": "Torbalı İzmir",
                    "tutar_num": 35880.0
                }
            ]
        }
    },
    {
        "dosya": "27.08.2025_Gelen Fatura (1)\\28.09.2024-PRT2024000003547.pdf",
        "analiz_zamani": "2025-08-28 09:47:13",
        "ocr_istatistikleri": {
            "ortalama_guven_skoru": "74.98%",
            "toplam_kelime": 273,
            "gecerli_kelime": 212,
            "ham_metin_uzunlugu": 1350,
            "ham_metin": "PARILTIM END.TOPLU YEMEK HIZ.TUR.SAN, VE TİC.A.Ş, GÖZTEPE MAH, EKSEN SOK. NO:8/1 BEYKOZ/ İSTANBUL İstanbul ee 34815 Beykoz/ istanbul ON Tel: 0216 465 96 66 Fax: 0216 465 97 17 & P/0: ? Web Sitesi; Www. pariltim-newrest,com Ve, if af E-Posta; muhasebe@pariltim-newrest.ey Nee ie Vergi Dairesi: BEYKOz erent aes” VKN: 9000068418 TICARETSICILNO: 702892-0 e-FATURA MERSISNO: 0721038111300018 SAYIN SOA TOPLU YEMEK ÜRETİM VE SERVİS AS. Özelleştirme No: TR1.2 SOA TOPLU YEMEK URETIM VE SERVIS AS. Senaryo: o Çaybaşı Mahallesi Aydın Caddesi No:51 35880 Torbalı İzmir Fatura Tipi SATIŞ 35880 Torbalı / İzle E-Posta; goktug.akishalioglu@soa.com.tr Fatura Tel: 0530 763 15 49 Fax: 0530 763 15 49 Fatura 74.09 2050 Vergi KOZYATAĞI Düzenleme Tarihi; 14-09-2024 VKN: 9000068418 Düzenleme Saati: ETIN: Se İrsaliye Tarihi; 08-09-2024 ETIN: Pn İskonto İskonto KDV ay . a 1. İSA BEDELI- [355 Adel 10,00000000 TL | | —— %10,00 Sa — Mal Hizmet Toplam Tutarı 206.140,00 TL Toplam İskonto | 00071 Hesaplanan GERCEK USULDE KATMA DEĞER | TL Vergiler Dahil Toplam Tutar 226.754,00 TL 226.754,00 TL iki yüz yirmi altı bin Yedi yüz elli dört türk lirası #SEVKADRESİ: SOA TOPLU YEMEK ÜRETİM VE SERVİS AS. Çaybaşı Mahallesi Aydın Caddesi No:51 35880 Torbalı İzmir Torbalı 35880 IZMIR 50.30.02 - Izmir MM Kemalpaşa Osb, 18, Sok No:132 Kemalpaşa/ izmir İzmir İzmir 34000 EGE BÖLGE"
        },
        "regex": {
            "tarih": [
                "14-09-2024",
                "08-09-2024",
                "50.30.02"
            ],
            "para": [
                "10,00",
                "206.140,00 TL",
                "226.754,00 TL"
            ],
            "iban": [],
            "fatura_no": [],
            "vergi_no": [
                "9000068418"
            ],
            "tc_no": [],
            "telefon": [],
            "email": [
                "muhasebe@pariltim-newrest.ey",
                "goktug.akishalioglu@soa.com.tr"
            ],
            "fatura_tipi": [
                "e-FATURA"
            ],
            "kdv_orani": [],
            "ettn": [],
            "mersis_no": [
                "072103811130001"
            ],
            "ticaret_sicil": [
                "702892"
            ],
            "musteri_no": [],
            "mal_hizmet_kodu": [],
            "alici_ad_soyad": [
                "SOA TOPLU YEMEK ÜRETİM VE"
            ],
            "alici_adres": [],
            "urun_aciklama": [],
            "urun_miktar": [
                "355"
            ],
            "birim_fiyat": [],
            "odeme_sekli": [],
            "kargo_bilgisi": [],
            "siparis_no": [],
            "fatura_tarihi": [],
            "duzenleme_saati": [],
            "satici_vkn": [],
            "alici_vkn": [],
            "odenecek_tutar": [],
            "doviz_kuru": [],
            "para_birimi": [
                "TL"
            ]
        },
        "structured": {
            "satici_firma_unvani": "ie TICARET",
            "satici_vergi_numarasi": "9000068418",
            "satici_mersis_no": "0721038111300018",
            "alici_firma_unvani": "SOA TOPLU YEMEK ÜRETİM VE SERVİS AS. Özelleştirme No",
            "alici_telefon": "0216 465 96 66",
            "fatura_tipi": "SATIŞ",
            "genel_toplam": "226.754,00",
            "tarih": "14-09-2024",
            "para": "10,00",
            "vergi_no": "9000068418",
            "email": "muhasebe@pariltim-newrest.ey",
            "mersis_no": "072103811130001",
            "ticaret_sicil": "702892",
            "alici_ad_soyad": "SOA TOPLU YEMEK ÜRETİM VE",
            "urun_miktar": "355",
            "para_birimi": "TL",
            "kalemler": [],
            "fatura_numarasi": "PRT2024000003547",
            "fatura_tarihi": "14-09-2024"
        }
    },
    {
        "dosya": "27.08.2025_Gelen Fatura (1)\\30.03.2023-MNT2023000000035.pdf",
        "analiz_zamani": "2025-08-28 09:47:13",
        "ocr_istatistikleri": {
            "ortalama_guven_skoru": "66.00%",
            "toplam_kelime": 243,
            "gecerli_kelime": 167,
            "ham_metin_uzunlugu": 1073,
            "ham_metin": "UYUMSOFT BİLGİ SİSTEMLERİ VE TEKNOLOJİLERİ TİCARET i fw T t T 0, << ee el a ote ANONİM ŞİRKETİ EŞ Tel: test@test.com Fax: 5 : f ON oe eal oy Web Sitesi: http://www.test.com a a fsa ate E-Posta: test@test.com NG i es ig Vergi Dairesi: test3 e oT: : VKN: 9000068418 TICARETSICILNO: 12345f Ir ek: ep MERSISNO: 11111111111111 e-FATURA [SSS cc ç ÖzelleştirmeNo: İRİ? Senaryo: İTICARIFATURA SAYIN Fatura Tipi: SATIS Usktidar/ Istanbul Fatura Tarihi: 30-03-2023 VKN: 9000068418 Düzenleme Tarihi: (30-03-2023 —— cc Cc Se Düzenleme Saati: 14:56:00 ETİN: dd3i6eb3-4c29-437a-8770-83db57816bc6 Birim Fiyat İskonto | İskonto KDV KDV Tutarı Diğer Vergiler | Mal Hizmet Tutarı Oranı Tutarı Oranı STİLO POŞET DOSYA ÖTV 4.LİSTE 100'lü 1 Adet} 84.745,76000000 TL | | % 18,00} 25.932,20 TY 84.745,76 TL Mal Hizmet Toplam Tutarı 84.745,76 TL Toplam İskonto 0,00 TL Hesaplanan KDW 9018.00) 25.932,20 TL Hesaplanan ÖTV 4.LISTE(%70.000)| _59.322,03 TL Vergiler Dahil Toplam Tutar 169.999,99 TL Ödenecek Tutar) TL Yalnız #Yüz Altmış Dokuz Bin Dokuz Yüz Doksan Dokuz Türk Lirası Doksan Dokuz Kurus#"
        },
        "regex": {
            "tarih": [
                "30-03-2023"
            ],
            "para": [
                "18,00",
                "25.932,20",
                "84.745,76 TL",
                "0,00 TL",
                "25.932,20 TL",
                "322,03 TL",
                "169.999,99 TL"
            ],
            "iban": [],
            "fatura_no": [],
            "vergi_no": [
                "9000068418"
            ],
            "tc_no": [],
            "telefon": [],
            "email": [
                "test@test.com"
            ],
            "fatura_tipi": [
                "e-FATURA"
            ],
            "kdv_orani": [],
            "ettn": [],
            "mersis_no": [],
            "ticaret_sicil": [],
            "musteri_no": [],
            "mal_hizmet_kodu": [],
            "alici_ad_soyad": [
                "Fatura Tipi"
            ],
            "alici_adres": [],
            "urun_aciklama": [],
            "urun_miktar": [
                "1"
            ],
            "birim_fiyat": [],
            "odeme_sekli": [],
            "kargo_bilgisi": [],
            "siparis_no": [],
            "fatura_tarihi": [
                "30-03-2023"
            ],
            "duzenleme_saati": [
                "14:56:00"
            ],
            "satici_vkn": [],
            "alici_vkn": [],
            "odenecek_tutar": [],
            "doviz_kuru": [],
            "para_birimi": [
                "TL"
            ]
        },
        "structured": {
            "satici_vergi_dairesi": "test",
            "satici_vergi_numarasi": "9000068418",
            "satici_email": "test@test.com",
            "satici_ticaret_sicil": "12345",
            "alici_firma_unvani": "Fatura Tipi",
            "alici_email": "test@test.com",
            "fatura_tarihi": "30-03-2023",
            "fatura_tipi": "SATIS Usktidar",
            "genel_toplam": "169.999,99",
            "tarih": "30-03-2023",
            "para": "18,00",
            "vergi_no": "9000068418",
            "email": "test@test.com",
            "alici_ad_soyad": "Fatura Tipi",
            "urun_miktar": "1",
            "duzenleme_saati": "14:56:00",
            "para_birimi": "TL",
            "kalemler": []
        }
    },
    {
        "dosya": "27.08.2025_Gelen Fatura (1)\\28.09.2024-PRT2024000003563.pdf",
        "analiz_zamani": "2025-08-28 09:47:13",
        "ocr_istatistikleri": {
            "ortalama_guven_skoru": "76.73%",
            "toplam_kelime": 279,
            "gecerli_kelime": 207,
            "ham_metin_uzunlugu": 1415,
            "ham_metin": "PARILTIM END.TOPLU YEMEK HİZ.TUR.SAN.VE TİC.A.Ş. Muhasebe GÖZTEPE MAH. EKSEN SOK. NO:8/1 BEYKOZ/ İSTANBUL İstanbul 34815 Beykoz/ İstanbul ON Tel: 0216 465 96 66 Fax: 0216 465 97 17 fom Web Sitesi: www.pariltim-newrest.com Ne. “gf! E-Posta: muhasebe@pariltim-newrest.eu “ Ab Vergi Dairesi: BEYKOZ eee VKN: 9000068418 TICARETSICILNO: 702892-0 e-FATURA MERSISNO: 0721038111300018 SAYIN BESER BALATACILIK SAN.VE TİC.A.Ş. Özelleştirme No: BEŞER BALATACILIK SAN.VE TİC.A.Ş. o oo İTICARIFATURA iz atra İSA 35080 BORNOVA/ İZMİR EPosta guler Tel: 0530 425 97 53 Fatura Tarihi: 14-09-2024 Vergi Dairesi, BORNOVA Düzenleme Tarihi: 14-09-2024 VEN: 9000068418 Saati: İrsaliye Tarihi: 08-09-2024 ETİN: d90b9219-bf00-4893-9bf2-fec6371e92b0 im ee iskonto | Iskonto | KDV wy . . m Tm | | e ve KAHVALTI-BEŞER o ÖĞLE YEMEĞİ-BEŞER 1.480 o AKŞAM YEMEĞİ-BEŞER 9 3 BALATACILIK-İZMİR MM 400 Adet 92,00000000 | | 10,00) 3.680,00 TL 36.800,00 TL AYRAN-BEŞER 3.200 o SODA-BEŞER | 2.500 Mal Hizmet Toplam Tutarı 236.948,00 TL Toplam İskonto Hesaplanan GERÇEK USÜLDE KATMA DEĞER VERGİSİ(Y010) 23.694,80 TL Vergiler Dahil Toplam Tutar 260.642,80 TL Ödenecek Tutar) _260.642,80 TL 8-14.09 FATURASI iki yüz altmış bin altı yüz kırk iki türk lirası ve seksen Kuruş #SEVKADRESI: BEŞER BALATACILIK SAN.VE TİC.A.Ş. ANKARA CAD. NO: 309 BORNOVA 35080 İZMİR 50.30.02 - İzmir MM 7 Kemalpaşa Osb. 18. Sok No:132 Kemalpaşa/ İzmir İzmir İzmir 34000 EGE BÖLGE"
        },
        "regex": {
            "tarih": [
                "14-09-2024",
                "08-09-2024",
                "8-14.09",
                "50.30.02"
            ],
            "para": [
                "10,00",
                "3.680,00 TL",
                "36.800,00 TL",
                "236.948,00 TL",
                "23.694,80 TL",
                "260.642,80 TL",
                "642,80 TL"
            ],
            "iban": [],
            "fatura_no": [],
            "vergi_no": [
                "9000068418"
            ],
            "tc_no": [],
            "telefon": [],
            "email": [
                "muhasebe@pariltim-newrest.eu"
            ],
            "fatura_tipi": [
                "e-FATURA"
            ],
            "kdv_orani": [],
            "ettn": [],
            "mersis_no": [
                "072103811130001"
            ],
            "ticaret_sicil": [
                "702892"
            ],
            "musteri_no": [],
            "mal_hizmet_kodu": [],
            "alici_ad_soyad": [
                "BESER BALATACILIK SAN.VE"
            ],
            "alici_adres": [],
            "urun_aciklama": [],
            "urun_miktar": [
                "400"
            ],
            "birim_fiyat": [],
            "odeme_sekli": [],
            "kargo_bilgisi": [],
            "siparis_no": [],
            "fatura_tarihi": [
                "14-09-2024"
            ],
            "duzenleme_saati": [],
            "satici_vkn": [],
            "alici_vkn": [],
            "odenecek_tutar": [],
            "doviz_kuru": [],
            "para_birimi": [
                "TL"
            ]
        },
        "structured": {
            "satici_firma_unvani": "TİC.A.Ş.",
            "alici_firma_unvani": "BESER BALATACILIK SAN.VE TİC.A.Ş. Özelleştirme No",
            "alici_email": "muhasebe@pariltim-newrest.eu",
            "alici_telefon": "0216 465 96 66",
            "fatura_tarihi": "14-09-2024",
            "genel_toplam": "260.642,80",
            "tarih": "14-09-2024",
            "para": "10,00",
            "vergi_no": "9000068418",
            "email": "muhasebe@pariltim-newrest.eu",
            "kalemler": [],
            "ettn": "d90b9219-bf00-4893-9bf2-fec6371e92b0"
        }
    },
    {
        "dosya": "27.08.2025_Gelen Fatura (1)\\28.09.2024-PRT2024000003502.pdf",
        "analiz_zamani": "2025-08-28 09:47:14",
        "ocr_istatistikleri": {
            "ortalama_guven_skoru": "76.96%",
            "toplam_kelime": 319,
            "gecerli_kelime": 244,
            "ham_metin_uzunlugu": 1562,
            "ham_metin": "PARILTIM END.TOPLU YEMEK HİZ.TUR.SAN.VE TİC.A.Ş. GÖZTEPE MAH, EKSEN SOK. NO:8/1 BEYKOZ/ İSTANBUL İstanbul ee 34815 Beykoz/ Istanbul fy = ON Tel: 0216 465 96 66 Fay: 0216 465 97 17 2 Web Sitesi: Www. pariltim-newrest,com Ve if nf E-Posta; muhasebe@pariltim-newrest.ey AN , iS Vergi Dairesi: BEYKOz erent aes” VKN: 9000068418 TICARETSICILNO: 702892-0 e-FATURA MERSISNO: 0721038111300018 SAYIN AKFEN TURIZM YATIRIMLARI VE ISLET MECİLİK A.Ş, Özelleştirme No: TR1.2 AKFEN TURIZM YATIRIMLARI VE İŞLETMECİLİK AS. TEMELFATURA KOZA CAD No:2 GOP ÇANKAYA/ANKARA Dara Fatura Tipi; SATIS 06700 ÇANKAYA / ANKARA E-Posta; Muhtur@akfen.com tr ara No: — Vel 312 441 42 11 Fax: 312 443 49 44 kura Tarihte 5994 Vergi Dairesi: CUMHURİYET Düzenleme Tarihi: 07-09-2024 VKN: 9000068418 Düzenleme Saati: ETIN: İrsaliye Tarihi: 01-09-2024 ETI: irim Eş İskonto İskonto KDV m | = KAHVALTI- AKFEN TURIZM | LOFT OTEL (BODRUM ban) Ez 67000000 | yo Th KUMANYA- AKFEN TURIZM ° OGLE YEMEĞİ-AKFEN TURİZM LOFT OTEL 505 Adet 121,18000000 TL “610,00 61.195,90 TL, (BODRUM MM) AKŞAM YEMEĞİ- AKFEN TURİZM LOFT OTEL 625 Adet Tı. “610,00 (BODRUM MM) Mal Hizmet Toplam Tutarı | 231353507) Toplam İskonto | Hesaplanan GERÇEK USÜLDE KATMA DEĞER 2610) Vergiler Dahil Toplam Tutar 254.488,85 TL 254.488,85 TL 1-7 EYLUL LOFT YEMEK SAYILARI, iki yüz elli dört bin dört yüz seksen Sekiz türk lirası ve seksen beş kuruş 7 7 #SEVKADRESI: Akfen Sevk Adresi GÖLKÖY MAH.325.SOKAK NO:7 BODRUM/MUĞLA BODRUM 48400 MUĞLA 50.20.01 - Bodrum MM . Konacık Mah. Gazderesi cad, No21-3 Bodrum/ Muğla Muğla Muğla 34000 EGE BÖLGE"
        },
        "regex": {
            "tarih": [
                "07-09-2024",
                "01-09-2024",
                "50.20.01"
            ],
            "para": [
                "610,00",
                "61.195,90 TL",
                "254.488,85 TL"
            ],
            "iban": [],
            "fatura_no": [],
            "vergi_no": [
                "9000068418"
            ],
            "tc_no": [],
            "telefon": [],
            "email": [
                "muhasebe@pariltim-newrest.ey",
                "Muhtur@akfen.com"
            ],
            "fatura_tipi": [
                "e-FATURA"
            ],
            "kdv_orani": [],
            "ettn": [],
            "mersis_no": [
                "072103811130001"
            ],
            "ticaret_sicil": [
                "702892"
            ],
            "musteri_no": [],
            "mal_hizmet_kodu": [],
            "alici_ad_soyad": [
                "AKFEN TURIZM YATIRIMLARI"
            ],
            "alici_adres": [],
            "urun_aciklama": [],
            "urun_miktar": [
                "505",
                "625"
            ],
            "birim_fiyat": [],
            "odeme_sekli": [],
            "kargo_bilgisi": [],
            "siparis_no": [],
            "fatura_tarihi": [],
            "duzenleme_saati": [],
            "satici_vkn": [],
            "alici_vkn": [],
            "odenecek_tutar": [],
            "doviz_kuru": [],
            "para_birimi": [
                "TL"
            ]
        },
        "structured": {
            "satici_firma_unvani": "PARILTIM END.TOPLU YEMEK HİZ.TUR.SAN.VE GÖZTEPE TİC.A.Ş.",
            "alici_firma_unvani": "AKFEN TURIZM YATIRIMLARI VE ISLET MECİLİK A.Ş",
            "alici_telefon": "0216 465 96 66",
            "genel_toplam": "254.488,85",
            "tarih": "07-09-2024",
            "para": "610,00",
            "vergi_no": "9000068418",
            "email": "muhasebe@pariltim-newrest.ey",
            "kalemler": [
                {
                    "aciklama": "OGLE YEMEĞİ-AKFEN TURİZM LOFT OTEL 505 Adet",
                    "tutar": "121,18000000 TL"
                },
                {
                    "aciklama": "OGLE",
                    "birim_fiyat": "YEMEĞİ-AKFEN TURİZM LOFT OTEL 505 Adet",
                    "tutar": "121,18000000 TL"
                }
            ],
            "fatura_numarasi": "PRT2024000003502",
            "fatura_tarihi": "07-09-2024"
        }
    },
    {
        "dosya": "27.08.2025_Gelen Fatura (1)\\30.06.2024-KPS2024000000054.pdf",
        "analiz_zamani": "2025-08-28 09:47:14",
        "ocr_istatistikleri": {
            "ortalama_guven_skoru": "64.67%",
            "toplam_kelime": 298,
            "gecerli_kelime": 197,
            "ham_metin_uzunlugu": 1163,
            "ham_metin": "il yr ex > Kepsoft Yazılım A Te et 1 No:1 MERKEZ/ BARTIN feat at ao Vergi Dairesi: Bartın Ne. my ir VKN: 9000068418 Nez Ta MERSISNO: 1 east fae mi aes TICARETSICILNO: 1 SAYIN TEST FRIMAS TEST ADRESI Ozellestirme No: TR1.2 Roan Senaryo: — İTICARIFATURA | Fatura Tipi: BARTIN/ BARTIN : E-Posta: Bos Fatura Tel: 05050000000 Fax: 05050000000 Fatura Tarihi: Vergi Dairesi: MERKEZ Düzenleme Tarihi: VKN: 9000068418 Düzenleme Saati: , Sipariş Tarihi; 30-06-2024 ETİN; 86€5232d-112d-4ada-b492-3363dbe1b333 . iskonto | iskonto KDV wy . . e m 234 TL 61,00 | mı) — 115.841,58 TL 2 İACIBİBERTANE 234 (o 495,05000000 TL | SC 115.841,58 TL ACI BIBER TANE yi 495,05000000 TL | 11.608,92 TL | 1.160.891,08 TL Mal Hizmet Toplam Tutarı 1.392.574,24 TL Toplam İskonto | 000TH Hesaplanan KDV(%18) | Vergiler Dahil Toplam Tutar 1.406.500,00 TL Ödenecek Tutar 1.406.500,00 TL Kdv % : 18 Matrah : 18.00 Kdv Tutar : 663.56 Kdv % : 1 Matrah : 1.00 Kdv Tutar : 13925.76 Yazı İle: BİRMİLYONDÖRTYÜZALTIBİNBEŞYÜZ TÜRK LİRASI SIFIR KURUŞ. Kdv % : 18 Matrah : 18.00 Kdv Tutar : 663.56 Kdv % + 1 Matrah : 1.00 Kdv Tutar : 13925,76 Yazı İle: BİRMİLYONDÖRTYÜZALTIBİNBEŞYÜZ TÜRK LİRASI SIFIR KURUŞ."
        },
        "regex": {
            "tarih": [
                "30-06-2024"
            ],
            "para": [
                "61,00",
                "115.841,58 TL",
                "11.608,92 TL",
                "1.160.891,08 TL",
                "1.392.574,24 TL",
                "1.406.500,00 TL",
                "13925,76"
            ],
            "iban": [],
            "fatura_no": [],
            "vergi_no": [
                "9000068418"
            ],
            "tc_no": [],
            "telefon": [
                "05050000000"
            ],
            "email": [],
            "fatura_tipi": [],
            "kdv_orani": [],
            "ettn": [],
            "mersis_no": [],
            "ticaret_sicil": [],
            "musteri_no": [],
            "mal_hizmet_kodu": [],
            "alici_ad_soyad": [
                "TEST FRIMAS TEST ADRESI"
            ],
            "alici_adres": [],
            "urun_aciklama": [],
            "urun_miktar": [
                "4"
            ],
            "birim_fiyat": [],
            "odeme_sekli": [],
            "kargo_bilgisi": [],
            "siparis_no": [],
            "fatura_tarihi": [],
            "duzenleme_saati": [],
            "satici_vkn": [],
            "alici_vkn": [],
            "odenecek_tutar": [
                "1.406.500,00 TL"
            ],
            "doviz_kuru": [],
            "para_birimi": [
                "TL"
            ]
        },
        "structured": {
            "satici_firma_unvani": "east TICARET",
            "satici_vergi_dairesi": "Bartın feat at ao VKN",
            "satici_vergi_numarasi": "9000068418",
            "satici_ticaret_sicil": "1",
            "alici_firma_unvani": "TEST FRIMAS TEST ADRESI Ozellestirme No",
            "alici_telefon": "05050000000",
            "fatura_tipi": "BARTIN",
            "genel_toplam": "1.406.500,00",
            "mal_hizmet_toplam": "1.392.574,24",
            "tarih": "30-06-2024",
            "para": "61,00",
            "vergi_no": "9000068418",
            "telefon": "05050000000",
            "alici_ad_soyad": "TEST FRIMAS TEST ADRESI",
            "urun_miktar": "4",
            "odenecek_tutar": "1.406.500,00 TL",
            "para_birimi": "TL",
            "kalemler": [],
            "fatura_numarasi": "kPs2024000000054",
            "fatura_tarihi": "Fatura Tarihi: [30-06-2024"
        }
    },
    {
        "dosya": "27.08.2025_Gelen Fatura (1)\\28.09.2024-PRT2024000003555.pdf",
        "analiz_zamani": "2025-08-28 09:47:14",
        "ocr_istatistikleri": {
            "ortalama_guven_skoru": "74.78%",
            "toplam_kelime": 348,
            "gecerli_kelime": 270,
            "ham_metin_uzunlugu": 1732,
            "ham_metin": "PARILTIM END.TOPLU YEMEK HİZ.TUR.SAN.VE TİC.A.Ş. Muhasebe mz GÖZTEPE MAH. EKSEN SOK. NO:8/1 BEYKOZ/ İSTANBUL İstanbul m 34815 Beykoz/ İstanbul (A Tel: 0216 465 96 66 Fax: 0216 465 97 17 fey & Web Sitesi: www.pariltim-newrest.com Ne E-Posta: muhasebe@pariltim-newrest.eu Ka ak er 5 Vergi Dairesi: BEYKOZ e ii VKN: 9000068418 TICARETSICILNO: 702892-0 e-FATURA MERSISNO: 0721038111300018 LEE İŞ SAYIN SOA TOPLU YEMEK ÜRETİM VE SERVİS A.Ş. Özelleştirme No: TR1.2 SOA TOPLU YEMEK ÜRETİM VE SERVİS A.Ş. İTICARIFATURA Çaybaşı Mahallesi Aydın Caddesi No:51 35880 Torbalı İzmir İFatura Tipi: 35880 İZMİR E-Posta: goktug.akishalioglu@soa.com.tr — PRT2024000003555 Tel: 0530 763 15 49 Fax: 0530 763 15 49 Fatura Tarihi: 14-09-2024 Vergi Dairesi: KOZYATAĞI Düzenleme Tarihi: 14-09-2024 VKN: 9000068418 Düzenleme Saati: 00:00:01 ETİN: fa68370a-bbba-4e29-a6c4-3699c6abc47c a İskonto | İskonto | KDV wy . . [or | on rr öte Tm ÖĞLE YEMEĞİ-SOA YEMEK e 92,00000000 TL 11.454,00 | 114.540,00 TL 2 YEMEGI-SOA 775 Adet | 410,00) | 7.130,00 | 71.300,00 TL İ3 O [SOA -POGACA BEDELI- 355 Adet 10,00000000 TL) O (910,00) Cs 3.550,00 TL 4 Çe BEDELI-SOA 355 Adet 10,00000000 no | | 355,00 yo 3.550,00 TL 5 220 Adet (© 60,00000000 no | | %10,00] | 1.320,00 13.200,00 TL Mal Hizmet Toplam Tutarı) 206.140,00 TL Toplam İskonto 0,00 TL Hesaplanan GERÇEK USÜLDE KATMA DEĞER VERGISI(%10)} | Vergiler Dahil Toplam Tutar) 226.754,00 TL Ödenecek Tutar) 226.754,00 TL 8-14.09 FATURASIDIR iki yüz yirmi altı bin yedi yüz elli dört türk lirası #SEVKADRESI: SOA TOPLU YEMEK ÜRETİM VE SERVİS A.Ş. Çaybaşı Mahallesi Aydın Caddesi No:51 35880 Torbalı izmir Torbalı 35880 İZMİR 50.30.02 - Izmir MM , . Kemalpaşa Osb. 18. Sok No:132 Kemalpaşa/ Izmir Izmir Izmir 34000 EGE BÖLGE"
        },
        "regex": {
            "tarih": [
                "14-09-2024",
                "8-14.09",
                "50.30.02"
            ],
            "para": [
                "11.454,00",
                "114.540,00 TL",
                "410,00",
                "7.130,00",
                "71.300,00 TL",
                "910,00",
                "3.550,00 TL",
                "355,00",
                "10,00",
                "1.320,00"
            ],
            "iban": [],
            "fatura_no": [],
            "vergi_no": [
                "9000068418"
            ],
            "tc_no": [],
            "telefon": [],
            "email": [
                "muhasebe@pariltim-newrest.eu",
                "goktug.akishalioglu@soa.com.tr"
            ],
            "fatura_tipi": [
                "e-FATURA"
            ],
            "kdv_orani": [],
            "ettn": [],
            "mersis_no": [
                "072103811130001"
            ],
            "ticaret_sicil": [
                "702892"
            ],
            "musteri_no": [],
            "mal_hizmet_kodu": [],
            "alici_ad_soyad": [
                "SOA TOPLU YEMEK ÜRETİM VE"
            ],
            "alici_adres": [],
            "urun_aciklama": [],
            "urun_miktar": [
                "775",
                "355",
                "220"
            ],
            "birim_fiyat": [
                "10,00000000 TL"
            ],
            "odeme_sekli": [],
            "kargo_bilgisi": [],
            "siparis_no": [],
            "fatura_tarihi": [
                "14-09-2024"
            ],
            "duzenleme_saati": [
                "00:00:01"
            ],
            "satici_vkn": [],
            "alici_vkn": [],
            "odenecek_tutar": [],
            "doviz_kuru": [],
            "para_birimi": [
                "TL"
            ]
        },
        "structured": {
            "satici_firma_unvani": "TİC.A.Ş.",
            "satici_vergi_dairesi": "BEYKOZ",
            "satici_telefon": "0216 465 96 66",
            "alici_firma_unvani": "SOA TOPLU YEMEK ÜRETİM VE SERVİS A.Ş. Özelleştirme No",
            "alici_email": "muhasebe@pariltim-newrest.eu",
            "alici_telefon": "0216 465 96 66",
            "fatura_numarasi": "PRT2024000003555",
            "fatura_tarihi": "14-09-2024",
            "genel_toplam": "226.754,00",
            "tarih": "14-09-2024",
            "para": "11.454,00",
            "vergi_no": "9000068418",
            "email": "muhasebe@pariltim-newrest.eu",
            "kalemler": [
                {
                    "tutar": "USÜLDE",
                    "aciklama": "GERÇEK"
                },
                {
                    "tutar": "VERGISI(%10)}",
                    "aciklama": "DEĞER",
                    "tutar_num": 10.0
                },
                {
                    "tutar": "Toplam",
                    "aciklama": "Dahil"
                }
            ]
        }
    },
    {
        "dosya": "27.08.2025_Gelen Fatura (1)\\29.07.2024-PRT2024000003357.pdf",
        "analiz_zamani": "2025-08-28 09:47:18",
        "ocr_istatistikleri": {
            "ortalama_guven_skoru": "61.15%",
            "toplam_kelime": 478,
            "gecerli_kelime": 336,
            "ham_metin_uzunlugu": 2055,
            "ham_metin": "PARILTIM YEMEK TİC.A.Ş, po GÖZTEPE MAH, EKSEN SOK. NO:8/1 ANADOLU HİSARI BEYKOZ/ EN ISTANBUL istanbul fe 9 34815 İstanbul = 3 Web Sitesi; WWW. pariltim-newrest.com Ne yy: Vergi Dairesi: BEYKOZ Cente > VKN: 9000068418 TICARETSICILNO: MERSISNO: 0721038111300018 e-FATURA SAYIN MİNG KARGO YURTİÇİ VE YURTDIŞI MNG KARGO YURTİÇİ VE YURTDIŞI Özelleştirme No; No: PRİZ AYAZAĞA MAH. CENDERE Cap, 1B APT. NO:109 B/5-6-7.g TICARIFATURA 34396 SARIYER / O E-Posta; sakbulut@mngkargo.com,tr Fatura Tipi: Tel: 0212 366 59 97 Fax: 0212 366 55 65 No: Vergi Dairesi: Büyük MÜKELLEF, ER Fatura —— VEN: 90000684138 Düzenleme Tarihi: 29-07-2024 ETME Düzenleme Saati: EM: İskonto İskonto KDV we . . age Jalan (ee MİNG MARMARA 10 1 | %10,00 48,00 TL 480,00 TL AKŞAM YEMEĞİMNG 102 Adet) —110,00000000 71 %10,00 GEBZE AKŞAM YEMEĞİ H__ İSECEYEMEĞİ mg 26 Adet 110,00000000 O 1.056,00 10.560,00 TL sane NS GEBZE 178 Adet! sö 71, İN ?610,00) 854.49 71, 8.544,00 TL ÖĞLE VEMEĞİ-MNG _ BAKIRKÖY TEKNİK ÖĞLEN 64 110, 00000000 +7, %10,00 704.09 71 7.040,00 TL YEMEĞİ AKŞAM YEMEGI-MNG BAKIRKÖY TEKNİK AKŞAM 110,00000000 Tı. %10,00 7.920,00 TL YEMEĞİ GECE YEMEĞİ-MNG YAKIRKÖY TEKNİK GECE | gs Adet) — 110,00000000 %10,00 YEMEĞİ 163 se 00000000 71 İN %10,00 782.40 7, | 7.824,00 TL ÖĞLE YEMEGI-MNG _ TEKNİK ÖĞLEN | 47 Adet! 610,00 YEMEĞİ AKŞAM TEKNİK AKŞAM | g3 Adet! — 110,00000000 %10,00f 693,09 T 6.930,00 TL YEMEĞİ GECE YEMEĞİ-MNG TEKNİK GECE | g4 Adet! — 110,00000000 1 %10,00f 794,09 71, 7.040,00 TL YEMEĞİ ÖĞLE YEMEĞİ-MNG | İSTANBUL TEKNİK DİET 6 Adet} — 110,00000000 71 %10,00 66,00 TL 660,00 TL YEMEĞİ KUMANYA-GENEL-MNG 1 İİSTANBULTEKNİK 88,00000000 Tı. %10,00 KUMANYA | TEKNİK Sa ANBUL | 55 Adet! 71 %10,00f 384,09 3.840,00 TL 98 Adet 9,00000000 Tı. %10,00 88,20 TL | 882,00 TL OGLE YEMEGI-MNG ESENYURT A cy | 75 Ace 110,00000000 Tı. %10,00/ 825,09 71, | 8.250,00 TL ESENYURT aay 86 110, 00000000 %10,00/ 946,00 9.460,00 TL BEDELİ-MNG 181 Adet) 48, 00000000 71 | 868,80 71, 8.688,00 TL OGLE YEMEGI-MNG MARMARA AŞ e 60 —110,00000000 7010/00) 60,00 6.600,00 TL 20 00000000 71 %10,001"
        },
        "regex": {
            "tarih": [
                "29-07-2024"
            ],
            "para": [
                "10,00",
                "48,00 TL",
                "480,00 TL",
                "1.056,00",
                "10.560,00 TL",
                "610,00",
                "8.544,00 TL",
                "7.040,00 TL",
                "7.920,00 TL",
                "7.824,00 TL"
            ],
            "iban": [],
            "fatura_no": [],
            "vergi_no": [
                "9000068418"
            ],
            "tc_no": [],
            "telefon": [],
            "email": [
                "sakbulut@mngkargo.com"
            ],
            "fatura_tipi": [
                "e-FATURA"
            ],
            "kdv_orani": [],
            "ettn": [],
            "mersis_no": [
                "072103811130001"
            ],
            "ticaret_sicil": [],
            "musteri_no": [],
            "mal_hizmet_kodu": [],
            "alici_ad_soyad": [
                "MİNG KARGO YURTİÇİ VE"
            ],
            "alici_adres": [],
            "urun_aciklama": [],
            "urun_miktar": [
                "102",
                "26",
                "178",
                "47",
                "3",
                "4",
                "6",
                "55",
                "98",
                "181"
            ],
            "birim_fiyat": [],
            "odeme_sekli": [],
            "kargo_bilgisi": [
                "YURTİÇİ VE YURTDIŞI MNG"
            ],
            "siparis_no": [],
            "fatura_tarihi": [],
            "duzenleme_saati": [],
            "satici_vkn": [],
            "alici_vkn": [],
            "odenecek_tutar": [],
            "doviz_kuru": [],
            "para_birimi": [
                "TL"
            ]
        },
        "structured": {
            "satici_vergi_numarasi": "9000068418",
            "alici_firma_unvani": "MİNG KARGO YURTİÇİ VE YURTDIŞI MNG KARGO YURTİÇİ VE YURTDIŞI Özelleştirme No",
            "alici_telefon": "0212 366 59 97",
            "fatura_tipi": "Tel",
            "kargo_bilgisi": "YURTİÇİ VE YURTDIŞI MNG",
            "genel_toplam": "10.560,00",
            "tarih": "29-07-2024",
            "para": "10,00",
            "vergi_no": "9000068418",
            "email": "sakbulut@mngkargo.com",
            "mersis_no": "072103811130001",
            "alici_ad_soyad": "MİNG KARGO YURTİÇİ VE",
            "urun_miktar": "102",
            "para_birimi": "TL",
            "kalemler": [],
            "fatura_numarasi": "PRT2024000003357",
            "fatura_tarihi": "29-07-2024"
        }
    },
    {
        "dosya": "27.08.2025_Gelen Fatura (1)\\29.08.2023-GUR2023000015746.pdf",
        "analiz_zamani": "2025-08-28 09:47:25",
        "ocr_istatistikleri": {
            "ortalama_guven_skoru": "53.58%",
            "toplam_kelime": 664,
            "gecerli_kelime": 244,
            "ham_metin_uzunlugu": 1454,
            "ham_metin": "III ACME LOGISTICS MERKEZ MAH. BULVAR CAD. NO:1 11111 AFYON Tel: 1111 Fax: 5555 Web Sitesi: www.ACME.com.tr E-Posta: fatura@ACME.com Vergi Dairesi: ESENLER VKN: 9000068418 e-FATURA m m SAYIN TEST MÜŞTERİSİ DEFTERDAR MAH.OTAKCILAR CADDESİ.FLATOFİS İSTANBUL İŞ MERK.K:3 N:83 K:4 NO:78 D:59/1 EYÜP/ İSTANBUL Tel: 90 212 467 0619 Vergi Dairesi: ESENLER VKN: 9000068418 ÖzelleştirmeNo: (| Fatura No: m SOS > ETİN: d433c9af-3ef1-4591-9baf-5817e1106del | | Öğ | | arom | serverler [Wal amet Tan [| 2 [1 Adet{ i | | 750,007 a İNAKLİYEBEDEİ [1 Adet{ — — 67,7671] | 5 __|naKLive peDeLi [a 918,00] Gizem | & | — zem | 7. | ezen | GÜMRÜK 2.İSKELE gi İŞLEMLERİ 1 © 741,00000000TL 918,00) 133,38 741,00 TL p_[NaKLive ooo oO| | zenan | ER HO İTEMİNAT BEDELİ Adet{_2.301,00000000TL| “| — | Hi | 12. — — | 135,001] | 750,007 GÜMRÜK 2.İSKELE 9 İŞLEMLERİ 1 Adet 741,00000000 TL % 18,00 133,38 no 741,00 TL 15 __[NAKLiVE BEDELY_ [i | — — | 143350071 16 İTEMİNAT BEDELİ | 2.30100 71 a | — — 135,001] | 750,00 TL 18 [i Adet{ | 7H 19 Adet| |. GÜMRÜK 2.İSKELE 2i BEDELİ [i — 230,00 71 22 | | 23_[mesaiUcreri [i Adet| — — 135,00 TL] | 750,007 24 |i Ader! | Gem 71 Toplam İskonto Ödenecek Tutar YALNIZ #YÜZİKİBİNALTIYÜZOTUZDÖRTTÜRKLİRASIDÖRTKURUŞ# 26 HAFTA PİYASA ret j GENEL: İLGİLİ TAŞIMA ALT TEDARİKÇİMİZ (PİYASA ARAÇLARI ) TARAFINDAN YAPILMIŞTIR TEVKİFAT KANUNU KAPSAMI İÇERİSİNDE YER ALMAMAKTADIR. + 01.07.2021 TARİHİ İTİBARİYLE TEVKİFATLI FATURA DÜZENLENEBİLM GEREKMEKTEDİR."
        },
        "regex": {
            "tarih": [
                "01.07.2021"
            ],
            "para": [
                "918,00",
                "133,38",
                "741,00 TL",
                "18,00",
                "750,00 TL",
                "230,00",
                "135,00 TL"
            ],
            "iban": [],
            "fatura_no": [],
            "vergi_no": [
                "9000068418"
            ],
            "tc_no": [],
            "telefon": [
                "90 212 467 0619"
            ],
            "email": [
                "fatura@ACME.com"
            ],
            "fatura_tipi": [
                "e-FATURA"
            ],
            "kdv_orani": [],
            "ettn": [],
            "mersis_no": [],
            "ticaret_sicil": [],
            "musteri_no": [],
            "mal_hizmet_kodu": [],
            "alici_ad_soyad": [
                "TEST MÜŞTERİSİ DEFTERDAR"
            ],
            "alici_adres": [],
            "urun_aciklama": [],
            "urun_miktar": [
                "1",
                "19"
            ],
            "birim_fiyat": [],
            "odeme_sekli": [],
            "kargo_bilgisi": [],
            "siparis_no": [],
            "fatura_tarihi": [],
            "duzenleme_saati": [],
            "satici_vkn": [],
            "alici_vkn": [],
            "odenecek_tutar": [],
            "doviz_kuru": [],
            "para_birimi": [
                "TL"
            ]
        },
        "structured": {
            "satici_vergi_dairesi": "ESENLER VKN",
            "satici_vergi_numarasi": "9000068418",
            "satici_telefon": "1111",
            "satici_email": "fatura@ACME.com",
            "alici_firma_unvani": "TEST MÜŞTERİSİ DEFTERDAR MAH.OTAKCILAR CADDESİ.FLATOFİS İSTANBUL İŞ MERK.K",
            "alici_email": "fatura@ACME.com",
            "alici_telefon": "1111",
            "genel_toplam": "918,00",
            "tarih": "01.07.2021",
            "para": "918,00",
            "vergi_no": "9000068418",
            "telefon": "90 212 467 0619",
            "email": "fatura@ACME.com",
            "kalemler": [],
            "fatura_tarihi": "01-07-2021"
        }
    }
]